Workbook
Name Moneda1: [1]Parametros!$B$17

Sheet 1 Estudiantes
A1: # de paralelos | B1: ='2 Tasa de Retención'!C5 -> 1 | C1: =B1+'2 Tasa de Retención'!D5 -> 3 | D1: =C1+'2 Tasa de Retención'!$C$5 -> 4 | E1: =D1+'2 Tasa de Retención'!$D$5 -> 6 | F1: =E1+'2 Tasa de Retención'!$C$5 -> 7 | G1: =F1+'2 Tasa de Retención'!$D$5 -> 9 | H1: =G1+'2 Tasa de Retención'!$C$5 -> 10 | I1: =H1+'2 Tasa de Retención'!$D$5 -> 12
A3: AÑO | B3: 2023 | C3: 2023 | D3: 2024 | E3: 2024 | F3: 2025 | G3: 2025 | H3: 2026 | I3: 2026
A4: 1 CICLO | B4: ='2 Tasa de Retención'!C10*'2 Tasa de Retención'!C5 -> 30 | C4: =+'2 Tasa de Retención'!D10*'2 Tasa de Retención'!D5 -> 60 | D4: =+B4 -> 30 | E4: =+C4 -> 60 | F4: =+D4 -> 30 | G4: =+E4 -> 60 | H4: =+F4 -> 30 | I4: =+G4 -> 60 | J4: Ret. 65% | S4: =+K4/35 -> 0 | T4: 7
A5: 2 CICLO | C5: =+'2 Tasa de Retención'!E10*'2 Tasa de Retención'!C5 -> 26.94 | D5: =+'2 Tasa de Retención'!F10*'2 Tasa de Retención'!D5 -> 53.88 | E5: =+C5 -> 26.94 | F5: =+D5 -> 53.88 | G5: =+E5 -> 26.94 | H5: =+F5 -> 53.88 | I5: =+E5 -> 26.94 | S5: =+K5/35 -> 0 | T5: 3 | X5: 13565 | Y5: 15553
A6: 3 CICLO | D6: =+'2 Tasa de Retención'!G10*'2 Tasa de Retención'!C5 -> 24.19212 | E6: =+'2 Tasa de Retención'!H10*'2 Tasa de Retención'!D5 -> 48.38424 | F6: =+D6 -> 24.19212 | G6: =+E6 -> 48.38424 | H6: =+F6 -> 24.19212 | I6: =+G6 -> 48.38424 | S6: =+K6/35 -> 0 | T6: 3 | V6: =3*1.5 -> 4.5 | X6: =+X5*2.2% -> 298.43
A7: 4 CICLO | E7: =+'2 Tasa de Retención'!I10*'2 Tasa de Retención'!C5 -> 21.724524 | F7: =+'2 Tasa de Retención'!J10*'2 Tasa de Retención'!D5 -> 43.449048 | G7: =+E7 -> 21.724524 | H7: =+F7 -> 43.449048 | I7: =+G7 -> 21.724524 | S7: =+K7/35 -> 0 | T7: 2 | V7: =+V6*16 -> 72 | X7: =+X6*15.7% -> 46.85351
A8: 5 CICLO | F8: =+'2 Tasa de Retención'!K10*'2 Tasa de Retención'!C5 -> 19.508622 | G8: =+'2 Tasa de Retención'!L10*'2 Tasa de Retención'!D5 -> 39.017245 | H8: =+F8 -> 19.508622 | I8: =+G8 -> 39.017245 | J8: Titu.67% | S8: =+K8/35 -> 0 | T8: 4
A9: 6 CICLO | G9: =+'2 Tasa de Retención'!M10*'2 Tasa de Retención'!C5 -> 18.482469 | H9: =+'2 Tasa de Retención'!N10*'2 Tasa de Retención'!D5 -> 36.964938 | I9: =+G9 -> 18.482469
A10: 7 CICLO | H10: =+'2 Tasa de Retención'!O10*'2 Tasa de Retención'!C5 -> 17.510291 | I10: =+'2 Tasa de Retención'!P10*'2 Tasa de Retención'!D5 -> 35.020582
A11: 8 CICLO | I11: =+'2 Tasa de Retención'!Q10*'2 Tasa de Retención'!C5 -> 17.510291 | S11: =+K11/35 -> 0 | T11: 2
A12: Total Nº de Estudiantes | B12: =SUM(B4:B11) -> 30 | C12: =SUM(C4:C11) -> 86.94 | D12: =SUM(D4:D11) -> 108.07212 | E12: =SUM(E4:E11) -> 157.04876 | F12: =SUM(F4:F11) -> 171.02979 | G12: =SUM(G4:G11) -> 214.54848 | H12: =SUM(H4:H11) -> 225.50502 | I12: =SUM(I4:I11) -> 267.07935
A15: Nº de Horas Clase Docencia Asistida x semana Acumuladas | B15: =+B17 -> 18 | C15: =+B15+C17 -> 60 | D15: =+C15+D17 -> 80 | E15: =+D15+E17 -> 122 | F15: =+E15+F17 -> 143 | G15: =+F15+G17 -> 183 | H15: =+G15+H17 -> 202 | I15: =+H15+I17 -> 234
A16: N° de Horas con Docencia Asistida SEMESTRAL | B16: 288 | C16: 336 | D16: 320 | E16: 336 | F16: 336 | G16: 320 | H16: 304 | I16: =256 -> 256 | K16: =SUM(B16:I16) -> 2496
A17: N° Horas Docencia Asistida por semana y por paralelos | B17: =+B16/16*'2 Tasa de Retención'!$C$5 -> 18 | C17: =(+C16/16)*'2 Tasa de Retención'!$D$5 -> 42 | D17: =(+D16/16)*'2 Tasa de Retención'!$C$5 -> 20 | E17: =(+E16/16)*'2 Tasa de Retención'!$D$5 -> 42 | F17: =(+F16/16)*'2 Tasa de Retención'!$C$5 -> 21 | G17: =(+G16/16)*'2 Tasa de Retención'!$D$5 -> 40 | H17: =(+H16/16)*'2 Tasa de Retención'!$C$5 -> 19 | I17: =(+I16/16)*'2 Tasa de Retención'!$D$5 -> 32
A19: Nº de Horas Clase Aplicac. Práctica x semana Acumuladas | B19: =+B21 -> 10 | C19: =+B19+C21 -> 32 | D19: =+C19+D21 -> 44 | E19: =+D19+E21 -> 70 | F19: =+E19+F21 -> 85 | G19: =+F19+G21 -> 118 | H19: =+G19+H21 -> 139 | I19: =+H19+I21 -> 189 | J19: Relación
A20: N° Horas Aplicación Práctica SEMESTRAL | B20: 160 | C20: 176 | D20: 192 | E20: 208 | F20: 240 | G20: =224+16+24 -> 264 | H20: =240+96 -> 336 | I20: =160+240 -> 400 | J20: 0 | K20: =SUM(B20:I20) -> 1976
A21: N° Horas Aplicación Práctica por semana y por paralelos | B21: =+B20/16*'2 Tasa de Retención'!$C$5 -> 10 | C21: =(+C20/16)*'2 Tasa de Retención'!$D$5 -> 22 | D21: =(+D20/16)*'2 Tasa de Retención'!$C$5 -> 12 | E21: =(+E20/16)*'2 Tasa de Retención'!$D$5 -> 26 | F21: =(+F20/16)*'2 Tasa de Retención'!$C$5 -> 15 | G21: =(+G20/16)*'2 Tasa de Retención'!$D$5 -> 33 | H21: =(+H20/16)*'2 Tasa de Retención'!$C$5 -> 21 | I21: =(+I20/16)*'2 Tasa de Retención'!$D$5 -> 50
J23: Horas Docente
A24: Docentes Requeridos | B24: =+B15/$J$24 -> 1 | C24: =+C15/$J$24 -> 3.3333333 | D24: =+D15/$J$24 -> 4.4444444 | E24: =+E15/$J$24 -> 6.7777778 | F24: =+F15/$J$24 -> 7.9444444 | G24: =+G15/$J$24 -> 10.166667 | H24: =+H15/$J$24 -> 11.222222 | I24: =+I15/$J$24 -> 13 | J24: 18
A25: Tiempo Completo PhD | B25: =+B26*0.4 -> 0.24 | C25: =+C26*0.4 -> 0.8 | D25: =+D26*0.4 -> 1.0666667 | E25: =+E26*0.4 -> 1.6266667 | F25: =+F26*0.4 -> 1.9066667 | G25: =+G26*0.4 -> 2.44 | H25: =+H26*0.4 -> 2.6933333 | I25: =+I26*0.4 -> 3.12
A26: Tiempo Completo Mgs. | B26: =+B24*0.6 -> 0.6 | C26: =+C24*0.6 -> 2 | D26: =+D24*0.6 -> 2.6666667 | E26: =+E24*0.6 -> 4.0666667 | F26: =+F24*0.6 -> 4.7666667 | G26: =+G24*0.6 -> 6.1 | H26: =+H24*0.6 -> 6.7333333 | I26: =+I24*0.6 -> 7.8
A27: Medio Tiempo
A28: Tiempo Parcial | B28: =+B24-B26-B25 -> 0.16 | C28: =+C24-C26-C25 -> 0.53333333 | D28: =+D24-D26-D25 -> 0.71111111 | E28: =+E24-E26-E25 -> 1.0844444 | F28: =+F24-F26-F25 -> 1.2711111 | G28: =+G24-G26-G25 -> 1.6266667 | H28: =+H24-H26-H25 -> 1.7955556 | I28: =+I24-I26-I25 -> 2.08
J29: Horas Tecnico
A30: Ocasional Tipo 2 (Técnico Docente) | B30: =+B19/$J$30 -> 0.25 | C30: =+C19/$J$30 -> 0.8 | D30: =+D19/$J$30 -> 1.1 | E30: =+E19/$J$30 -> 1.75 | F30: =+F19/$J$30 -> 2.125 | G30: =+G19/$J$30 -> 2.95 | H30: =+H19/$J$30 -> 3.475 | I30: =+I19/$J$30 -> 4.725 | J30: 40

Sheet Hoja1
B1: PROYECCION DE ACTIVOS
B2: CUENCA | C2: CUENCA | D2: AZOGUES | E2: CAÑAR | F2: TRONCAL | G2: MACAS | H2: EAD
B3: ACTIVOS AULAS | C3: 13 | D3: 9 | E3: 9 | F3: 9 | G3: 9 | H3: 9
B4: MESAS | C4: =13*25 -> 325 | D4: =9*25 -> 225 | E4: =9*25 -> 225 | F4: =9*25 -> 225 | G4: =9*25 -> 225 | H4: =9*25 -> 225
B5: SILLAS | C5: =+C4 -> 325 | D5: =+D4 -> 225 | E5: =+E4 -> 225 | F5: =+F4 -> 225 | G5: =+G4 -> 225 | H5: =+H4 -> 225 | L5: =54*6 -> 324
B6: PROYECTORES | C6: 13 | D6: =+D3 -> 9 | E6: =+E3 -> 9 | F6: =+F3 -> 9 | G6: =+G3 -> 9 | H6: =+H3 -> 9
B7: PANTALLAS | C7: 13 | D7: =+D3 -> 9 | E7: =+E3 -> 9 | F7: =+F3 -> 9 | G7: =+G3 -> 9 | H7: =+H3 -> 9 | L7: =800/50 -> 16
B8: PISARRAS | C8: 13 | D8: =+D3 -> 9 | E8: =+E3 -> 9 | F8: =+F3 -> 9 | G8: =+G3 -> 9 | H8: =+H3 -> 9 | L8: =16*20 -> 320 | M8: PRESE | N8: =320*9 -> 2880
B9: UTILES DIDACTICOS | L9: =+L7*30 -> 480 | M9: NO PRE | N9: =+N8/13 -> 221.53846
B10: SUMINISTROS DOCENTE | L10: =SUM(L8:L9) -> 800 | N10: =+N9/9 -> 24.615385
B11: CUMPUTADOR | L11: 9 | N11: =+N10*60% -> 14.769231 | O11: 2180 | P11: =+O11*N11 -> 32196.923
B12: MODULO DE TRABAJO | L12: =+L10*L11 -> 7200 | N12: =+N10-N11 -> 9.8461538 | O12: =+O11/2 -> 1090 | P12: =+O12*N12 -> 10732.308
B13: TELEFONO | P13: =SUM(P11:P12) -> 42929.231
B14: IMPRESORA | P14: =+P13*12 -> 515150.77
B15: ADMINISTRACION | P15: =+P14*40% -> 206060.31
B16: CUMPUTADOR | P16: =SUM(P14:P15) -> 721211.08
B17: MODULO DE TRABAJO | P17: =+P16*20% -> 144242.22
B18: TELEFONO | P18: =SUM(P16:P17) -> 865453.29 | Q18: SUELDOS APROX
B19: IMPRESORA | L19: =25*9 -> 225 | M19: =180*14 -> 2520 | N19: =+M19*L19 -> 567000
B20: ARCHIVADORES
B21: OTROS MUEBLES
B22: SECRETARIA | L22: =320/15 -> 21.333333
B23: CUMPUTADOR
B24: MODULO DE TRABAJO
B25: TELEFONO
B26: IMPRESORA
B27: ARCHIVADORES
B28: OTROS MUEBLES
B29: BIBLIOTECA
B30: CUMPUTADOR
B31: MODULO DE TRABAJO
B32: TELEFONO
B33: IMPRESORA
B34: ARCHIVADORES
... B49: OTROS MUEBLES

Sheet 2 Tasa de Retención
B1: SIMULACIÓN DEL COMPORTAMIENTO DE LA GRADUACIÓN | V1: SUMA | W1: PROM | X1: Tasa graduación
A2: tasa x ciclo | C2: 1° | D2: 2° | E2: 3° | K2: 4° | M2: 5° | P2: 6°
A3: 0.9474 | B3: N° alumnoss >>> | C3: 35 | D3: =+C3*A3 -> 33.159 | E3: =+D3*A3 -> 31.414837 | K3: =+E3*A3 -> 29.762416 | M3: =+K3*A3 -> 28.196913 | P3: =+M3*A3 -> 26.713755 | V3: =SUM(C3:T3) -> 184.24692 | W3: =+V3/9 -> 20.47188 | X3: 0.6657
C4: abr | D4: sep
B5: Paralelos >>> | C5: 1 | D5: 2
B6: SIMULACIÓN DEL COMPORTAMIENTO DE LA RETENCIÓN
C7: 1° | D7: 1° | E7: 2° | F7: 2° | G7: 3° | H7: 3° | I7: 4° | J7: 4° | K7: 5° | L7: 5° | M7: 6° | N7: 6° | O7: 7° | P7: 7° | Q7: 8°
B8: 0.898 | K8: 0.9474
P9: =+M9*B8 -> 0 | Q9: =+P9*C8 -> 0 | W9: Tasa de retención | AC9: =24/30 -> 0.8
B10: N° Alumnos >>> | C10: 30 | D10: 30 | E10: =+C10*B8 -> 26.94 | F10: =+D10*B8 -> 26.94 | G10: =+E10*B8 -> 24.19212 | H10: =+F10*B8 -> 24.19212 | I10: =+G10*B8 -> 21.724524 | J10: =+H10*B8 -> 21.724524 | K10: =+B8*I10 -> 19.508622 | L10: =+B8*J10 -> 19.508622 | M10: =+K10*K8 -> 18.482469 | N10: =+L10*K8 -> 18.482469 | O10: =+M10*K8 -> 17.510291 | P10: =+N10*K8 -> 17.510291 | Q10: =+O10 -> 17.510291 | V10: =SUM(C10:T10) -> 334.22634 | W10: =+V10/9 -> 37.13626 | X10: 0.65 | Y10: (Primero y arranque de 3° ciclo)
C11: Retención | K11: Graduación
M12: =+C10*0.64 -> 19.2 | S12: =+M12*0.283 -> 5.4336 | X12: 51
B13: NOTA: SE RECOMIENDA TOMAR LA SIMULACIÓN DE LA RETENCIÓN (ESTA INVOLUCRA A LAS DOS) | S13: =+M10*0.33 -> 6.0992147 | X13: 0
S14: 78 | X14: 78
J15: =+K10/C10 -> 0.65028741 | K15: =+Q10/K10 -> 0.89756676 | X15: 81
B16: REFERENCIA A LOS CRITERIOS DE ACREDITACIÓN: Indicador: Utilidad vs % de cumplimiento | J16: =+L10/D10 -> 0.65028741 | K16: =+P10/L10 -> 0.89756676
C18: GRADUACIÓN | K18: RETENCIÓN
C20: X | D20: Y | K20: X | M20: Y
C21: 0.001 | D21: 0 | K21: 0.1 | M21: 0.1 | N21: 0
C22: 14.9 | D22: 0 | K22: 59 | M22: 0.59
C23: 15 | D23: 1 | K23: 60 | M23: 1
C24: 60 | D24: 1 | K24: 70 | M24: 1
C25: 60.1 | D25: 0 | K25: 80 | M25: 1
C26: 100 | D26: 0 | K26: 100 | M26: 1

Sheet 3 Recursos físicos
A1: ACTIVOS FIJOS
A2: DESGLOSE DE SITUACIÓN INICIAL
A3: DESCRIPCIÓN | B3: CANTIDAD | C3: UNIDAD | D3: VALOR UNITARIO | E3: VALOR TOTAL
A4: Muebles y enseres | E4: =SUM(E5:E21) -> 0 | O4: 76853.06 | P4: =+O4/2 -> 38426.53
A5: Silla giratoria | B5: 0 | C5: UNI | D5: 192 | E5: =+D5*B5 -> 0 | O5: 123000 | P5: =+O5/2 -> 61500
A6: Silla de espera | B6: =+B5 -> 0 | C6: UNI | D6: 45 | E6: =+D6*B6 -> 0
A7: Archivador de madera | B7: =+B5 -> 0 | C7: UNI | D7: 150 | E7: =+D7*B7 -> 0
A8: Escritorio docentes | B8: =+B5 -> 0 | C8: UNI | D8: 306 | E8: =+D8*B8 -> 0
A9: Mesas de laboratorio | C9: UNI | D9: 250 | E9: =+D9*B9 -> 0
A10: Libros | C10: UNI | E10: =+D10*B10 -> 0
C11: UNI | D11: 60 | E11: =+D11*B11 -> 0
C12: UNI | D12: 30 | E12: =+D12*B12 -> 0
C13: UNI | D13: 150 | E13: =+D13*B13 -> 0
E14: =+D14*B14 -> 0
E15: =+D15*B15 -> 0
E16: =+D16*B16 -> 0
E17: =+D17*B17 -> 0
E18: =+D18*B18 -> 0
E19: =+D19*B19 -> 0
E20: =+D20*B20 -> 0
E21: =+D21*B21 -> 0
A22: Laboratorios y Equipos | E22: =SUM(E23:E39) -> 376.875
A23: Operatividad EVEA | B23: =+'1 Estudiantes'!B12 -> 30 | C23: UNI | D23: 7.5 | E23: =+B23*D23 -> 225
A24: Licencias, almacenamiento y webninar ZOOM | B24: =+'5 Demanda'!B20+10 -> 11.25 | C24: UNI | D24: 13.5 | E24: =+B24*D24 -> 151.875
A25: Laboratorio de Redes | C25: UNI | D25: 25000 | E25: =+B25*D25 -> 0
A26: Laboratorio de Redes | C26: UNI | D26: 25000 | E26: =+B26*D26 -> 0
C27: UNI | D27: 1105 | E27: =+B27*D27 -> 0
C28: UNI | D28: 1100 | E28: =+B28*D28 -> 0
A29: Equipo de audio | C29: UNI | D29: 80 | E29: =+B29*D29 -> 0
C30: UNI | D30: 1280 | E30: =+B30*D30 -> 0
E31: =+B31*D31 -> 0
E32: =+B32*D32 -> 0
E33: =+B33*D33 -> 0
E34: =+B34*D34 -> 0
E35: =+B35*D35 -> 0
E36: =+B36*D36 -> 0
E37: =+B37*D37 -> 0
E38: =+B38*D38 -> 0
E39: =+D39*B39*F39 -> 0
A40: Equipo de Computo | E40: =SUM(E41:E55) -> 1200
A41: Pizarra digital | C41: UNI | D41: 952 | E41: =+D41*B41 -> 0
A42: Perifericos | B42: =+B5 -> 0 | C42: UNI | D42: 66 | E42: =+D42*B42 -> 0
A43: Proyectores | B43: 0 | C43: UNI | D43: 750 | E43: =+D43*B43 -> 0
A44: Computador escritorio | B44: 0 | C44: UNI | D44: 675 | E44: =+D44*B44 -> 0
A45: Software | C45: UNI | E45: =+D45*B45 -> 0
A46: Computador portátil | B46: 1 | C46: UNI | D46: 1200 | E46: =+D46*B46 -> 1200
A47: Switch | C47: UNI | D47: 1500 | E47: =+D47*B47 -> 0
A48: Software (mantenimiento) | C48: UNI | E48: =+D48*B48 -> 0
E49: =+D49*B49 -> 0
E50: =+D50*B50 -> 0
E51: =+D51*B51 -> 0
E52: =+D52*B52 -> 0
E53: =+D53*B53 -> 0
E54: =+D54*B54 -> 0
E55: =+D55*B55 -> 0
A56: Equipo de Oficina | E56: =SUM(E57:E58) -> 0
A57: Teléfono | C57: UNI | D57: 100 | E57: =+D57*B57 -> 0
C58: UNI | E58: =+D58*B58 -> 0
E59: =+D59*B59 -> 0
E60: =+D60*B60 -> 0
A61: TOTAL | E61: =+E56+E40+E22+E4 -> 1576.875
A64: PROYECCION DE NECESIDADES EN UNIDADES
A65: DESCRIPCIÓN | B65: =+'1 Estudiantes'!B3 -> 2023 | C65: =+'1 Estudiantes'!C3 -> 2023 | D65: =+'1 Estudiantes'!D3 -> 2024 | E65: =+'1 Estudiantes'!E3 -> 2024 | F65: =+'1 Estudiantes'!F3 -> 2025 | G65: =+'1 Estudiantes'!G3 -> 2025 | H65: =+'1 Estudiantes'!H3 -> 2026 | I65: =+'1 Estudiantes'!I3 -> 2026
A66: =+A4 -> Muebles y enseres
A67: =+A5 -> Silla giratoria | C67: 0 | D67: 0 | E67: 0 | F67: 0 | G67: 0 | H67: 0 | I67: 0
A68: =+A6 -> Silla de espera | C68: =+C67 -> 0 | D68: =+D67 -> 0 | E68: =+E67 -> 0 | F68: =+F67 -> 0 | G68: =+G67 -> 0 | H68: =+H67 -> 0 | I68: =+I67 -> 0
A69: =+A7 -> Archivador de madera | C69: =+C68 -> 0 | D69: =+D68 -> 0 | E69: =+E68 -> 0 | F69: =+F68 -> 0 | G69: =+G68 -> 0 | H69: =+H68 -> 0 | I69: =+I68 -> 0
A70: =+A8 -> Escritorio docentes | C70: =+C69 -> 0 | D70: =+D69 -> 0 | E70: =+E69 -> 0 | F70: =+F69 -> 0 | G70: =+G69 -> 0 | H70: =+H69 -> 0 | I70: =+I69 -> 0
A71: =+A9 -> Mesas de laboratorio
A72: =+A10 -> Libros
A73: =+A11 -> 0
A74: =+A12 -> 0
A75: =+A13 -> 0
A76: =+A14 -> 0
A77: =+A15 -> 0
A78: =+A16 -> 0
A79: =+A17 -> 0
A80: =+A18 -> 0
A81: =+A19 -> 0
A82: =+A20 -> 0
... A84: =+A22 -> Laboratorios y Equipos
A85: =+A23 -> Operatividad EVEA | C85: =+'1 Estudiantes'!C12 -> 86.94 | D85: =+'1 Estudiantes'!D12 -> 108.07212 | E85: =+'1 Estudiantes'!E12 -> 157.04876 | F85: =+'1 Estudiantes'!F12 -> 171.02979 | G85: =+'1 Estudiantes'!G12 -> 214.54848 | H85: =+'1 Estudiantes'!H12 -> 225.50502 | I85: =+'1 Estudiantes'!I12 -> 267.07935
A86: =+A24 -> Licencias, almacenamiento y webninar ZOOM | C86: =+'5 Demanda'!C20 -> 4.1333333 | D86: =+'5 Demanda'!D20 -> 5.5444444 | E86: =+'5 Demanda'!E20 -> 8.5277778 | F86: =+'5 Demanda'!F20 -> 10.069444 | G86: =+'5 Demanda'!G20 -> 13.116667 | H86: =+'5 Demanda'!H20 -> 14.697222 | I86: =+'5 Demanda'!I20 -> 17.725
A87: =+A25 -> Laboratorio de Redes | D87: 1
A88: =+A26 -> Laboratorio de Redes | E88: 1
A89: =+A27 -> 0
A90: =+A28 -> 0
A91: =+A29 -> Equipo de audio
A92: =+A30 -> 0
A93: =+A31 -> 0
A94: =+A32 -> 0
A95: =+A33 -> 0
A96: =+A34 -> 0
A97: =+A35 -> 0
A98: =+A36 -> 0
A99: =+A37 -> 0
A100: =+A38 -> 0
... A107: =+A45 -> Software
A108: =+A46 -> Computador portátil | C108: 0 | D108: 0 | E108: 0 | F108: 0 | G108: 0 | H108: 0 | I108: 0
A109: =+A47 -> Switch
...

Sheet 4 Inversión Inicial
A1: RESUMEN INVERSIÓN INICIAL
A2: TIPO DE INVERSIÓN | B2: VALOR | C2: MONTO TOTAL
A3: ACTIVOS DIFERIDOS | C3: =SUM(B4:B4) -> 300
A4: Permiso Municipal y Bomberos | B4: ='Amortización '!B3 -> 300
A5: ACTIVOS FIJOS | C5: =SUM(B6:B9) -> 1576.875
A6: =+'3 Recursos físicos'!A4 -> Muebles y enseres | B6: =+'3 Recursos físicos'!E4 -> 0
A7: =+'3 Recursos físicos'!A22 -> Laboratorios y Equipos | B7: =+'3 Recursos físicos'!E22 -> 376.875
A8: =+'3 Recursos físicos'!A40 -> Equipo de Computo | B8: =+'3 Recursos físicos'!E40 -> 1200
A9: =+'3 Recursos físicos'!A56 -> Equipo de Oficina | B9: =+'3 Recursos físicos'!E56 -> 0
A10: TOTAL ACTIVOS | C10: =+C3+C5 -> 1876.875
A11: CAPITAL DE TRABAJO (2 meses) | B11: =+'6 Capital de trabajo'!D48*2 -> 16163.628
A12: Imprevistos 5% | B12: =+B11*5% -> 808.18139
A13: TOTAL DE INVERSION INICIAL | C13: =+C10+B11+B12 -> 18848.684

Sheet 6 Capital de trabajo
A1: CAPITAL DE TRABAJO
A2: CANTIDAD | B2: CONCEPTO | C2: VALOR UNITARIO | D2: VALOR MENSUAL
A3: GASTOS DE SERVICIO Y ADMINISTRACIÓN
A4: =+'7 Sueldos'!C3 -> 1 | B4: Decano | C4: 3880 | D4: =+'7 Sueldos'!K3/6 -> 490.87213
A5: =+'7 Sueldos'!C4 -> 1 | B5: Subdecano | C5: 2880 | D5: =+'7 Sueldos'!K4/6 -> 365.17689
A6: =+'7 Sueldos'!C5 -> 1 | B6: Director de Carrera | C6: 2200 | D6: =+'7 Sueldos'!K5/6 -> 2936.8933
A7: =+'7 Sueldos'!C6 -> 1 | B7: Secretario | C7: 1000 | D7: =+'7 Sueldos'!K6/6 -> 128.86984
A8: =+'7 Sueldos'!C7 -> 1 | B8: Auxiliar de Secretaria | C8: 850 | D8: =+'7 Sueldos'!K7/6 -> 110.01556
A9: =+'7 Sueldos'!C8 -> 1 | B9: Coordinador | C9: 900 | D9: =+'7 Sueldos'!K8/6 -> 116.30032
A10: =+'7 Sueldos'!C9 -> 1 | B10: Bienestar Estudiantil | C10: 900 | D10: =+'7 Sueldos'!K9/6 -> 116.30032
A11: =+'7 Sueldos'!C10 -> 0.24 | B11: =+'1 Estudiantes'!A25 -> Tiempo Completo PhD | C11: 2800 | D11: =+'7 Sueldos'!K10/6 -> 894.9056
A12: =+'7 Sueldos'!C11 -> 0.6 | B12: =+'1 Estudiantes'!A26 -> Tiempo Completo Mgs. | C12: 1800 | D12: =+'7 Sueldos'!K11/6 -> 1445.384
A13: =+'7 Sueldos'!C12 -> 0 | B13: =+'1 Estudiantes'!A27 -> Medio Tiempo | C13: =+C12/2 -> 900 | D13: =+'7 Sueldos'!K12/6 -> 0 | E13: Valor Hora Clase | F13: 12
A14: =+'7 Sueldos'!C13 -> 0.16 | B14: =+'1 Estudiantes'!A28 -> Tiempo Parcial | C14: =+F13*F14 -> 432 | D14: =+'7 Sueldos'!K13/6 -> 96.557909 | E14: Horas clase/MES | F14: =9*4 -> 36
A15: =+'7 Sueldos'!C14 -> 0.25 | B15: =+'1 Estudiantes'!A30 -> Ocasional Tipo 2 (Técnico Docente) | C15: 1350 | D15: =+'7 Sueldos'!K14/6 -> 453.76583
A16: =+'7 Sueldos'!C15 -> 1 | B16: Bibliotecario | C16: 800 | D16: =+'7 Sueldos'!K15/6 -> 103.73079
A17: =+'7 Sueldos'!C16 -> 2 | B17: Auxiliar de Servicio | C17: 450 | D17: =+'7 Sueldos'!K16/6 -> 119.47492
A18: =+'7 Sueldos'!C17 -> 1 | B18: Guardia | C18: 650 | D18: =+'7 Sueldos'!K17/6 -> 84.876508
B19: TOTAL | D19: =SUM(D4:D18) -> 7463.1239
A20: MATERIALES Y SUMINISTROS
A21: =+'5 Demanda'!B53 -> 6 | B21: Resma de papel bond de 75 gramos | C21: 3.25 | D21: =+C21*A21 -> 19.5
A22: =+'5 Demanda'!B54 -> 0.6 | B22: Cartuchos de impresora (Color) | C22: 50 | D22: =+C22*A22 -> 30
A23: =+'5 Demanda'!B55 -> 0.6 | B23: Cartuchos de impresora (Negro) | C23: 40 | D23: =+C23*A23 -> 24
A24: =+'5 Demanda'!B56 -> 60 | B24: Carpetas de cartón | C24: 1 | D24: =+C24*A24 -> 60
A25: =+'5 Demanda'!B57 -> 30 | B25: Porta files | C25: 2 | D25: =+C25*A25 -> 60
A26: =+'5 Demanda'!B58 -> 30 | B26: Esferos, micro minas, lápiz, borradores, correctores | C26: 0.25 | D26: =+C26*A26 -> 7.5
A27: =+'5 Demanda'!B59 -> 0.6 | B27: Grapas, clips (CAJA) | C27: 1 | D27: =+C27*A27 -> 0.6
B28: TOTAL | D28: =SUM(D20:D27) -> 201.6
A29: SUMINISTROS DE ASEO Y LIMPIEZA
A30: =+'5 Demanda'!B61 -> 0.9 | B30: Desinfectante (Galón) | C30: 4 | D30: =+C30*A30 -> 3.6
A31: =+'5 Demanda'!B62 -> 1.08 | B31: Jabón Líquido (Galón) | C31: 3 | D31: =+C31*A31 -> 3.24
A32: =+'5 Demanda'!B63 -> 23.4 | B32: Papel Higiénico (Rollo Grande) | C32: 10.5 | D32: =+C32*A32 -> 245.7
A33: =+'5 Demanda'!B64 -> 2 | B33: Escoba | C33: 10.5 | D33: =+C33*A33 -> 21
A34: =+'5 Demanda'!B65 -> 6 | B34: Paquete de Fundas de Basura | C34: 0.8 | D34: =+C34*A34 -> 4.8
A35: =+'5 Demanda'!B66 -> 3 | B35: Trapeador | C35: 2.5 | D35: =+C35*A35 -> 7.5
A36: =+'5 Demanda'!B67 -> 0.9 | B36: Cloro (Galón) | C36: 2.5 | D36: =+C36*A36 -> 2.25
B37: TOTAL | D37: =SUM(D30:D35) -> 285.84
A38: ACCESORIOS Y MATERIALES
A39: 1 | D39: =+C39*A39 -> 0
A40: =+'5 Demanda'!B69 -> 5.25 | B40: Grapadora | C40: 15 | D40: =+C40*A40 -> 78.75
A41: =+'5 Demanda'!B70 -> 5.25 | B41: Perforadora | C41: 10 | D41: =+C41*A41 -> 52.5
A42: =+'5 Demanda'!B72 -> 0 | D42: =+C42*A42 -> 0
A43: =+'5 Demanda'!B73 -> 0 | D43: =+C43*A43 -> 0
A44: =+'5 Demanda'!B74 -> 0 | D44: =+C44*A44 -> 0
A45: =+'5 Demanda'!B75 -> 0 | D45: =+C45*A45 -> 0
A46: =+'5 Demanda'!B76 -> 0 | D46: =+C46*A46 -> 0
B47: TOTAL | D47: =SUM(D39:D46) -> 131.25
A48: TOTAL | D48: =SUM(+D47+D37+D28+D19) -> 8081.8139

Sheet Depreciación
A1: DESCRIPCION | B1: VALOR | C1: VALOR RESIDUAL | D1: TIEMPO | E1: DEPRECIACION | N1: DEPRECIACION ACUMULADA
E2: =+'1 Estudiantes'!B3 -> 2023 | F2: =+'1 Estudiantes'!C3 -> 2023 | G2: =+'1 Estudiantes'!D3 -> 2024 | H2: =+'1 Estudiantes'!E3 -> 2024 | I2: =+'1 Estudiantes'!F3 -> 2025 | J2: =+'1 Estudiantes'!G3 -> 2025 | K2: =+'1 Estudiantes'!H3 -> 2026 | L2: =+'1 Estudiantes'!I3 -> 2026 | N2: =+F2 -> 2023 | O2: =+G2 -> 2024 | P2: =+H2 -> 2024 | Q2: =+I2 -> 2025 | R2: =+J2 -> 2025 | S2: =+K2 -> 2026 | T2: =+L2 -> 2026
A3: =+'3 Recursos físicos'!A4 -> Muebles y enseres | E3: =SUM(E4:E20) -> 0 | F3: =SUM(F4:F20) -> 0 | G3: =SUM(G4:G20) -> 0 | H3: =SUM(H4:H20) -> 0 | I3: =SUM(I4:I20) -> 0 | J3: =SUM(J4:J20) -> 0 | K3: =SUM(K4:K20) -> 0 | L3: =SUM(L4:L20) -> 0 | N3: =SUM(N4:N20) -> 0 | O3: =SUM(O4:O20) -> 0 | P3: =SUM(P4:P20) -> 0 | Q3: =SUM(Q4:Q20) -> 0 | R3: =SUM(R4:R20) -> 0 | S3: =SUM(S4:S20) -> 0 | T3: =SUM(T4:T20) -> 0
A4: =+'3 Recursos físicos'!A5 -> Silla giratoria | B4: =+'3 Recursos físicos'!E5 -> 0 | C4: =+B4*5% -> 0 | D4: 10 | E4: =+(B4-C4)/D4 -> 0 | F4: =+E4/2 -> 0 | G4: =+F4 -> 0 | H4: =+G4 -> 0 | I4: =+H4 -> 0 | J4: =+I4 -> 0 | K4: =+J4 -> 0 | L4: =+K4 -> 0 | N4: =+G4+(('3 Recursos físicos'!C127*0.95)/Depreciación!$D4) -> 0 | O4: =+H4+(('3 Recursos físicos'!D127*0.95)/Depreciación!$D4) -> 0 | P4: =+I4+(('3 Recursos físicos'!E127*0.95)/Depreciación!$D4) -> 0 | Q4: =+J4+(('3 Recursos físicos'!F127*0.95)/Depreciación!$D4) -> 0 | R4: =+K4+(('3 Recursos físicos'!G127*0.95)/Depreciación!$D4) -> 0 | S4: =+L4+(('3 Recursos físicos'!H127*0.95)/Depreciación!$D4) -> 0 | T4: =+F4+(('3 Recursos físicos'!I127*0.95)/Depreciación!$D4) -> 0
A5: =+'3 Recursos físicos'!A6 -> Silla de espera | B5: =+'3 Recursos físicos'!E6 -> 0 | C5: =+B5*5% -> 0 | D5: 10 | E5: =+(B5-C5)/D5 -> 0 | F5: =+E5/2 -> 0 | G5: =+F5 -> 0 | H5: =+G5 -> 0 | I5: =+H5 -> 0 | J5: =+I5 -> 0 | K5: =+J5 -> 0 | L5: =+K5 -> 0 | N5: =+G5+(('3 Recursos físicos'!C128*0.95)/Depreciación!$D5) -> 0 | O5: =+H5+(('3 Recursos físicos'!D128*0.95)/Depreciación!$D5) -> 0 | P5: =+I5+(('3 Recursos físicos'!E128*0.95)/Depreciación!$D5) -> 0 | Q5: =+J5+(('3 Recursos físicos'!F128*0.95)/Depreciación!$D5) -> 0 | R5: =+K5+(('3 Recursos físicos'!G128*0.95)/Depreciación!$D5) -> 0 | S5: =+L5+(('3 Recursos físicos'!H128*0.95)/Depreciación!$D5) -> 0 | T5: =+F5+(('3 Recursos físicos'!I128*0.95)/Depreciación!$D5) -> 0
A6: =+'3 Recursos físicos'!A7 -> Archivador de madera | B6: =+'3 Recursos físicos'!E7 -> 0 | C6: =+B6*5% -> 0 | D6: 10 | E6: =+(B6-C6)/D6 -> 0 | F6: =+E6/2 -> 0 | G6: =+F6 -> 0 | H6: =+G6 -> 0 | I6: =+H6 -> 0 | J6: =+I6 -> 0 | K6: =+J6 -> 0 | L6: =+K6 -> 0 | N6: =+G6+(('3 Recursos físicos'!C129*0.95)/Depreciación!$D6) -> 0 | O6: =+H6+(('3 Recursos físicos'!D129*0.95)/Depreciación!$D6) -> 0 | P6: =+I6+(('3 Recursos físicos'!E129*0.95)/Depreciación!$D6) -> 0 | Q6: =+J6+(('3 Recursos físicos'!F129*0.95)/Depreciación!$D6) -> 0 | R6: =+K6+(('3 Recursos físicos'!G129*0.95)/Depreciación!$D6) -> 0 | S6: =+L6+(('3 Recursos físicos'!H129*0.95)/Depreciación!$D6) -> 0 | T6: =+F6+(('3 Recursos físicos'!I129*0.95)/Depreciación!$D6) -> 0
A7: =+'3 Recursos físicos'!A8 -> Escritorio docentes | B7: =+'3 Recursos físicos'!E8 -> 0 | C7: =+B7*5% -> 0 | D7: 10 | E7: =+(B7-C7)/D7 -> 0 | F7: =+E7/2 -> 0 | G7: =+F7 -> 0 | H7: =+G7 -> 0 | I7: =+H7 -> 0 | J7: =+I7 -> 0 | K7: =+J7 -> 0 | L7: =+K7 -> 0 | N7: =+G7+(('3 Recursos físicos'!C130*0.95)/Depreciación!$D7) -> 0 | O7: =+H7+(('3 Recursos físicos'!D130*0.95)/Depreciación!$D7) -> 0 | P7: =+I7+(('3 Recursos físicos'!E130*0.95)/Depreciación!$D7) -> 0 | Q7: =+J7+(('3 Recursos físicos'!F130*0.95)/Depreciación!$D7) -> 0 | R7: =+K7+(('3 Recursos físicos'!G130*0.95)/Depreciación!$D7) -> 0 | S7: =+L7+(('3 Recursos físicos'!H130*0.95)/Depreciación!$D7) -> 0 | T7: =+F7+(('3 Recursos físicos'!I130*0.95)/Depreciación!$D7) -> 0
A8: =+'3 Recursos físicos'!A9 -> Mesas de laboratorio | B8: =+'3 Recursos físicos'!E9 -> 0 | C8: =+B8*5% -> 0 | D8: 10 | E8: =+(B8-C8)/D8 -> 0 | F8: =+E8/2 -> 0 | G8: =+F8 -> 0 | H8: =+G8 -> 0 | I8: =+H8 -> 0 | J8: =+I8 -> 0 | K8: =+J8 -> 0 | L8: =+K8 -> 0 | N8: =+G8+(('3 Recursos físicos'!C131*0.95)/Depreciación!$D8) -> 0 | O8: =+H8+(('3 Recursos físicos'!D131*0.95)/Depreciación!$D8) -> 0 | P8: =+I8+(('3 Recursos físicos'!E131*0.95)/Depreciación!$D8) -> 0 | Q8: =+J8+(('3 Recursos físicos'!F131*0.95)/Depreciación!$D8) -> 0 | R8: =+K8+(('3 Recursos físicos'!G131*0.95)/Depreciación!$D8) -> 0 | S8: =+L8+(('3 Recursos físicos'!H131*0.95)/Depreciación!$D8) -> 0 | T8: =+F8+(('3 Recursos físicos'!I131*0.95)/Depreciación!$D8) -> 0
A9: =+'3 Recursos físicos'!A10 -> Libros | B9: =+'3 Recursos físicos'!E10 -> 0 | C9: =+B9*5% -> 0 | D9: 10 | E9: =+(B9-C9)/D9 -> 0 | F9: =+E9/2 -> 0 | G9: =+F9 -> 0 | H9: =+G9 -> 0 | I9: =+H9 -> 0 | J9: =+I9 -> 0 | K9: =+J9 -> 0 | L9: =+K9 -> 0 | N9: =+G9+(('3 Recursos físicos'!C132*0.95)/Depreciación!$D9) -> 0 | O9: =+H9+(('3 Recursos físicos'!D132*0.95)/Depreciación!$D9) -> 0 | P9: =+I9+(('3 Recursos físicos'!E132*0.95)/Depreciación!$D9) -> 0 | Q9: =+J9+(('3 Recursos físicos'!F132*0.95)/Depreciación!$D9) -> 0 | R9: =+K9+(('3 Recursos físicos'!G132*0.95)/Depreciación!$D9) -> 0 | S9: =+L9+(('3 Recursos físicos'!H132*0.95)/Depreciación!$D9) -> 0 | T9: =+F9+(('3 Recursos físicos'!I132*0.95)/Depreciación!$D9) -> 0
A10: =+'3 Recursos físicos'!#REF! -> #REF! | B10: =+'3 Recursos físicos'!E11 -> 0 | C10: =+B10*5% -> 0 | D10: 1 | E10: =+(B10-C10)/D10 -> 0 | F10: =+E10/2 -> 0 | G10: =+F10 -> 0 | H10: =+G10 -> 0 | I10: =+H10 -> 0 | J10: =+I10 -> 0 | K10: =+J10 -> 0 | L10: =+K10 -> 0 | N10: =+G10+(('3 Recursos físicos'!C133*0.95)/Depreciación!$D10) -> 0 | O10: =+H10+(('3 Recursos físicos'!D133*0.95)/Depreciación!$D10) -> 0 | P10: =+I10+(('3 Recursos físicos'!E133*0.95)/Depreciación!$D10) -> 0 | Q10: =+J10+(('3 Recursos físicos'!F133*0.95)/Depreciación!$D10) -> 0 | R10: =+K10+(('3 Recursos físicos'!G133*0.95)/Depreciación!$D10) -> 0 | S10: =+L10+(('3 Recursos físicos'!H133*0.95)/Depreciación!$D10) -> 0 | T10: =+F10+(('3 Recursos físicos'!I133*0.95)/Depreciación!$D10) -> 0
A11: =+'3 Recursos físicos'!#REF! -> #REF! | B11: =+'3 Recursos físicos'!E12 -> 0 | C11: =+B11*5% -> 0 | D11: 10 | E11: =+(B11-C11)/D11 -> 0 | F11: =+E11/2 -> 0 | G11: =+F11 -> 0 | H11: =+G11 -> 0 | I11: =+H11 -> 0 | J11: =+I11 -> 0 | K11: =+J11 -> 0 | L11: =+K11 -> 0 | N11: =+G11+(('3 Recursos físicos'!C134*0.95)/Depreciación!$D11) -> 0 | O11: =+H11+(('3 Recursos físicos'!D134*0.95)/Depreciación!$D11) -> 0 | P11: =+I11+(('3 Recursos físicos'!E134*0.95)/Depreciación!$D11) -> 0 | Q11: =+J11+(('3 Recursos físicos'!F134*0.95)/Depreciación!$D11) -> 0 | R11: =+K11+(('3 Recursos físicos'!G134*0.95)/Depreciación!$D11) -> 0 | S11: =+L11+(('3 Recursos físicos'!H134*0.95)/Depreciación!$D11) -> 0 | T11: =+F11+(('3 Recursos físicos'!I134*0.95)/Depreciación!$D11) -> 0
A12: =+'3 Recursos físicos'!#REF! -> #REF! | B12: =+'3 Recursos físicos'!E13 -> 0 | C12: =+B12*5% -> 0 | D12: 10 | E12: =+(B12-C12)/D12 -> 0 | F12: =+E12/2 -> 0 | G12: =+F12 -> 0 | H12: =+G12 -> 0 | I12: =+H12 -> 0 | J12: =+I12 -> 0 | K12: =+J12 -> 0 | L12: =+K12 -> 0 | N12: =+G12+(('3 Recursos físicos'!C135*0.95)/Depreciación!$D12) -> 0 | O12: =+H12+(('3 Recursos físicos'!D135*0.95)/Depreciación!$D12) -> 0 | P12: =+I12+(('3 Recursos físicos'!E135*0.95)/Depreciación!$D12) -> 0 | Q12: =+J12+(('3 Recursos físicos'!F135*0.95)/Depreciación!$D12) -> 0 | R12: =+K12+(('3 Recursos físicos'!G135*0.95)/Depreciación!$D12) -> 0 | S12: =+L12+(('3 Recursos físicos'!H135*0.95)/Depreciación!$D12) -> 0 | T12: =+F12+(('3 Recursos físicos'!I135*0.95)/Depreciación!$D12) -> 0
A13: =+'3 Recursos físicos'!#REF! -> #REF! | B13: =+'3 Recursos físicos'!E14 -> 0 | C13: =+B13*5% -> 0 | D13: 10 | E13: =+(B13-C13)/D13 -> 0 | F13: =+E13/2 -> 0 | G13: =+F13 -> 0 | H13: =+G13 -> 0 | I13: =+H13 -> 0 | J13: =+I13 -> 0 | K13: =+J13 -> 0 | L13: =+K13 -> 0 | N13: =+G13+(('3 Recursos físicos'!C136*0.95)/Depreciación!$D13) -> 0 | O13: =+H13+(('3 Recursos físicos'!D136*0.95)/Depreciación!$D13) -> 0 | P13: =+I13+(('3 Recursos físicos'!E136*0.95)/Depreciación!$D13) -> 0 | Q13: =+J13+(('3 Recursos físicos'!F136*0.95)/Depreciación!$D13) -> 0 | R13: =+K13+(('3 Recursos físicos'!G136*0.95)/Depreciación!$D13) -> 0 | S13: =+L13+(('3 Recursos físicos'!H136*0.95)/Depreciación!$D13) -> 0 | T13: =+F13+(('3 Recursos físicos'!I136*0.95)/Depreciación!$D13) -> 0
A14: =+'3 Recursos físicos'!A10 -> Libros | B14: =+'3 Recursos físicos'!E15 -> 0 | C14: =+B14*5% -> 0 | D14: 10 | E14: =+(B14-C14)/D14 -> 0 | F14: =+E14/2 -> 0 | G14: =+F14 -> 0 | H14: =+G14 -> 0 | I14: =+H14 -> 0 | J14: =+I14 -> 0 | K14: =+J14 -> 0 | L14: =+K14 -> 0 | N14: =+G14+(('3 Recursos físicos'!C137*0.95)/Depreciación!$D14) -> 0 | O14: =+H14+(('3 Recursos físicos'!D137*0.95)/Depreciación!$D14) -> 0 | P14: =+I14+(('3 Recursos físicos'!E137*0.95)/Depreciación!$D14) -> 0 | Q14: =+J14+(('3 Recursos físicos'!F137*0.95)/Depreciación!$D14) -> 0 | R14: =+K14+(('3 Recursos físicos'!G137*0.95)/Depreciación!$D14) -> 0 | S14: =+L14+(('3 Recursos físicos'!H137*0.95)/Depreciación!$D14) -> 0 | T14: =+F14+(('3 Recursos físicos'!I137*0.95)/Depreciación!$D14) -> 0
A15: =+'3 Recursos físicos'!A11 -> 0 | B15: =+'3 Recursos físicos'!E16 -> 0 | C15: =+B15*5% -> 0 | D15: 10 | E15: =+(B15-C15)/D15 -> 0 | F15: =+E15/2 -> 0 | G15: =+F15 -> 0 | H15: =+G15 -> 0 | I15: =+H15 -> 0 | J15: =+I15 -> 0 | K15: =+J15 -> 0 | L15: =+K15 -> 0 | N15: =+G15+(('3 Recursos físicos'!C138*0.95)/Depreciación!$D15) -> 0 | O15: =+H15+(('3 Recursos físicos'!D138*0.95)/Depreciación!$D15) -> 0 | P15: =+I15+(('3 Recursos físicos'!E138*0.95)/Depreciación!$D15) -> 0 | Q15: =+J15+(('3 Recursos físicos'!F138*0.95)/Depreciación!$D15) -> 0 | R15: =+K15+(('3 Recursos físicos'!G138*0.95)/Depreciación!$D15) -> 0 | S15: =+L15+(('3 Recursos físicos'!H138*0.95)/Depreciación!$D15) -> 0 | T15: =+F15+(('3 Recursos físicos'!I138*0.95)/Depreciación!$D15) -> 0
A16: =+'3 Recursos físicos'!A12 -> 0 | B16: =+'3 Recursos físicos'!E17 -> 0 | C16: =+B16*5% -> 0 | D16: 10 | E16: =+(B16-C16)/D16 -> 0 | F16: =+E16/2 -> 0 | G16: =+F16 -> 0 | H16: =+G16 -> 0 | I16: =+H16 -> 0 | J16: =+I16 -> 0 | K16: =+J16 -> 0 | L16: =+K16 -> 0 | N16: =+G16+(('3 Recursos físicos'!C139*0.95)/Depreciación!$D16) -> 0 | O16: =+H16+(('3 Recursos físicos'!D139*0.95)/Depreciación!$D16) -> 0 | P16: =+I16+(('3 Recursos físicos'!E139*0.95)/Depreciación!$D16) -> 0 | Q16: =+J16+(('3 Recursos físicos'!F139*0.95)/Depreciación!$D16) -> 0 | R16: =+K16+(('3 Recursos físicos'!G139*0.95)/Depreciación!$D16) -> 0 | S16: =+L16+(('3 Recursos físicos'!H139*0.95)/Depreciación!$D16) -> 0 | T16: =+F16+(('3 Recursos físicos'!I139*0.95)/Depreciación!$D16) -> 0
A17: =+'3 Recursos físicos'!A13 -> 0 | B17: =+'3 Recursos físicos'!E18 -> 0 | C17: =+B17*5% -> 0 | D17: 10 | E17: =+(B17-C17)/D17 -> 0 | F17: =+E17/2 -> 0 | G17: =+F17 -> 0 | H17: =+G17 -> 0 | I17: =+H17 -> 0 | J17: =+I17 -> 0 | K17: =+J17 -> 0 | L17: =+K17 -> 0 | N17: =+G17+(('3 Recursos físicos'!C140*0.95)/Depreciación!$D17) -> 0 | O17: =+H17+(('3 Recursos físicos'!D140*0.95)/Depreciación!$D17) -> 0 | P17: =+I17+(('3 Recursos físicos'!E140*0.95)/Depreciación!$D17) -> 0 | Q17: =+J17+(('3 Recursos físicos'!F140*0.95)/Depreciación!$D17) -> 0 | R17: =+K17+(('3 Recursos físicos'!G140*0.95)/Depreciación!$D17) -> 0 | S17: =+L17+(('3 Recursos físicos'!H140*0.95)/Depreciación!$D17) -> 0 | T17: =+F17+(('3 Recursos físicos'!I140*0.95)/Depreciación!$D17) -> 0
A18: =+'3 Recursos físicos'!A14 -> 0 | B18: =+'3 Recursos físicos'!E19 -> 0 | C18: =+B18*5% -> 0 | D18: 10 | E18: =+(B18-C18)/D18 -> 0 | F18: =+E18/2 -> 0 | G18: =+F18 -> 0 | H18: =+G18 -> 0 | I18: =+H18 -> 0 | J18: =+I18 -> 0 | K18: =+J18 -> 0 | L18: =+K18 -> 0 | N18: =+G18+(('3 Recursos físicos'!C141*0.95)/Depreciación!$D18) -> 0 | O18: =+H18+(('3 Recursos físicos'!D141*0.95)/Depreciación!$D18) -> 0 | P18: =+I18+(('3 Recursos físicos'!E141*0.95)/Depreciación!$D18) -> 0 | Q18: =+J18+(('3 Recursos físicos'!F141*0.95)/Depreciación!$D18) -> 0 | R18: =+K18+(('3 Recursos físicos'!G141*0.95)/Depreciación!$D18) -> 0 | S18: =+L18+(('3 Recursos físicos'!H141*0.95)/Depreciación!$D18) -> 0 | T18: =+F18+(('3 Recursos físicos'!I141*0.95)/Depreciación!$D18) -> 0
A19: =+'3 Recursos físicos'!A15 -> 0 | B19: =+'3 Recursos físicos'!E20 -> 0 | C19: =+B19*5% -> 0 | D19: 10 | E19: =+(B19-C19)/D19 -> 0 | F19: =+E19/2 -> 0 | G19: =+F19 -> 0 | H19: =+G19 -> 0 | I19: =+H19 -> 0 | J19: =+I19 -> 0 | K19: =+J19 -> 0 | L19: =+K19 -> 0 | N19: =+G19+(('3 Recursos físicos'!C142*0.95)/Depreciación!$D19) -> 0 | O19: =+H19+(('3 Recursos físicos'!D142*0.95)/Depreciación!$D19) -> 0 | P19: =+I19+(('3 Recursos físicos'!E142*0.95)/Depreciación!$D19) -> 0 | Q19: =+J19+(('3 Recursos físicos'!F142*0.95)/Depreciación!$D19) -> 0 | R19: =+K19+(('3 Recursos físicos'!G142*0.95)/Depreciación!$D19) -> 0 | S19: =+L19+(('3 Recursos físicos'!H142*0.95)/Depreciación!$D19) -> 0 | T19: =+F19+(('3 Recursos físicos'!I142*0.95)/Depreciación!$D19) -> 0
A20: =+'3 Recursos físicos'!A16 -> 0 | B20: =+'3 Recursos físicos'!E21 -> 0 | C20: =+B20*5% -> 0 | D20: 10 | E20: =+(B20-C20)/D20 -> 0 | F20: =+E20/2 -> 0 | G20: =+F20 -> 0 | H20: =+G20 -> 0 | I20: =+H20 -> 0 | J20: =+I20 -> 0 | K20: =+J20 -> 0 | L20: =+K20 -> 0 | N20: =+G20+(('3 Recursos físicos'!C143*0.95)/Depreciación!$D20) -> 0 | O20: =+H20+(('3 Recursos físicos'!D143*0.95)/Depreciación!$D20) -> 0 | P20: =+I20+(('3 Recursos físicos'!E143*0.95)/Depreciación!$D20) -> 0 | Q20: =+J20+(('3 Recursos físicos'!F143*0.95)/Depreciación!$D20) -> 0 | R20: =+K20+(('3 Recursos físicos'!G143*0.95)/Depreciación!$D20) -> 0 | S20: =+L20+(('3 Recursos físicos'!H143*0.95)/Depreciación!$D20) -> 0 | T20: =+F20+(('3 Recursos físicos'!I143*0.95)/Depreciación!$D20) -> 0
A21: =+'3 Recursos físicos'!A22 -> Laboratorios y Equipos | E21: =SUM(E22:E34) -> 35.803125 | F21: =SUM(F22:F34) -> 17.901563 | G21: =SUM(G22:G34) -> 17.901563 | H21: =SUM(H22:H34) -> 17.901563 | I21: =SUM(I22:I34) -> 17.901563 | J21: =SUM(J22:J34) -> 17.901563 | K21: =SUM(K22:K34) -> 17.901563 | L21: =SUM(L22:L34) -> 17.901563 | N21: =SUM(N22:N34) -> 86.048406 | O21: =SUM(O22:O34) -> 2512.179 | P21: =SUM(P22:P34) -> 4956.1422 | Q21: =SUM(Q22:Q34) -> 4970.7853 | R21: =SUM(R22:R34) -> 5006.8561 | S21: =SUM(S22:S34) -> 5013.4966 | T21: =SUM(T22:T34) -> 5047.4538
A22: =+'3 Recursos físicos'!A23 -> Operatividad EVEA | B22: =+'3 Recursos físicos'!E23 -> 225 | C22: =+B22*5% -> 11.25 | D22: 10 | E22: =+(B22-C22)/D22 -> 21.375 | F22: =+E22/2 -> 10.6875 | G22: =+F22 -> 10.6875 | H22: =+G22 -> 10.6875 | I22: =+H22 -> 10.6875 | J22: =+I22 -> 10.6875 | K22: =+J22 -> 10.6875 | L22: =+K22 -> 10.6875 | N22: =+G22+(('3 Recursos físicos'!C145*0.95)/Depreciación!$D22) -> 73.46231 | O22: =+H22+(('3 Recursos físicos'!D145*0.95)/Depreciación!$D22) -> 88.790005 | P22: =+I22+(('3 Recursos físicos'!E145*0.95)/Depreciación!$D22) -> 124.18487 | Q22: =+J22+(('3 Recursos físicos'!F145*0.95)/Depreciación!$D22) -> 136.57975 | R22: =+K22+(('3 Recursos físicos'!G145*0.95)/Depreciación!$D22) -> 168.61315 | S22: =+L22+(('3 Recursos físicos'!H145*0.95)/Depreciación!$D22) -> 173.5289 | T22: =+F22+(('3 Recursos físicos'!I145*0.95)/Depreciación!$D22) -> 203.55051
A23: =+'3 Recursos físicos'!A24 -> Licencias, almacenamiento y webninar ZOOM | B23: =+'3 Recursos físicos'!E24 -> 151.875 | C23: =+B23*5% -> 7.59375 | D23: 10 | E23: =+(B23-C23)/D23 -> 14.428125 | F23: =+E23/2 -> 7.2140625 | G23: =+F23 -> 7.2140625 | H23: =+G23 -> 7.2140625 | I23: =+H23 -> 7.2140625 | J23: =+I23 -> 7.2140625 | K23: =+J23 -> 7.2140625 | L23: =+K23 -> 7.2140625 | N23: =+G23+(('3 Recursos físicos'!C146*0.95)/Depreciación!$D23) -> 12.586096 | O23: =+H23+(('3 Recursos físicos'!D146*0.95)/Depreciación!$D23) -> 14.426496 | P23: =+I23+(('3 Recursos físicos'!E146*0.95)/Depreciación!$D23) -> 18.307335 | Q23: =+J23+(('3 Recursos físicos'!F146*0.95)/Depreciación!$D23) -> 20.55558 | R23: =+K23+(('3 Recursos físicos'!G146*0.95)/Depreciación!$D23) -> 24.593 | S23: =+L23+(('3 Recursos físicos'!H146*0.95)/Depreciación!$D23) -> 26.317714 | T23: =+F23+(('3 Recursos físicos'!I146*0.95)/Depreciación!$D23) -> 30.253261
A24: =+'3 Recursos físicos'!A25 -> Laboratorio de Redes | B24: =+'3 Recursos físicos'!E25 -> 0 | C24: =+B24*5% -> 0 | D24: 10 | E24: =+(B24-C24)/D24 -> 0 | F24: =+E24/2 -> 0 | G24: =+F24 -> 0 | H24: =+G24 -> 0 | I24: =+H24 -> 0 | J24: =+I24 -> 0 | K24: =+J24 -> 0 | L24: =+K24 -> 0 | N24: =+G24+(('3 Recursos físicos'!C147*0.95)/Depreciación!$D24) -> 0 | O24: =+H24+(('3 Recursos físicos'!D147*0.95)/Depreciación!$D24) -> 2408.9625 | P24: 2406.825 | Q24: 2406.825 | R24: 2406.825 | S24: 2406.825 | T24: 2406.825
A25: =+'3 Recursos físicos'!A26 -> Laboratorio de Redes | B25: =+'3 Recursos físicos'!E26 -> 0 | C25: =+B25*5% -> 0 | D25: 10 | E25: =+(B25-C25)/D25 -> 0 | F25: =+E25/2 -> 0 | G25: =+F25 -> 0 | H25: =+G25 -> 0 | I25: =+H25 -> 0 | J25: =+I25 -> 0 | K25: =+J25 -> 0 | L25: =+K25 -> 0 | N25: =+G25+(('3 Recursos físicos'!C148*0.95)/Depreciación!$D25) -> 0 | O25: =+H25+(('3 Recursos físicos'!D148*0.95)/Depreciación!$D25) -> 0 | P25: 2406.825 | Q25: 2406.825 | R25: 2406.825 | S25: 2406.825 | T25: 2406.825
A26: =+'3 Recursos físicos'!A27 -> 0 | B26: =+'3 Recursos físicos'!E27 -> 0 | C26: =+B26*5% -> 0 | D26: 10 | E26: =+(B26-C26)/D26 -> 0 | F26: =+E26/2 -> 0 | G26: =+F26 -> 0 | H26: =+G26 -> 0 | I26: =+H26 -> 0 | J26: =+I26 -> 0 | K26: =+J26 -> 0 | L26: =+K26 -> 0 | N26: =+G26+(('3 Recursos físicos'!C161*0.95)/Depreciación!$D26) -> 0 | O26: =+H26+(('3 Recursos físicos'!D161*0.95)/Depreciación!$D26) -> 0 | P26: =+I26+(('3 Recursos físicos'!E161*0.95)/Depreciación!$D26) -> 0 | Q26: =+J26+(('3 Recursos físicos'!F161*0.95)/Depreciación!$D26) -> 0 | R26: =+K26+(('3 Recursos físicos'!G161*0.95)/Depreciación!$D26) -> 0 | S26: =+L26+(('3 Recursos físicos'!H161*0.95)/Depreciación!$D26)+R26 -> 0 | T26: =+M26+(('3 Recursos físicos'!I161*0.95)/Depreciación!$D26)+S26 -> 0
A27: =+'3 Recursos físicos'!A29 -> Equipo de audio | B27: =+'3 Recursos físicos'!E31 -> 0 | C27: =+B27*5% -> 0 | D27: 10 | E27: =+(B27-C27)/D27 -> 0 | F27: =+E27/2 -> 0 | G27: =+F27 -> 0 | H27: =+G27 -> 0 | I27: =+H27 -> 0 | J27: =+I27 -> 0 | K27: =+J27 -> 0 | L27: =+K27 -> 0 | N27: =+G27+(('3 Recursos físicos'!C163*0.95)/Depreciación!$D27) -> 0 | O27: =+H27+(('3 Recursos físicos'!D163*0.95)/Depreciación!$D27) -> 0 | P27: =+I27+(('3 Recursos físicos'!E163*0.95)/Depreciación!$D27) -> 0 | Q27: =+J27+(('3 Recursos físicos'!F163*0.95)/Depreciación!$D27) -> 0 | R27: =+K27+(('3 Recursos físicos'!G163*0.95)/Depreciación!$D27) -> 0 | S27: =+L27+(('3 Recursos físicos'!H163*0.95)/Depreciación!$D27) -> 0 | T27: =+N27+(('3 Recursos físicos'!I163*0.95)/Depreciación!$D27) -> 0
A28: =+'3 Recursos físicos'!A30 -> 0 | B28: =+'3 Recursos físicos'!E32 -> 0 | C28: =+B28*5% -> 0 | D28: 10 | E28: =+(B28-C28)/D28 -> 0 | F28: =+E28/2 -> 0 | G28: =+F28 -> 0 | H28: =+G28 -> 0 | I28: =+H28 -> 0 | J28: =+I28 -> 0 | K28: =+J28 -> 0 | L28: =+K28 -> 0 | N28: =+G28+(('3 Recursos físicos'!C164*0.95)/Depreciación!$D28) -> 0 | O28: =+H28+(('3 Recursos físicos'!D164*0.95)/Depreciación!$D28) -> 0 | P28: =+I28+(('3 Recursos físicos'!E164*0.95)/Depreciación!$D28) -> 0 | Q28: =+J28+(('3 Recursos físicos'!F164*0.95)/Depreciación!$D28) -> 0 | R28: =+K28+(('3 Recursos físicos'!G164*0.95)/Depreciación!$D28) -> 0 | S28: =+L28+(('3 Recursos físicos'!H164*0.95)/Depreciación!$D28) -> 0 | T28: =+M28+(('3 Recursos físicos'!I164*0.95)/Depreciación!$D28) -> 0
A29: =+'3 Recursos físicos'!A33 -> 0 | B29: =+'3 Recursos físicos'!E33 -> 0 | C29: =+B29*5% -> 0 | D29: 10 | E29: =+(B29-C29)/D29 -> 0 | F29: =+E29/2 -> 0 | G29: =+F29 -> 0 | H29: =+G29 -> 0 | I29: =+H29 -> 0 | J29: =+I29 -> 0 | K29: =+J29 -> 0 | L29: =+K29 -> 0 | N29: =+G29+(('3 Recursos físicos'!C165*0.95)/Depreciación!$D29) -> 0 | O29: =+H29+(('3 Recursos físicos'!D165*0.95)/Depreciación!$D29) -> 0 | P29: =+I29+(('3 Recursos físicos'!E165*0.95)/Depreciación!$D29) -> 0 | Q29: =+J29+(('3 Recursos físicos'!F165*0.95)/Depreciación!$D29) -> 0 | R29: =+K29+(('3 Recursos físicos'!G165*0.95)/Depreciación!$D29) -> 0 | S29: =+L29+(('3 Recursos físicos'!H165*0.95)/Depreciación!$D29) -> 0 | T29: =+N29+(('3 Recursos físicos'!I165*0.95)/Depreciación!$D29) -> 0
A30: =+'3 Recursos físicos'!A34 -> 0 | B30: =+'3 Recursos físicos'!E34 -> 0 | C30: =+B30*5% -> 0 | D30: 10 | E30: =+(B30-C30)/D30 -> 0 | F30: =+E30/2 -> 0 | G30: =+F30 -> 0 | H30: =+G30 -> 0 | I30: =+H30 -> 0 | J30: =+I30 -> 0 | K30: =+J30 -> 0 | L30: =+K30 -> 0 | N30: =+G30+(('3 Recursos físicos'!C166*0.95)/Depreciación!$D30) -> 0 | O30: =+H30+(('3 Recursos físicos'!D166*0.95)/Depreciación!$D30) -> 0 | P30: =+I30+(('3 Recursos físicos'!E166*0.95)/Depreciación!$D30) -> 0 | Q30: =+J30+(('3 Recursos físicos'!F166*0.95)/Depreciación!$D30) -> 0 | R30: =+K30+(('3 Recursos físicos'!G166*0.95)/Depreciación!$D30) -> 0 | S30: =+L30+(('3 Recursos físicos'!H166*0.95)/Depreciación!$D30) -> 0 | T30: =+N30+(('3 Recursos físicos'!I166*0.95)/Depreciación!$D30) -> 0
A31: =+'3 Recursos físicos'!A35 -> 0 | B31: =+'3 Recursos físicos'!E35 -> 0 | C31: =+B31*5% -> 0 | D31: 10 | E31: =+(B31-C31)/D31 -> 0 | F31: =+E31/2 -> 0 | G31: =+F31 -> 0 | H31: =+G31 -> 0 | I31: =+H31 -> 0 | J31: =+I31 -> 0 | K31: =+J31 -> 0 | L31: =+K31 -> 0 | N31: =+G31+(('3 Recursos físicos'!C167*0.95)/Depreciación!$D31) -> 0 | O31: =+H31+(('3 Recursos físicos'!D167*0.95)/Depreciación!$D31) -> 0 | P31: =+I31+(('3 Recursos físicos'!E167*0.95)/Depreciación!$D31) -> 0 | Q31: =+J31+(('3 Recursos físicos'!F167*0.95)/Depreciación!$D31) -> 0 | R31: =+K31+(('3 Recursos físicos'!G167*0.95)/Depreciación!$D31) -> 0 | S31: =+L31+(('3 Recursos físicos'!H167*0.95)/Depreciación!$D31) -> 0 | T31: =+N31+(('3 Recursos físicos'!I167*0.95)/Depreciación!$D31) -> 0
A32: =+'3 Recursos físicos'!A37 -> 0 | B32: =+'3 Recursos físicos'!E37 -> 0 | C32: =+B32*5% -> 0 | D32: 10 | E32: =+(B32-C32)/D32 -> 0 | F32: =+E32/2 -> 0 | G32: =+F32 -> 0 | H32: =+G32 -> 0 | I32: =+H32 -> 0 | J32: =+I32 -> 0 | K32: =+J32 -> 0 | L32: =+K32 -> 0 | N32: =+G32+(('3 Recursos físicos'!C169*0.95)/Depreciación!$D32) -> 0 | O32: =+H32+(('3 Recursos físicos'!D169*0.95)/Depreciación!$D32) -> 0 | P32: =+I32+(('3 Recursos físicos'!E169*0.95)/Depreciación!$D32) -> 0 | Q32: =+J32+(('3 Recursos físicos'!F169*0.95)/Depreciación!$D32) -> 0 | R32: =+K32+(('3 Recursos físicos'!G169*0.95)/Depreciación!$D32) -> 0 | S32: =+L32+(('3 Recursos físicos'!H169*0.95)/Depreciación!$D32) -> 0 | T32: =+N32+(('3 Recursos físicos'!I169*0.95)/Depreciación!$D32) -> 0
A33: =+'3 Recursos físicos'!A38 -> 0 | B33: =+'3 Recursos físicos'!E38 -> 0 | C33: =+B33*5% -> 0 | D33: 10 | E33: =+(B33-C33)/D33 -> 0 | F33: =+E33/2 -> 0 | G33: =+F33 -> 0 | H33: =+G33 -> 0 | I33: =+H33 -> 0 | J33: =+I33 -> 0 | K33: =+J33 -> 0 | L33: =+K33 -> 0 | N33: =+G33+(('3 Recursos físicos'!C170*0.95)/Depreciación!$D33) -> 0 | O33: =+H33+(('3 Recursos físicos'!D170*0.95)/Depreciación!$D33) -> 0 | P33: =+I33+(('3 Recursos físicos'!E170*0.95)/Depreciación!$D33) -> 0 | Q33: =+J33+(('3 Recursos físicos'!F170*0.95)/Depreciación!$D33) -> 0 | R33: =+K33+(('3 Recursos físicos'!G170*0.95)/Depreciación!$D33) -> 0 | S33: =+L33+(('3 Recursos físicos'!H170*0.95)/Depreciación!$D33) -> 0 | T33: =+N33+(('3 Recursos físicos'!I170*0.95)/Depreciación!$D33) -> 0
A34: =+'3 Recursos físicos'!A39 -> 0 | B34: =+'3 Recursos físicos'!E39 -> 0 | C34: =+B34*5% -> 0 | D34: 10 | E34: =+(B34-C34)/D34 -> 0 | F34: =+E34/2 -> 0 | G34: =+F34 -> 0 | H34: =+G34 -> 0 | I34: =+H34 -> 0 | J34: =+I34 -> 0 | K34: =+J34 -> 0 | L34: =+K34 -> 0 | N34: =+G34+(('3 Recursos físicos'!C171*0.95)/Depreciación!$D34) -> 0 | O34: =+H34+(('3 Recursos físicos'!D171*0.95)/Depreciación!$D34) -> 0 | P34: =+I34+(('3 Recursos físicos'!E171*0.95)/Depreciación!$D34) -> 0 | Q34: =+J34+(('3 Recursos físicos'!F171*0.95)/Depreciación!$D34) -> 0 | R34: =+K34+(('3 Recursos físicos'!G171*0.95)/Depreciación!$D34) -> 0 | S34: =+L34+(('3 Recursos físicos'!H171*0.95)/Depreciación!$D34) -> 0 | T34: =+M34+(('3 Recursos físicos'!I171*0.95)/Depreciación!$D34) -> 0
A35: =+'3 Recursos físicos'!A40 -> Equipo de Computo | E35: =SUM(E36:E50) -> 380 | F35: =SUM(F36:F50) -> 190 | G35: =SUM(G36:G50) -> 190 | H35: =SUM(H36:H50) -> 190 | I35: =SUM(I36:I50) -> 190 | J35: =SUM(J36:J50) -> 190 | K35: =SUM(K36:K50) -> 190 | L35: =SUM(L36:L50) -> 190 | N35: =SUM(N36:N50) -> 190 | O35: =SUM(O36:O50) -> 190 | P35: =SUM(P36:P50) -> 190 | Q35: =SUM(Q36:Q50) -> 190 | R35: =SUM(R36:R50) -> 190 | S35: =SUM(S36:S50) -> 190 | T35: =SUM(T36:T50) -> 0
A36: =+'3 Recursos físicos'!A41 -> Pizarra digital | B36: =+'3 Recursos físicos'!E41 -> 0 | C36: =+B36*5% -> 0 | D36: 3 | E36: =+(B36-C36)/D36 -> 0 | F36: =+E36/2 -> 0 | G36: =+F36 -> 0 | H36: =+G36 -> 0 | I36: =+H36 -> 0 | J36: =+I36 -> 0 | K36: =+J36 -> 0 | L36: =+K36 -> 0 | N36: =+G36+(('3 Recursos físicos'!C163*0.95)/Depreciación!$D36) -> 0 | O36: =+H36+(('3 Recursos físicos'!D163*0.95)/Depreciación!$D36) -> 0 | P36: =+I36+(('3 Recursos físicos'!E163*0.95)/Depreciación!$D36) -> 0 | Q36: =+J36+(('3 Recursos físicos'!F163*0.95)/Depreciación!$D36) -> 0 | R36: =+K36+(('3 Recursos físicos'!G163*0.95)/Depreciación!$D36) -> 0 | S36: =+L36+(('3 Recursos físicos'!H163*0.95)/Depreciación!$D36) -> 0 | T36: =+F36+(('3 Recursos físicos'!I163*0.95)/Depreciación!$D36) -> 0
A37: =+'3 Recursos físicos'!A42 -> Perifericos | B37: =+'3 Recursos físicos'!E42 -> 0 | C37: =+B37*5% -> 0 | D37: 3 | E37: =+(B37-C37)/D37 -> 0 | F37: =+E37/2 -> 0 | G37: =+F37 -> 0 | H37: =+G37 -> 0 | I37: =+H37 -> 0 | J37: =+I37 -> 0 | K37: =+J37 -> 0 | L37: =+K37 -> 0 | N37: =+G37+(('3 Recursos físicos'!C164*0.95)/Depreciación!$D37) -> 0 | O37: =+H37+(('3 Recursos físicos'!D164*0.95)/Depreciación!$D37) -> 0 | P37: =+I37+(('3 Recursos físicos'!E164*0.95)/Depreciación!$D37) -> 0 | Q37: =+J37+(('3 Recursos físicos'!F164*0.95)/Depreciación!$D37) -> 0 | R37: =+K37+(('3 Recursos físicos'!G164*0.95)/Depreciación!$D37) -> 0 | S37: =+L37+(('3 Recursos físicos'!H164*0.95)/Depreciación!$D37) -> 0 | T37: =+M37+(('3 Recursos físicos'!I164*0.95)/Depreciación!$D37) -> 0
A38: =+'3 Recursos físicos'!A43 -> Proyectores | B38: =+'3 Recursos físicos'!E43 -> 0 | C38: =+B38*5% -> 0 | D38: 3 | E38: =+(B38-C38)/D38 -> 0 | F38: =+E38/2 -> 0 | G38: =+F38 -> 0 | H38: =+G38 -> 0 | I38: =+H38 -> 0 | J38: =+I38 -> 0 | K38: =+J38 -> 0 | L38: =+K38 -> 0 | N38: =+G38+(('3 Recursos físicos'!C165*0.95)/Depreciación!$D38) -> 0 | O38: =+H38+(('3 Recursos físicos'!D165*0.95)/Depreciación!$D38) -> 0 | P38: =+I38+(('3 Recursos físicos'!E165*0.95)/Depreciación!$D38) -> 0 | Q38: =+J38+(('3 Recursos físicos'!F165*0.95)/Depreciación!$D38) -> 0 | R38: =+K38+(('3 Recursos físicos'!G165*0.95)/Depreciación!$D38) -> 0 | S38: =+L38+(('3 Recursos físicos'!H165*0.95)/Depreciación!$D38) -> 0 | T38: =+N38+(('3 Recursos físicos'!I165*0.95)/Depreciación!$D38) -> 0
A39: =+'3 Recursos físicos'!A44 -> Computador escritorio | B39: =+'3 Recursos físicos'!E44 -> 0 | C39: =+B39*5% -> 0 | D39: 3 | E39: =+(B39-C39)/D39 -> 0 | F39: =+E39/2 -> 0 | G39: =+F39 -> 0 | H39: =+G39 -> 0 | I39: =+H39 -> 0 | J39: =+I39 -> 0 | K39: =+J39 -> 0 | L39: =+K39 -> 0 | N39: =+G39+(('3 Recursos físicos'!C166*0.95)/Depreciación!$D39) -> 0 | O39: =+H39+(('3 Recursos físicos'!D166*0.95)/Depreciación!$D39) -> 0 | P39: =+I39+(('3 Recursos físicos'!E166*0.95)/Depreciación!$D39) -> 0 | Q39: =+J39+(('3 Recursos físicos'!F166*0.95)/Depreciación!$D39) -> 0 | R39: =+K39+(('3 Recursos físicos'!G166*0.95)/Depreciación!$D39) -> 0 | S39: =+L39+(('3 Recursos físicos'!H166*0.95)/Depreciación!$D39) -> 0 | T39: =+N39+(('3 Recursos físicos'!I166*0.95)/Depreciación!$D39) -> 0
A40: =+'3 Recursos físicos'!A45 -> Software | B40: =+'3 Recursos físicos'!E45 -> 0 | C40: =+B40*5% -> 0 | D40: 3 | E40: =+(B40-C40)/D40 -> 0 | F40: =+E40/2 -> 0 | G40: =+F40 -> 0 | H40: =+G40 -> 0 | I40: =+H40 -> 0 | J40: =+I40 -> 0 | K40: =+J40 -> 0 | L40: =+K40 -> 0 | N40: =+G40+(('3 Recursos físicos'!C167*0.95)/Depreciación!$D40) -> 0 | O40: =+H40+(('3 Recursos físicos'!D167*0.95)/Depreciación!$D40) -> 0 | P40: =+I40+(('3 Recursos físicos'!E167*0.95)/Depreciación!$D40) -> 0 | Q40: =+J40+(('3 Recursos físicos'!F167*0.95)/Depreciación!$D40) -> 0 | R40: =+K40+(('3 Recursos físicos'!G167*0.95)/Depreciación!$D40) -> 0 | S40: =+L40+(('3 Recursos físicos'!H167*0.95)/Depreciación!$D40) -> 0 | T40: =+M40+(('3 Recursos físicos'!I167*0.95)/Depreciación!$D40) -> 0
A41: =+'3 Recursos físicos'!A46 -> Computador portátil | B41: =+'3 Recursos físicos'!E46 -> 1200 | C41: =+B41*5% -> 60 | D41: 3 | E41: =+(B41-C41)/D41 -> 380 | F41: =+E41/2 -> 190 | G41: =+F41 -> 190 | H41: =+G41 -> 190 | I41: =+H41 -> 190 | J41: =+I41 -> 190 | K41: =+J41 -> 190 | L41: =+K41 -> 190 | N41: =+G41+(('3 Recursos físicos'!C168*0.95)/Depreciación!$D41) -> 190 | O41: =+H41+(('3 Recursos físicos'!D168*0.95)/Depreciación!$D41) -> 190 | P41: =+I41+(('3 Recursos físicos'!E168*0.95)/Depreciación!$D41) -> 190 | Q41: =+J41+(('3 Recursos físicos'!F168*0.95)/Depreciación!$D41) -> 190 | R41: =+K41+(('3 Recursos físicos'!G168*0.95)/Depreciación!$D41) -> 190 | S41: =+L41+(('3 Recursos físicos'!H168*0.95)/Depreciación!$D41) -> 190 | T41: =+M41+(('3 Recursos físicos'!I168*0.95)/Depreciación!$D41) -> 0
A42: =+'3 Recursos físicos'!A47 -> Switch | B42: =+'3 Recursos físicos'!E47 -> 0 | C42: =+B42*5% -> 0 | D42: 3 | E42: =+(B42-C42)/D42 -> 0 | F42: =+E42/2 -> 0 | G42: =+F42 -> 0 | H42: =+G42 -> 0 | I42: =+H42 -> 0 | J42: =+I42 -> 0 | K42: =+J42 -> 0 | L42: =+K42 -> 0 | N42: =+G42+(('3 Recursos físicos'!C169*0.95)/Depreciación!$D42) -> 0 | O42: =+H42+(('3 Recursos físicos'!D169*0.95)/Depreciación!$D42) -> 0 | P42: =+I42+(('3 Recursos físicos'!E169*0.95)/Depreciación!$D42) -> 0 | Q42: =+J42+(('3 Recursos físicos'!F169*0.95)/Depreciación!$D42) -> 0 | R42: =+K42+(('3 Recursos físicos'!G169*0.95)/Depreciación!$D42) -> 0 | S42: =+L42+(('3 Recursos físicos'!H169*0.95)/Depreciación!$D42) -> 0 | T42: =+M42+(('3 Recursos físicos'!I169*0.95)/Depreciación!$D42) -> 0
A43: =+'3 Recursos físicos'!A48 -> Software (mantenimiento) | B43: =+'3 Recursos físicos'!E48 -> 0 | C43: =+B43*5% -> 0 | D43: 3 | E43: =+(B43-C43)/D43 -> 0 | F43: =+E43/2 -> 0 | G43: =+F43 -> 0 | H43: =+G43 -> 0 | I43: =+H43 -> 0 | J43: =+I43 -> 0 | K43: =+J43 -> 0 | L43: =+K43 -> 0 | N43: =+G43+(('3 Recursos físicos'!C170*0.95)/Depreciación!$D43) -> 0 | O43: =+H43+(('3 Recursos físicos'!D170*0.95)/Depreciación!$D43) -> 0 | P43: =+I43+(('3 Recursos físicos'!E170*0.95)/Depreciación!$D43) -> 0 | Q43: =+J43+(('3 Recursos físicos'!F170*0.95)/Depreciación!$D43) -> 0 | R43: =+K43+(('3 Recursos físicos'!G170*0.95)/Depreciación!$D43) -> 0 | S43: =+L43+(('3 Recursos físicos'!H170*0.95)/Depreciación!$D43) -> 0 | T43: =+M43+(('3 Recursos físicos'!I170*0.95)/Depreciación!$D43) -> 0
A44: =+'3 Recursos físicos'!A49 -> 0 | B44: =+'3 Recursos físicos'!E49 -> 0 | C44: =+B44*5% -> 0 | D44: 3 | E44: =+(B44-C44)/D44 -> 0 | F44: =+E44/2 -> 0 | G44: =+F44 -> 0 | H44: =+G44 -> 0 | I44: =+H44 -> 0 | J44: =+I44 -> 0 | K44: =+J44 -> 0 | L44: =+K44 -> 0 | N44: =+G44+(('3 Recursos físicos'!C171*0.95)/Depreciación!$D44) -> 0 | O44: =+H44+(('3 Recursos físicos'!D171*0.95)/Depreciación!$D44) -> 0 | P44: =+I44+(('3 Recursos físicos'!E171*0.95)/Depreciación!$D44) -> 0 | Q44: =+J44+(('3 Recursos físicos'!F171*0.95)/Depreciación!$D44) -> 0 | R44: =+K44+(('3 Recursos físicos'!G171*0.95)/Depreciación!$D44) -> 0 | S44: =+L44+(('3 Recursos físicos'!H171*0.95)/Depreciación!$D44) -> 0 | T44: =+M44+(('3 Recursos físicos'!I171*0.95)/Depreciación!$D44) -> 0
A45: =+'3 Recursos físicos'!A50 -> 0 | B45: =+'3 Recursos físicos'!E50 -> 0 | C45: =+B45*5% -> 0 | D45: 3 | E45: =+(B45-C45)/D45 -> 0 | F45: =+E45/2 -> 0 | G45: =+F45 -> 0 | H45: =+G45 -> 0 | I45: =+H45 -> 0 | J45: =+I45 -> 0 | K45: =+J45 -> 0 | L45: =+K45 -> 0 | N45: =+G45+(('3 Recursos físicos'!C172*0.95)/Depreciación!$D45) -> 0 | O45: =+H45+(('3 Recursos físicos'!D172*0.95)/Depreciación!$D45) -> 0 | P45: =+I45+(('3 Recursos físicos'!E172*0.95)/Depreciación!$D45) -> 0 | Q45: =+J45+(('3 Recursos físicos'!F172*0.95)/Depreciación!$D45) -> 0 | R45: =+K45+(('3 Recursos físicos'!G172*0.95)/Depreciación!$D45) -> 0 | S45: =+L45+(('3 Recursos físicos'!H172*0.95)/Depreciación!$D45) -> 0 | T45: =+M45+(('3 Recursos físicos'!I172*0.95)/Depreciación!$D45) -> 0
A46: =+'3 Recursos físicos'!A51 -> 0 | B46: =+'3 Recursos físicos'!E51 -> 0 | C46: =+B46*5% -> 0 | D46: 3 | E46: =+(B46-C46)/D46 -> 0 | F46: =+E46/2 -> 0 | G46: =+F46 -> 0 | H46: =+G46 -> 0 | I46: =+H46 -> 0 | J46: =+I46 -> 0 | K46: =+J46 -> 0 | L46: =+K46 -> 0 | N46: =+G46+(('3 Recursos físicos'!C173*0.95)/Depreciación!$D46) -> 0 | O46: =+H46+(('3 Recursos físicos'!D173*0.95)/Depreciación!$D46) -> 0 | P46: =+I46+(('3 Recursos físicos'!E173*0.95)/Depreciación!$D46) -> 0 | Q46: =+J46+(('3 Recursos físicos'!F173*0.95)/Depreciación!$D46) -> 0 | R46: =+K46+(('3 Recursos físicos'!G173*0.95)/Depreciación!$D46) -> 0 | S46: =+L46+(('3 Recursos físicos'!H173*0.95)/Depreciación!$D46) -> 0 | T46: =+M46+(('3 Recursos físicos'!I173*0.95)/Depreciación!$D46) -> 0
A47: =+'3 Recursos físicos'!A52 -> 0 | B47: =+'3 Recursos físicos'!E52 -> 0 | C47: =+B47*5% -> 0 | D47: 3 | E47: =+(B47-C47)/D47 -> 0 | F47: =+E47/2 -> 0 | G47: =+F47 -> 0 | H47: =+G47 -> 0 | I47: =+H47 -> 0 | J47: =+I47 -> 0 | K47: =+J47 -> 0 | L47: =+K47 -> 0 | N47: =+G47+(('3 Recursos físicos'!C174*0.95)/Depreciación!$D47) -> 0 | O47: =+H47+(('3 Recursos físicos'!D174*0.95)/Depreciación!$D47) -> 0 | P47: =+I47+(('3 Recursos físicos'!E174*0.95)/Depreciación!$D47) -> 0 | Q47: =+J47+(('3 Recursos físicos'!F174*0.95)/Depreciación!$D47) -> 0 | R47: =+K47+(('3 Recursos físicos'!G174*0.95)/Depreciación!$D47) -> 0 | S47: =+L47+(('3 Recursos físicos'!H174*0.95)/Depreciación!$D47) -> 0 | T47: =+M47+(('3 Recursos físicos'!I174*0.95)/Depreciación!$D47) -> 0
A48: =+'3 Recursos físicos'!A53 -> 0 | B48: =+'3 Recursos físicos'!E53 -> 0 | C48: =+B48*5% -> 0 | D48: 3 | E48: =+(B48-C48)/D48 -> 0 | F48: =+E48/2 -> 0 | G48: =+F48 -> 0 | H48: =+G48 -> 0 | I48: =+H48 -> 0 | J48: =+I48 -> 0 | K48: =+J48 -> 0 | L48: =+K48 -> 0 | N48: =+G48+(('3 Recursos físicos'!C175*0.95)/Depreciación!$D48) -> 0 | O48: =+H48+(('3 Recursos físicos'!D175*0.95)/Depreciación!$D48) -> 0 | P48: =+I48+(('3 Recursos físicos'!E175*0.95)/Depreciación!$D48) -> 0 | Q48: =+J48+(('3 Recursos físicos'!F175*0.95)/Depreciación!$D48) -> 0 | R48: =+K48+(('3 Recursos físicos'!G175*0.95)/Depreciación!$D48) -> 0 | S48: =+L48+(('3 Recursos físicos'!H175*0.95)/Depreciación!$D48) -> 0 | T48: =+M48+(('3 Recursos físicos'!I175*0.95)/Depreciación!$D48) -> 0
A49: =+'3 Recursos físicos'!A54 -> 0 | B49: =+'3 Recursos físicos'!E54 -> 0 | C49: =+B49*5% -> 0 | D49: 3 | E49: =+(B49-C49)/D49 -> 0 | F49: =+E49/2 -> 0 | G49: =+F49 -> 0 | H49: =+G49 -> 0 | I49: =+H49 -> 0 | J49: =+I49 -> 0 | K49: =+J49 -> 0 | L49: =+K49 -> 0 | N49: =+G49+(('3 Recursos físicos'!C176*0.95)/Depreciación!$D49) -> 0 | O49: =+H49+(('3 Recursos físicos'!D176*0.95)/Depreciación!$D49) -> 0 | P49: =+I49+(('3 Recursos físicos'!E176*0.95)/Depreciación!$D49) -> 0 | Q49: =+J49+(('3 Recursos físicos'!F176*0.95)/Depreciación!$D49) -> 0 | R49: =+K49+(('3 Recursos físicos'!G176*0.95)/Depreciación!$D49) -> 0 | S49: =+L49+(('3 Recursos físicos'!H176*0.95)/Depreciación!$D49) -> 0 | T49: =+M49+(('3 Recursos físicos'!I176*0.95)/Depreciación!$D49) -> 0
A50: =+'3 Recursos físicos'!A55 -> 0 | B50: =+'3 Recursos físicos'!E55 -> 0 | C50: =+B50*5% -> 0 | D50: 3 | E50: =+(B50-C50)/D50 -> 0 | F50: =+E50/2 -> 0 | G50: =+F50 -> 0 | H50: =+G50 -> 0 | I50: =+H50 -> 0 | J50: =+I50 -> 0 | K50: =+J50 -> 0 | L50: =+K50 -> 0 | N50: =+G50+(('3 Recursos físicos'!C177*0.95)/Depreciación!$D50) -> 0 | O50: =+H50+(('3 Recursos físicos'!D177*0.95)/Depreciación!$D50) -> 0 | P50: =+I50+(('3 Recursos físicos'!E177*0.95)/Depreciación!$D50) -> 0 | Q50: =+J50+(('3 Recursos físicos'!F177*0.95)/Depreciación!$D50) -> 0 | R50: =+K50+(('3 Recursos físicos'!G177*0.95)/Depreciación!$D50) -> 0 | S50: =+L50+(('3 Recursos físicos'!H177*0.95)/Depreciación!$D50) -> 0 | T50: =+M50+(('3 Recursos físicos'!I177*0.95)/Depreciación!$D50) -> 0
A51: =+'3 Recursos físicos'!A56 -> Equipo de Oficina | E51: =SUM(E52:E55) -> 0 | F51: =SUM(F52:F55) -> 0 | G51: =SUM(G52:G55) -> 0 | H51: =SUM(H52:H55) -> 0 | I51: =SUM(I52:I55) -> 0 | J51: =SUM(J52:J55) -> 0 | K51: =SUM(K52:K55) -> 0 | L51: =SUM(L52:L55) -> 0 | N51: =SUM(N52:N55) -> 0 | O51: =SUM(O52:O55) -> 0 | P51: =SUM(P52:P55) -> 0 | Q51: =SUM(Q52:Q55) -> 0 | R51: =SUM(R52:R55) -> 0 | S51: =SUM(S52:S55) -> 0 | T51: =SUM(T52:T55) -> 0
A52: =+'3 Recursos físicos'!A57 -> Teléfono | B52: =+'3 Recursos físicos'!E57 -> 0 | C52: =+B52*5% -> 0 | D52: 1 | E52: =+(B52-C52)/D52 -> 0 | F52: =+E52/2 -> 0 | G52: =+F52 -> 0 | H52: =+G52 -> 0 | I52: =+H52 -> 0 | J52: =+I52 -> 0 | K52: =+J52 -> 0 | L52: =+K52 -> 0 | N52: =+G52+(('3 Recursos físicos'!C179*0.95)/Depreciación!$D52) -> 0 | O52: =+H52+(('3 Recursos físicos'!D179*0.95)/Depreciación!$D52) -> 0 | P52: =+I52+(('3 Recursos físicos'!E179*0.95)/Depreciación!$D52) -> 0 | Q52: =+J52+(('3 Recursos físicos'!F179*0.95)/Depreciación!$D52) -> 0 | R52: =+K52+(('3 Recursos físicos'!G179*0.95)/Depreciación!$D52) -> 0 | S52: =+L52+(('3 Recursos físicos'!H179*0.95)/Depreciación!$D52) -> 0 | T52: =+F52+(('3 Recursos físicos'!I179*0.95)/Depreciación!$D52) -> 0
A53: =+'3 Recursos físicos'!A58 -> 0 | B53: =+'3 Recursos físicos'!E58 -> 0 | C53: =+B53*5% -> 0 | D53: 1 | E53: =+(B53-C53)/D53 -> 0 | F53: =+E53/2 -> 0 | G53: =+F53 -> 0 | H53: =+G53 -> 0 | I53: =+H53 -> 0 | J53: =+I53 -> 0 | K53: =+J53 -> 0 | L53: =+K53 -> 0 | N53: =+G53+(('3 Recursos físicos'!C180*0.95)/Depreciación!$D53) -> 0 | O53: =+H53+(('3 Recursos físicos'!D180*0.95)/Depreciación!$D53) -> 0 | P53: =+I53+(('3 Recursos físicos'!E180*0.95)/Depreciación!$D53) -> 0 | Q53: =+J53+(('3 Recursos físicos'!F180*0.95)/Depreciación!$D53) -> 0 | R53: =+K53+(('3 Recursos físicos'!G180*0.95)/Depreciación!$D53) -> 0 | S53: =+L53+(('3 Recursos físicos'!H180*0.95)/Depreciación!$D53) -> 0 | T53: =+F53+(('3 Recursos físicos'!I180*0.95)/Depreciación!$D53) -> 0
A54: =+'3 Recursos físicos'!A59 -> 0 | B54: =+'3 Recursos físicos'!E59 -> 0 | C54: =+B54*5% -> 0 | D54: 1 | E54: =+(B54-C54)/D54 -> 0 | F54: =+E54/2 -> 0 | G54: =+F54 -> 0 | H54: =+G54 -> 0 | I54: =+H54 -> 0 | J54: =+I54 -> 0 | K54: =+J54 -> 0 | L54: =+K54 -> 0 | N54: =+G54+(('3 Recursos físicos'!C181*0.95)/Depreciación!$D54) -> 0 | O54: =+H54+(('3 Recursos físicos'!D181*0.95)/Depreciación!$D54) -> 0 | P54: =+I54+(('3 Recursos físicos'!E181*0.95)/Depreciación!$D54) -> 0 | Q54: =+J54+(('3 Recursos físicos'!F181*0.95)/Depreciación!$D54) -> 0 | R54: =+K54+(('3 Recursos físicos'!G181*0.95)/Depreciación!$D54) -> 0 | S54: =+L54+(('3 Recursos físicos'!H181*0.95)/Depreciación!$D54) -> 0 | T54: =+F54+(('3 Recursos físicos'!I181*0.95)/Depreciación!$D54) -> 0
A55: =+'3 Recursos físicos'!A60 -> 0 | B55: =+'3 Recursos físicos'!E60 -> 0 | C55: =+B55*5% -> 0 | D55: 1 | E55: =+(B55-C55)/D55 -> 0 | F55: =+E55/2 -> 0 | G55: =+F55 -> 0 | H55: =+G55 -> 0 | I55: =+H55 -> 0 | J55: =+I55 -> 0 | K55: =+J55 -> 0 | L55: =+K55 -> 0 | N55: =+G55+(('3 Recursos físicos'!C182*0.95)/Depreciación!$D55) -> 0 | O55: =+H55+(('3 Recursos físicos'!D182*0.95)/Depreciación!$D55) -> 0 | P55: =+I55+(('3 Recursos físicos'!E182*0.95)/Depreciación!$D55) -> 0 | Q55: =+J55+(('3 Recursos físicos'!F182*0.95)/Depreciación!$D55) -> 0 | R55: =+K55+(('3 Recursos físicos'!G182*0.95)/Depreciación!$D55) -> 0 | S55: =+L55+(('3 Recursos físicos'!H182*0.95)/Depreciación!$D55) -> 0 | T55: =+F55+(('3 Recursos físicos'!I182*0.95)/Depreciación!$D55) -> 0
A56: TOTAL | B56: =SUM(B4:B55) -> 1576.875 | C56: =SUM(C4:C55) -> 78.84375 | E56: =+E51+E35+E21+E3 -> 415.80313 | F56: =+F51+F35+F21+F3 -> 207.90156 | G56: =+G51+G35+G21+G3 -> 207.90156 | H56: =+H51+H35+H21+H3 -> 207.90156 | I56: =+I51+I35+I21+I3 -> 207.90156 | J56: =+J51+J35+J21+J3 -> 207.90156 | K56: =+K51+K35+K21+K3 -> 207.90156 | L56: =+L51+L35+L21+L3 -> 207.90156 | N56: =+N51+N35+N21+N3 -> 276.04841 | O56: =+O51+O35+O21+O3 -> 2702.179 | P56: =+P51+P35+P21+P3 -> 5146.1422 | Q56: =+Q51+Q35+Q21+Q3 -> 5160.7853 | R56: =+R51+R35+R21+R3 -> 5196.8561 | S56: =+S51+S35+S21+S3 -> 5203.4966 | T56: =+T51+T35+T21+T3 -> 5047.4538

Sheet 7 Sueldos
B1: =+'1 Estudiantes'!B3 -> 2023 | E1: INFLACIÓN | F1: 1 | K1: estudiantes U. académica | L1: 285
B2: PESO | C2: Nº | D2: CARGO | E2: SUELDO MENSUAL | F2: DECIMO XIII | G2: DECIMO IV | H2: VACACIONES | I2: FONDOS DE RESERVA MENSUAL | J2: APORTE PATRONAL MENSUAL | K2: TOTAL
B3: =+L3/M3 -> 0.095238095 | C3: 1 | D3: =+'6 Capital de trabajo'!B4 -> Decano | E3: =+'6 Capital de trabajo'!C4 -> 3880 | F3: =+E3*12/12/2 -> 1940 | G3: =+(400/2)*$F$1 -> 200 | H3: =+E3*12/24/2 -> 970 | I3: =+E3*8.33% -> 323.204 | J3: =+E3*11.15% -> 432.62 | K3: =+((((E3+I3+J3)*6)+F3+G3+H3)*C3)*B3 -> 2945.2328 | L3: ='1 Estudiantes'!$B$12 -> 30 | M3: =+$L$1+L3 -> 315
B4: =+L4/M4 -> 0.095238095 | C4: 1 | D4: =+'6 Capital de trabajo'!B5 -> Subdecano | E4: =+'6 Capital de trabajo'!C5 -> 2880 | F4: =+E4*12/12/2 -> 1440 | G4: =+(400/2)*$F$1 -> 200 | H4: =+E4*12/24/2 -> 720 | I4: =+E4*8.33% -> 239.904 | J4: =+E4*11.15% -> 321.12 | K4: =+((((E4+I4+J4)*6)+F4+G4+H4)*C4)*B4 -> 2191.0613 | L4: ='1 Estudiantes'!$B$12 -> 30 | M4: =+$L$1+L4 -> 315
B5: 1 | C5: 1 | D5: =+'6 Capital de trabajo'!B6 -> Director de Carrera | E5: =+'6 Capital de trabajo'!C6 -> 2200 | F5: =+E5*12/12/2 -> 1100 | G5: =+(400/2)*$F$1 -> 200 | H5: =+E5*12/24/2 -> 550 | I5: =+E5*8.33% -> 183.26 | J5: =+E5*11.15% -> 245.3 | K5: =+((((E5+I5+J5)*6)+F5+G5+H5)*C5)*B5 -> 17621.36 | L5: ='1 Estudiantes'!$B$12 -> 30 | M5: =+$L$1+L5 -> 315
B6: =+L6/M6 -> 0.095238095 | C6: 1 | D6: =+'6 Capital de trabajo'!B7 -> Secretario | E6: =+'6 Capital de trabajo'!C7 -> 1000 | F6: =+E6*12/12/2 -> 500 | G6: =+(400/2)*$F$1 -> 200 | H6: =+E6*12/24/2 -> 250 | I6: =+E6*8.33% -> 83.3 | J6: =+E6*11.15% -> 111.5 | K6: =+((((E6+I6+J6)*6)+F6+G6+H6)*C6)*B6 -> 773.21905 | L6: ='1 Estudiantes'!$B$12 -> 30 | M6: =+$L$1+L6 -> 315
B7: =+L7/M7 -> 0.095238095 | C7: 1 | D7: =+'6 Capital de trabajo'!B8 -> Auxiliar de Secretaria | E7: =+'6 Capital de trabajo'!C8 -> 850 | F7: =+E7*12/12/2 -> 425 | G7: =+(400/2)*$F$1 -> 200 | H7: =+E7*12/24/2 -> 212.5 | I7: =+E7*8.33% -> 70.805 | J7: =+E7*11.15% -> 94.775 | K7: =+((((E7+I7+J7)*6)+F7+G7+H7)*C7)*B7 -> 660.09333 | L7: ='1 Estudiantes'!$B$12 -> 30 | M7: =+$L$1+L7 -> 315
B8: =+L8/M8 -> 0.095238095 | C8: 1 | D8: =+'6 Capital de trabajo'!B9 -> Coordinador | E8: =+'6 Capital de trabajo'!C9 -> 900 | F8: =+E8*12/12/2 -> 450 | G8: =+(400/2)*$F$1 -> 200 | H8: =+E8*12/24/2 -> 225 | I8: =+E8*8.33% -> 74.97 | J8: =+E8*11.15% -> 100.35 | K8: =+((((E8+I8+J8)*6)+F8+G8+H8)*C8)*B8 -> 697.8019 | L8: ='1 Estudiantes'!$B$12 -> 30 | M8: =+$L$1+L8 -> 315
B9: =+L9/M9 -> 0.095238095 | C9: 1 | D9: =+'6 Capital de trabajo'!B10 -> Bienestar Estudiantil | E9: =+'6 Capital de trabajo'!C10 -> 900 | F9: =+E9*12/12/2 -> 450 | G9: =+(400/2)*$F$1 -> 200 | H9: =+E9*12/24/2 -> 225 | I9: =+E9*8.33% -> 74.97 | J9: =+E9*11.15% -> 100.35 | K9: =+((((E9+I9+J9)*6)+F9+G9+H9)*C9)*B9 -> 697.8019 | L9: ='1 Estudiantes'!$B$12 -> 30 | M9: =+$L$1+L9 -> 315
B10: 1 | C10: =+'5 Demanda'!B15 -> 0.24 | D10: =+'6 Capital de trabajo'!B11 -> Tiempo Completo PhD | E10: =+'6 Capital de trabajo'!C11 -> 2800 | F10: =+E10*12/12/2 -> 1400 | G10: =+(400/2)*$F$1 -> 200 | H10: =+E10*12/24/2 -> 700 | I10: =+E10*8.33% -> 233.24 | J10: =+E10*11.15% -> 312.2 | K10: =+((((E10+I10+J10)*6)+F10+G10+H10)*C10)*B10 -> 5369.4336 | L10: ='1 Estudiantes'!$B$12 -> 30 | M10: =+$L$1+L10 -> 315
B11: 1 | C11: =+'5 Demanda'!B16 -> 0.6 | D11: =+'6 Capital de trabajo'!B12 -> Tiempo Completo Mgs. | E11: =+'6 Capital de trabajo'!C12 -> 1800 | F11: =+E11*12/12/2 -> 900 | G11: =+(400/2)*$F$1 -> 200 | H11: =+E11*12/24/2 -> 450 | I11: =+E11*8.33% -> 149.94 | J11: =+E11*11.15% -> 200.7 | K11: =+((((E11+I11+J11)*6)+F11+G11+H11)*C11)*B11 -> 8672.304 | L11: ='1 Estudiantes'!$B$12 -> 30 | M11: =+$L$1+L11 -> 315
B12: 1 | C12: =+'5 Demanda'!B17 -> 0 | D12: =+'6 Capital de trabajo'!B13 -> Medio Tiempo | E12: =+'6 Capital de trabajo'!C13 -> 900 | F12: =+E12*12/12/2 -> 450 | G12: =+(400/2)*$F$1 -> 200 | H12: =+E12*12/24/2 -> 225 | I12: =+E12*8.33% -> 74.97 | J12: =+E12*11.15% -> 100.35 | K12: =+((((E12+I12+J12)*6)+F12+G12+H12)*C12)*B12 -> 0 | L12: ='1 Estudiantes'!$B$12 -> 30 | M12: =+$L$1+L12 -> 315
B13: 1 | C13: =+'5 Demanda'!B18 -> 0.16 | D13: =+'6 Capital de trabajo'!B14 -> Tiempo Parcial | E13: =+'6 Capital de trabajo'!C14 -> 432 | F13: =+E13*12/12/2 -> 216 | G13: =+(400/2)*$F$1 -> 200 | H13: =+E13*12/24/2 -> 108 | I13: =+E13*8.33% -> 35.9856 | J13: =+E13*11.15% -> 48.168 | K13: =+((((E13+I13+J13)*6)+F13+G13+H13)*C13)*B13 -> 579.34746 | L13: ='1 Estudiantes'!$B$12 -> 30 | M13: =+$L$1+L13 -> 315
B14: 1 | C14: =+'1 Estudiantes'!B30 -> 0.25 | D14: =+'1 Estudiantes'!A30 -> Ocasional Tipo 2 (Técnico Docente) | E14: =+'6 Capital de trabajo'!C15 -> 1350 | F14: =+E14*12/12/2 -> 675 | G14: =+(400/2)*$F$1 -> 200 | H14: =+E14*12/24/2 -> 337.5 | I14: =+E14*8.33% -> 112.455 | J14: =+E14*11.15% -> 150.525 | K14: =+((((E14+I14+J14)*6)+F14+G14+H14)*C14)*B14 -> 2722.595 | L14: ='1 Estudiantes'!$B$12 -> 30 | M14: =+$L$1+L14 -> 315
B15: =+L15/M15 -> 0.095238095 | C15: 1 | D15: =+'6 Capital de trabajo'!B16 -> Bibliotecario | E15: =+'6 Capital de trabajo'!C16 -> 800 | F15: =+E15*12/12/2 -> 400 | G15: =+(400/2)*$F$1 -> 200 | H15: =+E15*12/24/2 -> 200 | I15: =+E15*8.33% -> 66.64 | J15: =+E15*11.15% -> 89.2 | K15: =+((((E15+I15+J15)*6)+F15+G15+H15)*C15)*B15 -> 622.38476 | L15: ='1 Estudiantes'!$B$12 -> 30 | M15: =+$L$1+L15 -> 315
B16: =+L16/M16 -> 0.095238095 | C16: 2 | D16: =+'6 Capital de trabajo'!B17 -> Auxiliar de Servicio | E16: =+'6 Capital de trabajo'!C17 -> 450 | F16: =+E16*12/12/2 -> 225 | G16: =+(400/2)*$F$1 -> 200 | H16: =+E16*12/24/2 -> 112.5 | I16: =+E16*8.33% -> 37.485 | J16: =+E16*11.15% -> 50.175 | K16: =+((((E16+I16+J16)*6)+F16+G16+H16)*C16)*B16 -> 716.84952 | L16: ='1 Estudiantes'!$B$12 -> 30 | M16: =+$L$1+L16 -> 315
B17: =+L17/M17 -> 0.095238095 | C17: 1 | D17: =+'6 Capital de trabajo'!B18 -> Guardia | E17: =+'6 Capital de trabajo'!C18 -> 650 | F17: =+E17*12/12/2 -> 325 | G17: =+(400/2)*$F$1 -> 200 | H17: =+E17*12/24/2 -> 162.5 | I17: =+E17*8.33% -> 54.145 | J17: =+E17*11.15% -> 72.475 | K17: =+((((E17+I17+J17)*6)+F17+G17+H17)*C17)*B17 -> 509.25905 | L17: ='1 Estudiantes'!$B$12 -> 30 | M17: =+$L$1+L17 -> 315
D18: TOTAL | E18: =SUM(E3:E17) -> 21792 | F18: =SUM(F3:F17) -> 10896 | G18: =SUM(G3:G17) -> 3000 | H18: =SUM(H3:H17) -> 5448 | I18: =SUM(I3:I17) -> 1815.2736 | J18: =SUM(J3:J17) -> 2429.808 | K18: =SUM(K3:K17) -> 44778.744
B20: =+'1 Estudiantes'!C3 -> 2023 | E20: INFLACIÓN | F20: =+Inflación!C11/100+1 -> 1.0134 | O20: =475-26 -> 449
C21: =+C2 -> Nº | D21: CARGO | E21: SUELDO MENSUAL | F21: DECIMO XIII | G21: DECIMO IV | H21: VACACIONES | I21: FONDOS DE RESERVA MENSUAL | J21: APORTE PATRONAL MENSUAL | K21: TOTAL | O21: =+O22/P22 -> 0.29093895
B22: =+L22/M22 -> 0.23374738 | C22: =+C3 -> 1 | D22: =+D3 -> Decano | E22: =+E3*$F$20 -> 3931.992 | F22: =+E22*12/12/2 -> 1965.996 | G22: =+(400/2)*$F$1*1.05 -> 210 | H22: =+E22*12/24/2 -> 982.998 | I22: =+E22*8.33% -> 327.53493 | J22: =+E22*11.15% -> 438.41711 | K22: =+((((E22+I22+J22)*6)+F22+G22+H22)*C22)*B22 -> 7327.1992 | L22: =+'1 Estudiantes'!$C$12 -> 86.94 | M22: =+$L$1+L22 -> 371.94 | O22: =+L17+L22 -> 116.94 | P22: =+M17+L22 -> 401.94
B23: =+L23/M23 -> 0.23374738 | C23: =+C4 -> 1 | D23: =+D4 -> Subdecano | E23: =+E4*$F$20 -> 2918.592 | F23: =+E23*12/12/2 -> 1459.296 | G23: =+(400/2)*$F$1*1.05 -> 210 | H23: =+E23*12/24/2 -> 729.648 | I23: =+E23*8.33% -> 243.11871 | J23: =+E23*11.15% -> 325.42301 | K23: =+((((E23+I23+J23)*6)+F23+G23+H23)*C23)*B23 -> 5451.3971 | L23: =+'1 Estudiantes'!$C$12 -> 86.94 | M23: =+$L$1+L23 -> 371.94
B24: =+B5 -> 1 | C24: =+C5 -> 1 | D24: =+D5 -> Director de Carrera | E24: =+E5*$F$20 -> 2229.48 | F24: =+E24*12/12/2 -> 1114.74 | G24: =+(400/2)*$F$1*1.05 -> 210 | H24: =+E24*12/24/2 -> 557.37 | I24: =+E24*8.33% -> 185.71568 | J24: =+E24*11.15% -> 248.58702 | K24: =+((((E24+I24+J24)*6)+F24+G24+H24)*C24)*B24 -> 17864.806 | L24: =+'1 Estudiantes'!$C$12 -> 86.94 | M24: =+$L$1+L24 -> 371.94
B25: =+L25/M25 -> 0.23374738 | C25: =+C6 -> 1 | D25: =+D6 -> Secretario | E25: =+E6*$F$20 -> 1013.4 | F25: =+E25*12/12/2 -> 506.7 | G25: =+(400/2)*$F$1*1.05 -> 210 | H25: =+E25*12/24/2 -> 253.35 | I25: =+E25*8.33% -> 84.41622 | J25: =+E25*11.15% -> 112.9941 | K25: =+((((E25+I25+J25)*6)+F25+G25+H25)*C25)*B25 -> 1924.8891 | L25: =+'1 Estudiantes'!$C$12 -> 86.94 | M25: =+$L$1+L25 -> 371.94
B26: =+L26/M26 -> 0.23374738 | C26: =+C7 -> 1 | D26: =+D7 -> Auxiliar de Secretaria | E26: =+E7*$F$20 -> 861.39 | F26: =+E26*12/12/2 -> 430.695 | G26: =+(400/2)*$F$1*1.05 -> 210 | H26: =+E26*12/24/2 -> 215.3475 | I26: =+E26*8.33% -> 71.753787 | J26: =+E26*11.15% -> 96.044985 | K26: =+((((E26+I26+J26)*6)+F26+G26+H26)*C26)*B26 -> 1643.5188 | L26: =+'1 Estudiantes'!$C$12 -> 86.94 | M26: =+$L$1+L26 -> 371.94
B27: =+L27/M27 -> 0.23374738 | C27: =+C8 -> 1 | D27: =+D8 -> Coordinador | E27: =+E8*$F$20 -> 912.06 | F27: =+E27*12/12/2 -> 456.03 | G27: =+(400/2)*$F$1*1.05 -> 210 | H27: =+E27*12/24/2 -> 228.015 | I27: =+E27*8.33% -> 75.974598 | J27: =+E27*11.15% -> 101.69469 | K27: =+((((E27+I27+J27)*6)+F27+G27+H27)*C27)*B27 -> 1737.3089 | L27: =+'1 Estudiantes'!$C$12 -> 86.94 | M27: =+$L$1+L27 -> 371.94
B28: =+L28/M28 -> 0.23374738 | C28: =+C9 -> 1 | D28: =+D9 -> Bienestar Estudiantil | E28: =+E9*$F$20 -> 912.06 | F28: =+E28*12/12/2 -> 456.03 | G28: =+(400/2)*$F$1*1.05 -> 210 | H28: =+E28*12/24/2 -> 228.015 | I28: =+E28*8.33% -> 75.974598 | J28: =+E28*11.15% -> 101.69469 | K28: =+((((E28+I28+J28)*6)+F28+G28+H28)*C28)*B28 -> 1737.3089 | L28: =+'1 Estudiantes'!$C$12 -> 86.94 | M28: =+$L$1+L28 -> 371.94
B29: =+B10 -> 1 | C29: =+'5 Demanda'!C15 -> 0.8 | D29: =+D10 -> Tiempo Completo PhD | E29: =+E10*$F$20 -> 2837.52 | F29: =+E29*12/12/2 -> 1418.76 | G29: =+(400/2)*$F$1*1.05 -> 210 | H29: =+E29*12/24/2 -> 709.38 | I29: =+E29*8.33% -> 236.36542 | J29: =+E29*11.15% -> 316.38348 | K29: =+((((E29+I29+J29)*6)+F29+G29+H29)*C29)*B29 -> 18143.803 | L29: =+'1 Estudiantes'!$C$12 -> 86.94 | M29: =+$L$1+L29 -> 371.94
B30: =+B11 -> 1 | C30: =+'5 Demanda'!C16 -> 2 | D30: =+D11 -> Tiempo Completo Mgs. | E30: =+E11*$F$20 -> 1824.12 | F30: =+E30*12/12/2 -> 912.06 | G30: =+(400/2)*$F$1*1.05 -> 210 | H30: =+E30*12/24/2 -> 456.03 | I30: =+E30*8.33% -> 151.9492 | J30: =+E30*11.15% -> 203.38938 | K30: =+((((E30+I30+J30)*6)+F30+G30+H30)*C30)*B30 -> 29309.683 | L30: =+'1 Estudiantes'!$C$12 -> 86.94 | M30: =+$L$1+L30 -> 371.94
B31: =+B12 -> 1 | C31: =+'5 Demanda'!C17 -> 0 | D31: =+D12 -> Medio Tiempo | E31: =+E12*$F$20 -> 912.06 | F31: =+E31*12/12/2 -> 456.03 | G31: =+(400/2)*$F$1*1.05 -> 210 | H31: =+E31*12/24/2 -> 228.015 | I31: =+E31*8.33% -> 75.974598 | J31: =+E31*11.15% -> 101.69469 | K31: =+((((E31+I31+J31)*6)+F31+G31+H31)*C31)*B31 -> 0 | L31: =+'1 Estudiantes'!$C$12 -> 86.94 | M31: =+$L$1+L31 -> 371.94
B32: =+B13 -> 1 | C32: =+'5 Demanda'!C18 -> 0.53333333 | D32: =+D13 -> Tiempo Parcial | E32: =+E13*$F$20 -> 437.7888 | F32: =+E32*12/12/2 -> 218.8944 | G32: =+(400/2)*$F$1*1.05 -> 210 | H32: =+E32*12/24/2 -> 109.4472 | I32: =+E32*8.33% -> 36.467807 | J32: =+E32*11.15% -> 48.813451 | K32: =+((((E32+I32+J32)*6)+F32+G32+H32)*C32)*B32 -> 1960.9397 | L32: =+'1 Estudiantes'!$C$12 -> 86.94 | M32: =+$L$1+L32 -> 371.94
B33: =+B14 -> 1 | C33: =+'1 Estudiantes'!C30 -> 0.8 | D33: =+D14 -> Ocasional Tipo 2 (Técnico Docente) | E33: =+E14*$F$20 -> 1368.09 | F33: =+E33*12/12/2 -> 684.045 | G33: =+(400/2)*$F$1*1.05 -> 210 | H33: =+E33*12/24/2 -> 342.0225 | I33: =+E33*8.33% -> 113.9619 | J33: =+E33*11.15% -> 152.54204 | K33: =+((((E33+I33+J33)*6)+F33+G33+H33)*C33)*B33 -> 8834.9049 | L33: =+'1 Estudiantes'!$C$12 -> 86.94 | M33: =+$L$1+L33 -> 371.94
B34: =+L34/M34 -> 0.23374738 | C34: =+C15 -> 1 | D34: =+D15 -> Bibliotecario | E34: =+E15*$F$20 -> 810.72 | F34: =+E34*12/12/2 -> 405.36 | G34: =+(400/2)*$F$1*1.05 -> 210 | H34: =+E34*12/24/2 -> 202.68 | I34: =+E34*8.33% -> 67.532976 | J34: =+E34*11.15% -> 90.39528 | K34: =+((((E34+I34+J34)*6)+F34+G34+H34)*C34)*B34 -> 1549.7286 | L34: =+'1 Estudiantes'!$C$12 -> 86.94 | M34: =+$L$1+L34 -> 371.94
B35: =+L35/M35 -> 0.23374738 | C35: =+C16 -> 2 | D35: =+D16 -> Auxiliar de Servicio | E35: =+E16*$F$20 -> 456.03 | F35: =+E35*12/12/2 -> 228.015 | G35: =+(400/2)*$F$1*1.05 -> 210 | H35: =+E35*12/24/2 -> 114.0075 | I35: =+E35*8.33% -> 37.987299 | J35: =+E35*11.15% -> 50.847345 | K35: =+((((E35+I35+J35)*6)+F35+G35+H35)*C35)*B35 -> 1786.3958 | L35: =+'1 Estudiantes'!$C$12 -> 86.94 | M35: =+$L$1+L35 -> 371.94
B36: =+L36/M36 -> 0.23374738 | C36: =+C17 -> 1 | D36: =+D17 -> Guardia | E36: =+E17*$F$20 -> 658.71 | F36: =+E36*12/12/2 -> 329.355 | G36: =+(400/2)*$F$1*1.05 -> 210 | H36: =+E36*12/24/2 -> 164.6775 | I36: =+E36*8.33% -> 54.870543 | J36: =+E36*11.15% -> 73.446165 | K36: =+((((E36+I36+J36)*6)+F36+G36+H36)*C36)*B36 -> 1268.3583 | L36: =+'1 Estudiantes'!$C$12 -> 86.94 | M36: =+$L$1+L36 -> 371.94
D37: =+D18 -> TOTAL | E37: =SUM(E22:E36) -> 22084.013 | F37: =SUM(F22:F36) -> 11042.006 | G37: =SUM(G22:G36) -> 3150 | H37: =SUM(H22:H36) -> 5521.0032 | I37: =SUM(I22:I36) -> 1839.5983 | K37: =SUM(K22:K36) -> 100540.24
B39: =+'1 Estudiantes'!D3 -> 2024 | E39: INFLACIÓN | F39: =+Inflación!C12/100+1 -> 1.0143
C40: Nº | D40: CARGO | E40: SUELDO MENSUAL | F40: DECIMO XIII | G40: DECIMO IV | H40: VACACIONES | I40: FONDOS DE RESERVA MENSUAL | J40: APORTE PATRONAL MENSUAL | K40: TOTAL
B41: =+L41/M41 -> 0.27494222 | C41: =+C3 -> 1 | D41: =+D22 -> Decano | E41: =+E22 -> 3931.992 | F41: =+E41*12/12/2 -> 1965.996 | G41: =+G22 -> 210 | H41: =+E41*12/24/2 -> 982.998 | I41: =+E41*8.33% -> 327.53493 | J41: =+E41*11.15% -> 438.41711 | K41: =+((((E41+I41+J41)*6)+F41+G41+H41)*C41)*B41 -> 8618.5197 | L41: =+'1 Estudiantes'!$D$12 -> 108.07212 | M41: =+$L$1+L41 -> 393.07212
B42: =+L42/M42 -> 0.27494222 | C42: =+C4 -> 1 | D42: =+D23 -> Subdecano | E42: =+E23 -> 2918.592 | F42: =+E42*12/12/2 -> 1459.296 | G42: =+G23 -> 210 | H42: =+E42*12/24/2 -> 729.648 | I42: =+E42*8.33% -> 243.11871 | J42: =+E42*11.15% -> 325.42301 | K42: =+((((E42+I42+J42)*6)+F42+G42+H42)*C42)*B42 -> 6412.1326 | L42: =+'1 Estudiantes'!$D$12 -> 108.07212 | M42: =+$L$1+L42 -> 393.07212
B43: =+B24 -> 1 | C43: =+C5 -> 1 | D43: =+D24 -> Director de Carrera | E43: =+E24 -> 2229.48 | F43: =+E43*12/12/2 -> 1114.74 | G43: =+G24 -> 210 | H43: =+E43*12/24/2 -> 557.37 | I43: =+E43*8.33% -> 185.71568 | J43: =+E43*11.15% -> 248.58702 | K43: =+((((E43+I43+J43)*6)+F43+G43+H43)*C43)*B43 -> 17864.806 | L43: =+'1 Estudiantes'!$D$12 -> 108.07212 | M43: =+$L$1+L43 -> 393.07212
B44: =+L44/M44 -> 0.27494222 | C44: =+C6 -> 1 | D44: =+D25 -> Secretario | E44: =+E25 -> 1013.4 | F44: =+E44*12/12/2 -> 506.7 | G44: =+G25 -> 210 | H44: =+E44*12/24/2 -> 253.35 | I44: =+E44*8.33% -> 84.41622 | J44: =+E44*11.15% -> 112.9941 | K44: =+((((E44+I44+J44)*6)+F44+G44+H44)*C44)*B44 -> 2264.1249 | L44: =+'1 Estudiantes'!$D$12 -> 108.07212 | M44: =+$L$1+L44 -> 393.07212
B45: =+L45/M45 -> 0.27494222 | C45: =+C7 -> 1 | D45: =+D26 -> Auxiliar de Secretaria | E45: =+E26 -> 861.39 | F45: =+E45*12/12/2 -> 430.695 | G45: =+G26 -> 210 | H45: =+E45*12/24/2 -> 215.3475 | I45: =+E45*8.33% -> 71.753787 | J45: =+E45*11.15% -> 96.044985 | K45: =+((((E45+I45+J45)*6)+F45+G45+H45)*C45)*B45 -> 1933.1669 | L45: =+'1 Estudiantes'!$D$12 -> 108.07212 | M45: =+$L$1+L45 -> 393.07212
B46: =+L46/M46 -> 0.27494222 | C46: =+C8 -> 1 | D46: =+D27 -> Coordinador | E46: =+E27 -> 912.06 | F46: =+E46*12/12/2 -> 456.03 | G46: =+G27 -> 210 | H46: =+E46*12/24/2 -> 228.015 | I46: =+E46*8.33% -> 75.974598 | J46: =+E46*11.15% -> 101.69469 | K46: =+((((E46+I46+J46)*6)+F46+G46+H46)*C46)*B46 -> 2043.4862 | L46: =+'1 Estudiantes'!$D$12 -> 108.07212 | M46: =+$L$1+L46 -> 393.07212
B47: =+L47/M47 -> 0.27494222 | C47: =+C9 -> 1 | D47: =+D28 -> Bienestar Estudiantil | E47: =+E28 -> 912.06 | F47: =+E47*12/12/2 -> 456.03 | G47: =+G28 -> 210 | H47: =+E47*12/24/2 -> 228.015 | I47: =+E47*8.33% -> 75.974598 | J47: =+E47*11.15% -> 101.69469 | K47: =+((((E47+I47+J47)*6)+F47+G47+H47)*C47)*B47 -> 2043.4862 | L47: =+'1 Estudiantes'!$D$12 -> 108.07212 | M47: =+$L$1+L47 -> 393.07212
B48: =+B29 -> 1 | C48: =+'5 Demanda'!D15 -> 1.0666667 | D48: =+D29 -> Tiempo Completo PhD | E48: =+E29 -> 2837.52 | F48: =+E48*12/12/2 -> 1418.76 | G48: =+G29 -> 210 | H48: =+E48*12/24/2 -> 709.38 | I48: =+E48*8.33% -> 236.36542 | J48: =+E48*11.15% -> 316.38348 | K48: =+((((E48+I48+J48)*6)+F48+G48+H48)*C48)*B48 -> 24191.737 | L48: =+'1 Estudiantes'!$D$12 -> 108.07212 | M48: =+$L$1+L48 -> 393.07212
B49: =+B30 -> 1 | C49: =+'5 Demanda'!D16 -> 2.6666667 | D49: =+D30 -> Tiempo Completo Mgs. | E49: =+E30 -> 1824.12 | F49: =+E49*12/12/2 -> 912.06 | G49: =+G30 -> 210 | H49: =+E49*12/24/2 -> 456.03 | I49: =+E49*8.33% -> 151.9492 | J49: =+E49*11.15% -> 203.38938 | K49: =+((((E49+I49+J49)*6)+F49+G49+H49)*C49)*B49 -> 39079.577 | L49: =+'1 Estudiantes'!$D$12 -> 108.07212 | M49: =+$L$1+L49 -> 393.07212
B50: =+B31 -> 1 | C50: =+'5 Demanda'!D17 -> 0 | D50: =+D31 -> Medio Tiempo | E50: =+E31 -> 912.06 | F50: =+E50*12/12/2 -> 456.03 | G50: =+G31 -> 210 | H50: =+E50*12/24/2 -> 228.015 | I50: =+E50*8.33% -> 75.974598 | J50: =+E50*11.15% -> 101.69469 | K50: =+((((E50+I50+J50)*6)+F50+G50+H50)*C50)*B50 -> 0 | L50: =+'1 Estudiantes'!$D$12 -> 108.07212 | M50: =+$L$1+L50 -> 393.07212
B51: =+B32 -> 1 | C51: =+'5 Demanda'!D18 -> 0.71111111 | D51: =+D32 -> Tiempo Parcial | E51: =+E32 -> 437.7888 | F51: =+E51*12/12/2 -> 218.8944 | G51: =+G32 -> 210 | H51: =+E51*12/24/2 -> 109.4472 | I51: =+E51*8.33% -> 36.467807 | J51: =+E51*11.15% -> 48.813451 | K51: =+((((E51+I51+J51)*6)+F51+G51+H51)*C51)*B51 -> 2614.5863 | L51: =+'1 Estudiantes'!$D$12 -> 108.07212 | M51: =+$L$1+L51 -> 393.07212
B52: =+B33 -> 1 | C52: =+'1 Estudiantes'!D30 -> 1.1 | D52: =+D33 -> Ocasional Tipo 2 (Técnico Docente) | E52: =+E33 -> 1368.09 | F52: =+E52*12/12/2 -> 684.045 | G52: =+G33 -> 210 | H52: =+E52*12/24/2 -> 342.0225 | I52: =+E52*8.33% -> 113.9619 | J52: =+E52*11.15% -> 152.54204 | K52: =+((((E52+I52+J52)*6)+F52+G52+H52)*C52)*B52 -> 12147.994 | L52: =+'1 Estudiantes'!$D$12 -> 108.07212 | M52: =+$L$1+L52 -> 393.07212
B53: =+L53/M53 -> 0.27494222 | C53: =+C15 -> 1 | D53: =+D34 -> Bibliotecario | E53: =+E34 -> 810.72 | F53: =+E53*12/12/2 -> 405.36 | G53: =+G34 -> 210 | H53: =+E53*12/24/2 -> 202.68 | I53: =+E53*8.33% -> 67.532976 | J53: =+E53*11.15% -> 90.39528 | K53: =+((((E53+I53+J53)*6)+F53+G53+H53)*C53)*B53 -> 1822.8475 | L53: =+'1 Estudiantes'!$D$12 -> 108.07212 | M53: =+$L$1+L53 -> 393.07212
B54: =+L54/M54 -> 0.27494222 | C54: =+C16 -> 2 | D54: =+D35 -> Auxiliar de Servicio | E54: =+E35 -> 456.03 | F54: =+E54*12/12/2 -> 228.015 | G54: =+G35 -> 210 | H54: =+E54*12/24/2 -> 114.0075 | I54: =+E54*8.33% -> 37.987299 | J54: =+E54*11.15% -> 50.847345 | K54: =+((((E54+I54+J54)*6)+F54+G54+H54)*C54)*B54 -> 2101.2241 | L54: =+'1 Estudiantes'!$D$12 -> 108.07212 | M54: =+$L$1+L54 -> 393.07212
B55: =+L55/M55 -> 0.27494222 | C55: =+C17 -> 1 | D55: =+D36 -> Guardia | E55: =+E36 -> 658.71 | F55: =+E55*12/12/2 -> 329.355 | G55: =+G36 -> 210 | H55: =+E55*12/24/2 -> 164.6775 | I55: =+E55*8.33% -> 54.870543 | J55: =+E55*11.15% -> 73.446165 | K55: =+((((E55+I55+J55)*6)+F55+G55+H55)*C55)*B55 -> 1491.8895 | L55: =+'1 Estudiantes'!$D$12 -> 108.07212 | M55: =+$L$1+L55 -> 393.07212
D56: =+D37 -> TOTAL | E56: =SUM(E41:E55) -> 22084.013 | F56: =SUM(F41:F55) -> 11042.006 | G56: =SUM(G41:G55) -> 3150 | H56: =SUM(H41:H55) -> 5521.0032 | I56: =SUM(I41:I55) -> 1839.5983 | K56: =SUM(K41:K55) -> 124629.58
B58: =+'1 Estudiantes'!E3 -> 2024 | E58: INFLACIÓN | F58: =+Inflación!C12/100+1 -> 1.0143
C59: Nº | D59: CARGO | E59: SUELDO MENSUAL | F59: DECIMO XIII | G59: DECIMO IV | H59: VACACIONES | I59: FONDOS DE RESERVA MENSUAL | J59: APORTE PATRONAL MENSUAL | K59: TOTAL
B60: =+L60/M60 -> 0.35527475 | C60: =+C3 -> 1 | D60: =+D3 -> Decano | E60: =+E41*$F$58 -> 3988.2195 | F60: =+E60*12/12/2 -> 1994.1097 | G60: =+G41*1.05 -> 220.5 | H60: =+E60*12/24/2 -> 997.05487 | I60: =+E60*8.33% -> 332.21868 | J60: =+E60*11.15% -> 444.68647 | K60: =+((((E60+I60+J60)*6)+F60+G60+H60)*C60)*B60 -> 11298.594 | L60: =+'1 Estudiantes'!$E$12 -> 157.04876 | M60: =+$L$1+L60 -> 442.04876
B61: =+L61/M61 -> 0.35527475 | C61: =+C4 -> 1 | D61: =+D4 -> Subdecano | E61: =+E42*$F$58 -> 2960.3279 | F61: =+E61*12/12/2 -> 1480.1639 | G61: =+G42*1.05 -> 220.5 | H61: =+E61*12/24/2 -> 740.08197 | I61: =+E61*8.33% -> 246.59531 | J61: =+E61*11.15% -> 330.07656 | K61: =+((((E61+I61+J61)*6)+F61+G61+H61)*C61)*B61 -> 8406.7756 | L61: =+'1 Estudiantes'!$E$12 -> 157.04876 | M61: =+$L$1+L61 -> 442.04876
B62: =+B43 -> 1 | C62: =+C5 -> 1 | D62: =+D5 -> Director de Carrera | E62: =+E43*$F$58 -> 2261.3616 | F62: =+E62*12/12/2 -> 1130.6808 | G62: =+G43*1.05 -> 220.5 | H62: =+E62*12/24/2 -> 565.34039 | I62: =+E62*8.33% -> 188.37142 | J62: =+E62*11.15% -> 252.14181 | K62: =+((((E62+I62+J62)*6)+F62+G62+H62)*C62)*B62 -> 18127.77 | L62: =+'1 Estudiantes'!$E$12 -> 157.04876 | M62: =+$L$1+L62 -> 442.04876
B63: =+L63/M63 -> 0.35527475 | C63: =+C6 -> 1 | D63: =+D6 -> Secretario | E63: =+E44*$F$58 -> 1027.8916 | F63: =+E63*12/12/2 -> 513.94581 | G63: =+G44*1.05 -> 220.5 | H63: =+E63*12/24/2 -> 256.97291 | I63: =+E63*8.33% -> 85.623372 | J63: =+E63*11.15% -> 114.60992 | K63: =+((((E63+I63+J63)*6)+F63+G63+H63)*C63)*B63 -> 2970.1566 | L63: =+'1 Estudiantes'!$E$12 -> 157.04876 | M63: =+$L$1+L63 -> 442.04876
B64: =+L64/M64 -> 0.35527475 | C64: =+C7 -> 1 | D64: =+D7 -> Auxiliar de Secretaria | E64: =+E45*$F$58 -> 873.70788 | F64: =+E64*12/12/2 -> 436.85394 | G64: =+G45*1.05 -> 220.5 | H64: =+E64*12/24/2 -> 218.42697 | I64: =+E64*8.33% -> 72.779866 | J64: =+E64*11.15% -> 97.418428 | K64: =+((((E64+I64+J64)*6)+F64+G64+H64)*C64)*B64 -> 2536.3839 | L64: =+'1 Estudiantes'!$E$12 -> 157.04876 | M64: =+$L$1+L64 -> 442.04876
B65: =+L65/M65 -> 0.35527475 | C65: =+C8 -> 1 | D65: =+D8 -> Coordinador | E65: =+E46*$F$58 -> 925.10246 | F65: =+E65*12/12/2 -> 462.55123 | G65: =+G46*1.05 -> 220.5 | H65: =+E65*12/24/2 -> 231.27561 | I65: =+E65*8.33% -> 77.061035 | J65: =+E65*11.15% -> 103.14892 | K65: =+((((E65+I65+J65)*6)+F65+G65+H65)*C65)*B65 -> 2680.9748 | L65: =+'1 Estudiantes'!$E$12 -> 157.04876 | M65: =+$L$1+L65 -> 442.04876
B66: =+L66/M66 -> 0.35527475 | C66: =+C9 -> 1 | D66: =+D9 -> Bienestar Estudiantil | E66: =+E47*$F$58 -> 925.10246 | F66: =+E66*12/12/2 -> 462.55123 | G66: =+G47*1.05 -> 220.5 | H66: =+E66*12/24/2 -> 231.27561 | I66: =+E66*8.33% -> 77.061035 | J66: =+E66*11.15% -> 103.14892 | K66: =+((((E66+I66+J66)*6)+F66+G66+H66)*C66)*B66 -> 2680.9748 | L66: =+'1 Estudiantes'!$E$12 -> 157.04876 | M66: =+$L$1+L66 -> 442.04876
B67: =+B48 -> 1 | C67: =+'5 Demanda'!E15 -> 1.6266667 | D67: =+D10 -> Tiempo Completo PhD | E67: =+E48*$F$58 -> 2878.0965 | F67: =+E67*12/12/2 -> 1439.0483 | G67: =+G48*1.05 -> 220.5 | H67: =+E67*12/24/2 -> 719.52413 | I67: =+E67*8.33% -> 239.74544 | J67: =+E67*11.15% -> 320.90776 | K67: =+((((E67+I67+J67)*6)+F67+G67+H67)*C67)*B67 -> 37432.155 | L67: =+'1 Estudiantes'!$E$12 -> 157.04876 | M67: =+$L$1+L67 -> 442.04876
B68: =+B49 -> 1 | C68: =+'5 Demanda'!E16 -> 4.0666667 | D68: =+D11 -> Tiempo Completo Mgs. | E68: =+E49*$F$58 -> 1850.2049 | F68: =+E68*12/12/2 -> 925.10246 | G68: =+G49*1.05 -> 220.5 | H68: =+E68*12/24/2 -> 462.55123 | I68: =+E68*8.33% -> 154.12207 | J68: =+E68*11.15% -> 206.29785 | K68: =+((((E68+I68+J68)*6)+F68+G68+H68)*C68)*B68 -> 60479.071 | L68: =+'1 Estudiantes'!$E$12 -> 157.04876 | M68: =+$L$1+L68 -> 442.04876
B69: =+B50 -> 1 | C69: =+'5 Demanda'!E17 -> 0 | D69: =+D12 -> Medio Tiempo | E69: =+E50*$F$58 -> 925.10246 | F69: =+E69*12/12/2 -> 462.55123 | G69: =+G50*1.05 -> 220.5 | H69: =+E69*12/24/2 -> 231.27561 | I69: =+E69*8.33% -> 77.061035 | J69: =+E69*11.15% -> 103.14892 | K69: =+((((E69+I69+J69)*6)+F69+G69+H69)*C69)*B69 -> 0 | L69: =+'1 Estudiantes'!$E$12 -> 157.04876 | M69: =+$L$1+L69 -> 442.04876
B70: =+B51 -> 1 | C70: =+'5 Demanda'!E18 -> 1.0844444 | D70: =+D13 -> Tiempo Parcial | E70: =+E51*$F$58 -> 444.04918 | F70: =+E70*12/12/2 -> 222.02459 | G70: =+G51*1.05 -> 220.5 | H70: =+E70*12/24/2 -> 111.01229 | I70: =+E70*8.33% -> 36.989297 | J70: =+E70*11.15% -> 49.511484 | K70: =+((((E70+I70+J70)*6)+F70+G70+H70)*C70)*B70 -> 4052.3917 | L70: =+'1 Estudiantes'!$E$12 -> 157.04876 | M70: =+$L$1+L70 -> 442.04876
B71: =+B52 -> 1 | C71: =+'1 Estudiantes'!E30 -> 1.75 | D71: =+D14 -> Ocasional Tipo 2 (Técnico Docente) | E71: =+E52*$F$58 -> 1387.6537 | F71: =+E71*12/12/2 -> 693.82684 | G71: =+G52*1.05 -> 220.5 | H71: =+E71*12/24/2 -> 346.91342 | I71: =+E71*8.33% -> 115.59155 | J71: =+E71*11.15% -> 154.72339 | K71: =+((((E71+I71+J71)*6)+F71+G71+H71)*C71)*B71 -> 19615.841 | L71: =+'1 Estudiantes'!$E$12 -> 157.04876 | M71: =+$L$1+L71 -> 442.04876
B72: =+L72/M72 -> 0.35527475 | C72: =+C15 -> 1 | D72: =+D15 -> Bibliotecario | E72: =+E53*$F$58 -> 822.3133 | F72: =+E72*12/12/2 -> 411.15665 | G72: =+G53*1.05 -> 220.5 | H72: =+E72*12/24/2 -> 205.57832 | I72: =+E72*8.33% -> 68.498698 | J72: =+E72*11.15% -> 91.687933 | K72: =+((((E72+I72+J72)*6)+F72+G72+H72)*C72)*B72 -> 2391.7929 | L72: =+'1 Estudiantes'!$E$12 -> 157.04876 | M72: =+$L$1+L72 -> 442.04876
B73: =+L73/M73 -> 0.35527475 | C73: =+C16 -> 2 | D73: =+D16 -> Auxiliar de Servicio | E73: =+E54*$F$58 -> 462.55123 | F73: =+E73*12/12/2 -> 231.27561 | G73: =+G54*1.05 -> 220.5 | H73: =+E73*12/24/2 -> 115.63781 | I73: =+E73*8.33% -> 38.530517 | J73: =+E73*11.15% -> 51.574462 | K73: =+((((E73+I73+J73)*6)+F73+G73+H73)*C73)*B73 -> 2759.3129 | L73: =+'1 Estudiantes'!$E$12 -> 157.04876 | M73: =+$L$1+L73 -> 442.04876
B74: =+L74/M74 -> 0.35527475 | C74: =+C17 -> 1 | D74: =+D17 -> Guardia | E74: =+E55*$F$58 -> 668.12955 | F74: =+E74*12/12/2 -> 334.06478 | G74: =+G55*1.05 -> 220.5 | H74: =+E74*12/24/2 -> 167.03239 | I74: =+E74*8.33% -> 55.655192 | J74: =+E74*11.15% -> 74.496445 | K74: =+((((E74+I74+J74)*6)+F74+G74+H74)*C74)*B74 -> 1958.0201 | L74: =+'1 Estudiantes'!$E$12 -> 157.04876 | M74: =+$L$1+L74 -> 442.04876
D75: =+D56 -> TOTAL | E75: =SUM(E60:E74) -> 22399.814 | F75: =SUM(F60:F74) -> 11199.907 | G75: =SUM(G60:G74) -> 3307.5 | H75: =SUM(H60:H74) -> 5599.9535 | I75: =SUM(I60:I74) -> 1865.9045 | K75: =SUM(K60:K74) -> 177390.21
B77: =+'1 Estudiantes'!F3 -> 2025 | E77: INFLACIÓN | F77: =+Inflación!C13/100+1 -> 1.0331
C78: Nº | D78: CARGO | E78: SUELDO MENSUAL | F78: DECIMO XIII | G78: DECIMO IV | H78: VACACIONES | I78: FONDOS DE RESERVA MENSUAL | J78: APORTE PATRONAL MENSUAL | K78: TOTAL
B79: =+L79/M79 -> 0.37504083 | C79: =+C3 -> 1 | D79: =+D22 -> Decano | E79: =+E60 -> 3988.2195 | F79: =+E79*12/12/2 -> 1994.1097 | G79: =+G60 -> 220.5 | H79: =+E79*12/24/2 -> 997.05487 | I79: =+E79*8.33% -> 332.21868 | J79: =+E79*11.15% -> 444.68647 | K79: =+((((E79+I79+J79)*6)+F79+G79+H79)*C79)*B79 -> 11927.203 | L79: =+'1 Estudiantes'!$F$12 -> 171.02979 | M79: =+$L$1+L79 -> 456.02979
B80: =+L80/M80 -> 0.37504083 | C80: =+C4 -> 1 | D80: =+D23 -> Subdecano | E80: =+E61 -> 2960.3279 | F80: =+E80*12/12/2 -> 1480.1639 | G80: =+G61 -> 220.5 | H80: =+E80*12/24/2 -> 740.08197 | I80: =+E80*8.33% -> 246.59531 | J80: =+E80*11.15% -> 330.07656 | K80: =+((((E80+I80+J80)*6)+F80+G80+H80)*C80)*B80 -> 8874.4952 | L80: =+'1 Estudiantes'!$F$12 -> 171.02979 | M80: =+$L$1+L80 -> 456.02979
B81: =+B62 -> 1 | C81: =+C5 -> 1 | D81: =+D24 -> Director de Carrera | E81: =+E62 -> 2261.3616 | F81: =+E81*12/12/2 -> 1130.6808 | G81: =+G62 -> 220.5 | H81: =+E81*12/24/2 -> 565.34039 | I81: =+E81*8.33% -> 188.37142 | J81: =+E81*11.15% -> 252.14181 | K81: =+((((E81+I81+J81)*6)+F81+G81+H81)*C81)*B81 -> 18127.77 | L81: =+'1 Estudiantes'!$F$12 -> 171.02979 | M81: =+$L$1+L81 -> 456.02979
B82: =+L82/M82 -> 0.37504083 | C82: =+C6 -> 1 | D82: =+D25 -> Secretario | E82: =+E63 -> 1027.8916 | F82: =+E82*12/12/2 -> 513.94581 | G82: =+G63 -> 220.5 | H82: =+E82*12/24/2 -> 256.97291 | I82: =+E82*8.33% -> 85.623372 | J82: =+E82*11.15% -> 114.60992 | K82: =+((((E82+I82+J82)*6)+F82+G82+H82)*C82)*B82 -> 3135.4044 | L82: =+'1 Estudiantes'!$F$12 -> 171.02979 | M82: =+$L$1+L82 -> 456.02979
B83: =+L83/M83 -> 0.37504083 | C83: =+C7 -> 1 | D83: =+D26 -> Auxiliar de Secretaria | E83: =+E64 -> 873.70788 | F83: =+E83*12/12/2 -> 436.85394 | G83: =+G64 -> 220.5 | H83: =+E83*12/24/2 -> 218.42697 | I83: =+E83*8.33% -> 72.779866 | J83: =+E83*11.15% -> 97.418428 | K83: =+((((E83+I83+J83)*6)+F83+G83+H83)*C83)*B83 -> 2677.4982 | L83: =+'1 Estudiantes'!$F$12 -> 171.02979 | M83: =+$L$1+L83 -> 456.02979
B84: =+L84/M84 -> 0.37504083 | C84: =+C8 -> 1 | D84: =+D27 -> Coordinador | E84: =+E65 -> 925.10246 | F84: =+E84*12/12/2 -> 462.55123 | G84: =+G65 -> 220.5 | H84: =+E84*12/24/2 -> 231.27561 | I84: =+E84*8.33% -> 77.061035 | J84: =+E84*11.15% -> 103.14892 | K84: =+((((E84+I84+J84)*6)+F84+G84+H84)*C84)*B84 -> 2830.1336 | L84: =+'1 Estudiantes'!$F$12 -> 171.02979 | M84: =+$L$1+L84 -> 456.02979
B85: =+L85/M85 -> 0.37504083 | C85: =+C9 -> 1 | D85: =+D28 -> Bienestar Estudiantil | E85: =+E66 -> 925.10246 | F85: =+E85*12/12/2 -> 462.55123 | G85: =+G66 -> 220.5 | H85: =+E85*12/24/2 -> 231.27561 | I85: =+E85*8.33% -> 77.061035 | J85: =+E85*11.15% -> 103.14892 | K85: =+((((E85+I85+J85)*6)+F85+G85+H85)*C85)*B85 -> 2830.1336 | L85: =+'1 Estudiantes'!$F$12 -> 171.02979 | M85: =+$L$1+L85 -> 456.02979
B86: =+B67 -> 1 | C86: =+'5 Demanda'!F15 -> 1.9066667 | D86: =+D29 -> Tiempo Completo PhD | E86: =+E67 -> 2878.0965 | F86: =+E86*12/12/2 -> 1439.0483 | G86: =+G67 -> 220.5 | H86: =+E86*12/24/2 -> 719.52413 | I86: =+E86*8.33% -> 239.74544 | J86: =+E86*11.15% -> 320.90776 | K86: =+((((E86+I86+J86)*6)+F86+G86+H86)*C86)*B86 -> 43875.395 | L86: =+'1 Estudiantes'!$F$12 -> 171.02979 | M86: =+$L$1+L86 -> 456.02979
B87: =+B68 -> 1 | C87: =+'5 Demanda'!F16 -> 4.7666667 | D87: =+D30 -> Tiempo Completo Mgs. | E87: =+E68 -> 1850.2049 | F87: =+E87*12/12/2 -> 925.10246 | G87: =+G68 -> 220.5 | H87: =+E87*12/24/2 -> 462.55123 | I87: =+E87*8.33% -> 154.12207 | J87: =+E87*11.15% -> 206.29785 | K87: =+((((E87+I87+J87)*6)+F87+G87+H87)*C87)*B87 -> 70889.403 | L87: =+'1 Estudiantes'!$F$12 -> 171.02979 | M87: =+$L$1+L87 -> 456.02979
B88: =+B69 -> 1 | C88: =+'5 Demanda'!F17 -> 0 | D88: =+D31 -> Medio Tiempo | E88: =+E69 -> 925.10246 | F88: =+E88*12/12/2 -> 462.55123 | G88: =+G69 -> 220.5 | H88: =+E88*12/24/2 -> 231.27561 | I88: =+E88*8.33% -> 77.061035 | J88: =+E88*11.15% -> 103.14892 | K88: =+((((E88+I88+J88)*6)+F88+G88+H88)*C88)*B88 -> 0 | L88: =+'1 Estudiantes'!$F$12 -> 171.02979 | M88: =+$L$1+L88 -> 456.02979
B89: =+B70 -> 1 | C89: =+'5 Demanda'!F18 -> 1.2711111 | D89: =+D32 -> Tiempo Parcial | E89: =+E70 -> 444.04918 | F89: =+E89*12/12/2 -> 222.02459 | G89: =+G70 -> 220.5 | H89: =+E89*12/24/2 -> 111.01229 | I89: =+E89*8.33% -> 36.989297 | J89: =+E89*11.15% -> 49.511484 | K89: =+((((E89+I89+J89)*6)+F89+G89+H89)*C89)*B89 -> 4749.9346 | L89: =+'1 Estudiantes'!$F$12 -> 171.02979 | M89: =+$L$1+L89 -> 456.02979
B90: =+B71 -> 1 | C90: =+'1 Estudiantes'!F30 -> 2.125 | D90: =+D33 -> Ocasional Tipo 2 (Técnico Docente) | E90: =+E71 -> 1387.6537 | F90: =+E90*12/12/2 -> 693.82684 | G90: =+G71 -> 220.5 | H90: =+E90*12/24/2 -> 346.91342 | I90: =+E90*8.33% -> 115.59155 | J90: =+E90*11.15% -> 154.72339 | K90: =+((((E90+I90+J90)*6)+F90+G90+H90)*C90)*B90 -> 23819.236 | L90: =+'1 Estudiantes'!$F$12 -> 171.02979 | M90: =+$L$1+L90 -> 456.02979
B91: =+L91/M91 -> 0.37504083 | C91: =+C15 -> 1 | D91: =+D34 -> Bibliotecario | E91: =+E72 -> 822.3133 | F91: =+E91*12/12/2 -> 411.15665 | G91: =+G72 -> 220.5 | H91: =+E91*12/24/2 -> 205.57832 | I91: =+E91*8.33% -> 68.498698 | J91: =+E91*11.15% -> 91.687933 | K91: =+((((E91+I91+J91)*6)+F91+G91+H91)*C91)*B91 -> 2524.8628 | L91: =+'1 Estudiantes'!$F$12 -> 171.02979 | M91: =+$L$1+L91 -> 456.02979
B92: =+L92/M92 -> 0.37504083 | C92: =+C16 -> 2 | D92: =+D35 -> Auxiliar de Servicio | E92: =+E73 -> 462.55123 | F92: =+E92*12/12/2 -> 231.27561 | G92: =+G73 -> 220.5 | H92: =+E92*12/24/2 -> 115.63781 | I92: =+E92*8.33% -> 38.530517 | J92: =+E92*11.15% -> 51.574462 | K92: =+((((E92+I92+J92)*6)+F92+G92+H92)*C92)*B92 -> 2912.8301 | L92: =+'1 Estudiantes'!$F$12 -> 171.02979 | M92: =+$L$1+L92 -> 456.02979
B93: =+L93/M93 -> 0.37504083 | C93: =+C17 -> 1 | D93: =+D36 -> Guardia | E93: =+E74 -> 668.12955 | F93: =+E93*12/12/2 -> 334.06478 | G93: =+G74 -> 220.5 | H93: =+E93*12/24/2 -> 167.03239 | I93: =+E93*8.33% -> 55.655192 | J93: =+E93*11.15% -> 74.496445 | K93: =+((((E93+I93+J93)*6)+F93+G93+H93)*C93)*B93 -> 2066.9566 | L93: =+'1 Estudiantes'!$F$12 -> 171.02979 | M93: =+$L$1+L93 -> 456.02979
D94: TOTAL | E94: =SUM(E79:E93) -> 22399.814 | F94: =SUM(F79:F93) -> 11199.907 | G94: =SUM(G79:G93) -> 3307.5 | H94: =SUM(H79:H93) -> 5599.9535 | I94: =SUM(I79:I93) -> 1865.9045 | K94: =SUM(K79:K93) -> 201241.26
B96: =+'1 Estudiantes'!G3 -> 2025 | E96: INFLACIÓN | F96: =+Inflación!C13/100+1 -> 1.0331
C97: Nº | D97: CARGO | E97: SUELDO MENSUAL | F97: DECIMO XIII | G97: DECIMO IV | H97: VACACIONES | I97: FONDOS DE RESERVA MENSUAL | J97: APORTE PATRONAL MENSUAL | K97: TOTAL
B98: =+L98/M98 -> 0.4294848 | C98: =+C3 -> 1 | D98: =+D3 -> Decano | E98: =+E79*$F$96 -> 4120.2296 | F98: =+E98*12/12/2 -> 2060.1148 | G98: =+G79*1.05 -> 231.525 | H98: =+E98*12/24/2 -> 1030.0574 | I98: =+E98*8.33% -> 343.21512 | J98: =+E98*11.15% -> 459.40559 | K98: =+((((E98+I98+J98)*6)+F98+G98+H98)*C98)*B98 -> 14112.355 | L98: =+'1 Estudiantes'!$G$12 -> 214.54848 | M98: =+$L$1+L98 -> 499.54848
B99: =+L99/M99 -> 0.4294848 | C99: =+C4 -> 1 | D99: =+D4 -> Subdecano | E99: =+E80*$F$96 -> 3058.3147 | F99: =+E99*12/12/2 -> 1529.1574 | G99: =+G80*1.05 -> 231.525 | H99: =+E99*12/24/2 -> 764.57868 | I99: =+E99*8.33% -> 254.75762 | J99: =+E99*11.15% -> 341.00209 | K99: =+((((E99+I99+J99)*6)+F99+G99+H99)*C99)*B99 -> 10500.778 | L99: =+'1 Estudiantes'!$G$12 -> 214.54848 | M99: =+$L$1+L99 -> 499.54848
B100: =+B81 -> 1 | C100: =+C5 -> 1 | D100: =+D5 -> Director de Carrera | E100: =+E81*$F$96 -> 2336.2126 | F100: =+E100*12/12/2 -> 1168.1063 | G100: =+G81*1.05 -> 231.525 | H100: =+E100*12/24/2 -> 584.05316 | I100: =+E100*8.33% -> 194.60651 | J100: =+E100*11.15% -> 260.48771 | K100: =+((((E100+I100+J100)*6)+F100+G100+H100)*C100)*B100 -> 18731.526 | L100: =+'1 Estudiantes'!$G$12 -> 214.54848 | M100: =+$L$1+L100 -> 499.54848
B101: =+L101/M101 -> 0.4294848 | C101: =+C6 -> 1 | D101: =+D6 -> Secretario | E101: =+E82*$F$96 -> 1061.9148 | F101: =+E101*12/12/2 -> 530.95742 | G101: =+G82*1.05 -> 231.525 | H101: =+E101*12/24/2 -> 265.47871 | I101: =+E101*8.33% -> 88.457506 | J101: =+E101*11.15% -> 118.4035 | K101: =+((((E101+I101+J101)*6)+F101+G101+H101)*C101)*B101 -> 3711.0133 | L101: =+'1 Estudiantes'!$G$12 -> 214.54848 | M101: =+$L$1+L101 -> 499.54848
B102: =+L102/M102 -> 0.4294848 | C102: =+C7 -> 1 | D102: =+D7 -> Auxiliar de Secretaria | E102: =+E83*$F$96 -> 902.62761 | F102: =+E102*12/12/2 -> 451.3138 | G102: =+G83*1.05 -> 231.525 | H102: =+E102*12/24/2 -> 225.6569 | I102: =+E102*8.33% -> 75.18888 | J102: =+E102*11.15% -> 100.64298 | K102: =+((((E102+I102+J102)*6)+F102+G102+H102)*C102)*B102 -> 3169.2768 | L102: =+'1 Estudiantes'!$G$12 -> 214.54848 | M102: =+$L$1+L102 -> 499.54848
B103: =+L103/M103 -> 0.4294848 | C103: =+C8 -> 1 | D103: =+D8 -> Coordinador | E103: =+E84*$F$96 -> 955.72335 | F103: =+E103*12/12/2 -> 477.86167 | G103: =+G84*1.05 -> 231.525 | H103: =+E103*12/24/2 -> 238.93084 | I103: =+E103*8.33% -> 79.611755 | J103: =+E103*11.15% -> 106.56315 | K103: =+((((E103+I103+J103)*6)+F103+G103+H103)*C103)*B103 -> 3349.8556 | L103: =+'1 Estudiantes'!$G$12 -> 214.54848 | M103: =+$L$1+L103 -> 499.54848
B104: =+L104/M104 -> 0.4294848 | C104: =+C9 -> 1 | D104: =+D9 -> Bienestar Estudiantil | E104: =+E85*$F$96 -> 955.72335 | F104: =+E104*12/12/2 -> 477.86167 | G104: =+G85*1.05 -> 231.525 | H104: =+E104*12/24/2 -> 238.93084 | I104: =+E104*8.33% -> 79.611755 | J104: =+E104*11.15% -> 106.56315 | K104: =+((((E104+I104+J104)*6)+F104+G104+H104)*C104)*B104 -> 3349.8556 | L104: =+'1 Estudiantes'!$G$12 -> 214.54848 | M104: =+$L$1+L104 -> 499.54848
B105: =+B86 -> 1 | C105: =+'5 Demanda'!G15 -> 2.44 | D105: =+D10 -> Tiempo Completo PhD | E105: =+E86*$F$96 -> 2973.3615 | F105: =+E105*12/12/2 -> 1486.6808 | G105: =+G86*1.05 -> 231.525 | H105: =+E105*12/24/2 -> 743.34038 | I105: =+E105*8.33% -> 247.68102 | J105: =+E105*11.15% -> 331.52981 | K105: =+((((E105+I105+J105)*6)+F105+G105+H105)*C105)*B105 -> 58015.832 | L105: =+'1 Estudiantes'!$G$12 -> 214.54848 | M105: =+$L$1+L105 -> 499.54848
...

Sheet Hoja2
B2: No. Alumnos | C2: 60 | D2: 113.7 | E2: 161.7615 | F2: 209.823 | G2: 257.8845 | H2: 305.946 | I2: 354.0075 | J2: 402.069
B3: CARGO/DEPARTAMENTO | C3: 2020 | D3: 2021 | E3: 2021 | F3: 2022 | G3: 2022 | H3: 2023 | I3: 2023 | J3: 2024
A4: ='Planta central'!A4 -> Auditoría | B4: =+UPPER(A4) -> AUDITORÍA | C4: =SUBTOTAL(9,'Planta central'!M4:M8) -> 96.168571 | D4: =SUBTOTAL(9,'Planta central'!N4:N8) -> 278.69652 | E4: =SUBTOTAL(9,'Planta central'!O4:O8) -> 346.43804 | F4: =SUBTOTAL(9,'Planta central'!P4:P8) -> 503.43851 | G4: =SUBTOTAL(9,'Planta central'!Q4:Q8) -> 548.25635 | H4: =SUBTOTAL(9,'Planta central'!R4:R8) -> 687.76068 | I4: =SUBTOTAL(9,'Planta central'!S4:S8) -> 722.88318 | J4: =SUBTOTAL(9,'Planta central'!T4:T8) -> 856.15465
A5: ='Planta central'!A5 -> 0
A6: ='Planta central'!A6 -> 0
A7: ='Planta central'!A7 -> 0
A8: ='Planta central'!A8 -> 0
A9: ='Planta central'!A9 -> TITULACION Y REGISTRO | B9: =+UPPER(A9) -> TITULACION Y REGISTRO | C9: =SUBTOTAL(9,'Planta central'!M9:M13) -> 81.230404 | D9: =SUBTOTAL(9,'Planta central'!N9:N13) -> 235.40571 | E9: =SUBTOTAL(9,'Planta central'!O9:O13) -> 292.62473 | F9: =SUBTOTAL(9,'Planta central'!P9:P13) -> 425.23782 | G9: =SUBTOTAL(9,'Planta central'!Q9:Q13) -> 463.09397 | H9: =SUBTOTAL(9,'Planta central'!R9:R13) -> 580.92865 | I9: =SUBTOTAL(9,'Planta central'!S9:S13) -> 610.59546 | J9: =SUBTOTAL(9,'Planta central'!T9:T13) -> 723.16545
A10: ='Planta central'!A10 -> 0
A11: ='Planta central'!A11 -> 0
A12: ='Planta central'!A12 -> UNIDAD COORDINADORA DE ESTUDIOS NO PRESENCIALES | B12: =+UPPER(A12) -> UNIDAD COORDINADORA DE ESTUDIOS NO PRESENCIALES | C12: =SUBTOTAL(9,'Planta central'!M12:M14) -> 50.287478 | D12: =SUBTOTAL(9,'Planta central'!N12:N14) -> 145.73311 | E12: =SUBTOTAL(9,'Planta central'!O12:O14) -> 181.15581 | F12: =SUBTOTAL(9,'Planta central'!P12:P14) -> 263.25288 | G12: =SUBTOTAL(9,'Planta central'!Q12:Q14) -> 286.68856 | H12: =SUBTOTAL(9,'Planta central'!R12:R14) -> 359.63673 | I12: =SUBTOTAL(9,'Planta central'!S12:S14) -> 378.00262 | J12: =SUBTOTAL(9,'Planta central'!T12:T14) -> 447.69157
A13: ='Planta central'!A13 -> 0
A14: ='Planta central'!A14 -> 0
A15: ='Planta central'!A15 -> Rectorado | B15: =+UPPER(A15) -> RECTORADO | C15: =SUBTOTAL(9,'Planta central'!M15:M17) -> 35.511683 | D15: =SUBTOTAL(9,'Planta central'!N15:N17) -> 102.91286 | E15: =SUBTOTAL(9,'Planta central'!O15:O17) -> 127.92743 | F15: =SUBTOTAL(9,'Planta central'!P15:P17) -> 185.9022 | G15: =SUBTOTAL(9,'Planta central'!Q15:Q17) -> 202.45186 | H15: =SUBTOTAL(9,'Planta central'!R15:R17) -> 253.96592 | I15: =SUBTOTAL(9,'Planta central'!S15:S17) -> 266.93543 | J15: =SUBTOTAL(9,'Planta central'!T15:T17) -> 316.14791
A16: ='Planta central'!A16 -> 0
A17: ='Planta central'!A17 -> 0
A18: ='Planta central'!A18 -> 0
A19: ='Planta central'!A19 -> 0
A20: ='Planta central'!A20 -> 0
A21: ='Planta central'!A21 -> 0
A22: ='Planta central'!A22 -> 0
A23: ='Planta central'!A23 -> 0
A24: ='Planta central'!A24 -> Secretaría General | B24: =+UPPER(A24) -> SECRETARÍA GENERAL | C24: =SUBTOTAL(9,'Planta central'!M24:M34) -> 230.12413 | D24: =SUBTOTAL(9,'Planta central'!N24:N34) -> 666.89974 | E24: =SUBTOTAL(9,'Planta central'!O24:O34) -> 829.0001 | F24: =SUBTOTAL(9,'Planta central'!P24:P34) -> 1204.6904 | G24: =SUBTOTAL(9,'Planta central'!Q24:Q34) -> 1311.9361 | H24: =SUBTOTAL(9,'Planta central'!R24:R34) -> 1645.7594 | I24: =SUBTOTAL(9,'Planta central'!S24:S34) -> 1729.8049 | J24: =SUBTOTAL(9,'Planta central'!T24:T34) -> 2048.7135
A25: ='Planta central'!A25 -> 0
A26: ='Planta central'!A26 -> 0
A27: ='Planta central'!A27 -> 0
A28: ='Planta central'!A28 -> 0
A29: ='Planta central'!A29 -> 0
A30: ='Planta central'!A30 -> 0
A31: ='Planta central'!A31 -> 0
A32: ='Planta central'!A32 -> 0
A33: ='Planta central'!A33 -> 0
A34: ='Planta central'!A34 -> 0
A35: ='Planta central'!A35 -> CENTRO DE APOYO - QUITO | B35: =+UPPER(A35) -> CENTRO DE APOYO - QUITO | C35: =SUBTOTAL(9,'Planta central'!M35:M41) -> 62.162947 | D35: =SUBTOTAL(9,'Planta central'!N35:N41) -> 180.14822 | E35: =SUBTOTAL(9,'Planta central'!O35:O41) -> 223.93605 | F35: =SUBTOTAL(9,'Planta central'!P35:P41) -> 325.42047 | G35: =SUBTOTAL(9,'Planta central'!Q35:Q41) -> 354.39053 | H35: =SUBTOTAL(9,'Planta central'!R35:R41) -> 444.56552 | I35: =SUBTOTAL(9,'Planta central'!S35:S41) -> 467.26855 | J35: =SUBTOTAL(9,'Planta central'!T35:T41) -> 553.41465
A36: ='Planta central'!A36 -> 0
A37: ='Planta central'!A37 -> 0
A38: ='Planta central'!A38 -> 0
A39: ='Planta central'!A39 -> 0
A40: ='Planta central'!A40 -> 0
A41: ='Planta central'!A41 -> 0
A42: ='Planta central'!A42 -> Evaluación Interna | B42: =+UPPER(A42) -> EVALUACIÓN INTERNA | C42: =SUBTOTAL(9,'Planta central'!M42:M48) -> 80.440906 | D42: =SUBTOTAL(9,'Planta central'!N42:N48) -> 233.11775 | E42: =SUBTOTAL(9,'Planta central'!O42:O48) -> 289.78064 | F42: =SUBTOTAL(9,'Planta central'!P42:P48) -> 421.10483 | G42: =SUBTOTAL(9,'Planta central'!Q42:Q48) -> 458.59304 | H42: =SUBTOTAL(9,'Planta central'!R42:R48) -> 575.28246 | I42: =SUBTOTAL(9,'Planta central'!S42:S48) -> 604.66093 | J42: =SUBTOTAL(9,'Planta central'!T42:T48) -> 716.13683
A43: ='Planta central'!A43 -> 0
A44: ='Planta central'!A44 -> 0
A45: ='Planta central'!A45 -> 0
A46: ='Planta central'!A46 -> 0
A47: ='Planta central'!A47 -> 0
A48: ='Planta central'!A48 -> 0
A49: ='Planta central'!A49 -> CENTRO DE APOYO - TENA | B49: =+UPPER(A49) -> CENTRO DE APOYO - TENA | C49: =SUBTOTAL(9,'Planta central'!M49:M54) -> 65.572746 | D49: =SUBTOTAL(9,'Planta central'!N49:N54) -> 190.02982 | E49: =SUBTOTAL(9,'Planta central'!O49:O54) -> 236.21952 | F49: =SUBTOTAL(9,'Planta central'!P49:P54) -> 343.27062 | G49: =SUBTOTAL(9,'Planta central'!Q49:Q54) -> 373.82977 | H49: =SUBTOTAL(9,'Planta central'!R49:R54) -> 468.95109 | I49: =SUBTOTAL(9,'Planta central'!S49:S54) -> 492.89944 | J49: =SUBTOTAL(9,'Planta central'!T49:T54) -> 583.77088
A50: ='Planta central'!A50 -> 0
A51: ='Planta central'!A51 -> 0
A52: ='Planta central'!A52 -> 0
A53: ='Planta central'!A53 -> 0
A54: ='Planta central'!A54 -> 0
A55: ='Planta central'!A55 -> Editorial | B55: =+UPPER(A55) -> EDITORIAL | C55: =SUBTOTAL(9,'Planta central'!M55:M62) -> 75.942407 | D55: =SUBTOTAL(9,'Planta central'!N55:N62) -> 220.0811 | E55: =SUBTOTAL(9,'Planta central'!O55:O62) -> 273.57523 | F55: =SUBTOTAL(9,'Planta central'!P55:P62) -> 397.55537 | G55: =SUBTOTAL(9,'Planta central'!Q55:Q62) -> 432.94713 | H55: =SUBTOTAL(9,'Planta central'!R55:R62) -> 543.11093 | I55: =SUBTOTAL(9,'Planta central'!S55:S62) -> 570.84647 | J55: =SUBTOTAL(9,'Planta central'!T55:T62) -> 676.08829
A56: ='Planta central'!A56 -> 0
A57: ='Planta central'!A57 -> 0
A58: ='Planta central'!A58 -> 0
A59: ='Planta central'!A59 -> 0
A60: ='Planta central'!A60 -> 0
A61: ='Planta central'!A61 -> 0
A62: ='Planta central'!A62 -> 0
A63: ='Planta central'!A63 -> Seguridad Ocupacional | B63: =+UPPER(A63) -> SEGURIDAD OCUPACIONAL | C63: =SUBTOTAL(9,'Planta central'!M63:M65) -> 36.068804 | D63: =SUBTOTAL(9,'Planta central'!N63:N65) -> 104.52739 | E63: =SUBTOTAL(9,'Planta central'!O63:O65) -> 129.9344 | F63: =SUBTOTAL(9,'Planta central'!P63:P65) -> 188.8187 | G63: =SUBTOTAL(9,'Planta central'!Q63:Q65) -> 205.628 | H63: =SUBTOTAL(9,'Planta central'!R63:R65) -> 257.95023 | I63: =SUBTOTAL(9,'Planta central'!S63:S65) -> 271.12321 | J63: =SUBTOTAL(9,'Planta central'!T63:T65) -> 321.10776
A64: ='Planta central'!A64 -> 0
A65: ='Planta central'!A65 -> 0
A66: ='Planta central'!A66 -> CENTRO DE APOYO - ZAMORA | B66: =+UPPER(A66) -> CENTRO DE APOYO - ZAMORA | C66: =SUBTOTAL(9,'Planta central'!M66:M70) -> 53.532121 | D66: =SUBTOTAL(9,'Planta central'!N66:N70) -> 155.13609 | E66: =SUBTOTAL(9,'Planta central'!O66:O70) -> 192.84433 | F66: =SUBTOTAL(9,'Planta central'!P66:P70) -> 280.23845 | G66: =SUBTOTAL(9,'Planta central'!Q66:Q70) -> 305.18625 | H66: =SUBTOTAL(9,'Planta central'!R66:R70) -> 382.84117 | I66: =SUBTOTAL(9,'Planta central'!S66:S70) -> 402.39207 | J66: =SUBTOTAL(9,'Planta central'!T66:T70) -> 476.57747
A67: ='Planta central'!A67 -> 0
A68: ='Planta central'!A68 -> 0
A69: ='Planta central'!A69 -> 0
A70: ='Planta central'!A70 -> 0
A71: ='Planta central'!A71 -> Dirección de Planificación | B71: =+UPPER(A71) -> DIRECCIÓN DE PLANIFICACIÓN | C71: =SUBTOTAL(9,'Planta central'!M71:M80) -> 116.71973 | D71: =SUBTOTAL(9,'Planta central'!N71:N80) -> 338.25377 | E71: =SUBTOTAL(9,'Planta central'!O71:O80) -> 420.47162 | F71: =SUBTOTAL(9,'Planta central'!P71:P80) -> 611.02297 | G71: =SUBTOTAL(9,'Planta central'!Q71:Q80) -> 665.41836 | H71: =SUBTOTAL(9,'Planta central'!R71:R80) -> 834.73467 | I71: =SUBTOTAL(9,'Planta central'!S71:S80) -> 877.36282 | J71: =SUBTOTAL(9,'Planta central'!T71:T80) -> 1039.1143
A72: ='Planta central'!A72 -> 0
A73: ='Planta central'!A73 -> 0
A74: ='Planta central'!A74 -> 0
A75: ='Planta central'!A75 -> 0
A76: ='Planta central'!A76 -> 0
A77: ='Planta central'!A77 -> 0
A78: ='Planta central'!A78 -> 0
A79: ='Planta central'!A79 -> 0
A80: ='Planta central'!A80 -> 0
A81: ='Planta central'!A81 -> Gestión de Calidad | B81: =+UPPER(A81) -> GESTIÓN DE CALIDAD | C81: =SUBTOTAL(9,'Planta central'!M81:M85) -> 51.029329 | D81: =SUBTOTAL(9,'Planta central'!N81:N85) -> 147.88299 | E81: =SUBTOTAL(9,'Planta central'!O81:O85) -> 183.82826 | F81: =SUBTOTAL(9,'Planta central'!P81:P85) -> 267.13643 | G81: =SUBTOTAL(9,'Planta central'!Q81:Q85) -> 290.91785 | H81: =SUBTOTAL(9,'Planta central'!R81:R85) -> 364.94216 | I81: =SUBTOTAL(9,'Planta central'!S81:S85) -> 383.57899 | J81: =SUBTOTAL(9,'Planta central'!T81:T85) -> 454.296
A82: ='Planta central'!A82 -> 0
A83: ='Planta central'!A83 -> 0
A84: ='Planta central'!A84 -> 0
A85: ='Planta central'!A85 -> 0
A86: ='Planta central'!A86 -> CENTRO DE DOCUMENTACION Y ARCHIVO | B86: =+UPPER(A86) -> CENTRO DE DOCUMENTACION Y ARCHIVO | C86: =SUBTOTAL(9,'Planta central'!M86:M95) -> 124.4705 | D86: =SUBTOTAL(9,'Planta central'!N86:N95) -> 360.71552 | E86: =SUBTOTAL(9,'Planta central'!O86:O95) -> 448.39304 | F86: =SUBTOTAL(9,'Planta central'!P86:P95) -> 651.59795 | G86: =SUBTOTAL(9,'Planta central'!Q86:Q95) -> 709.60546 | H86: =SUBTOTAL(9,'Planta central'!R86:R95) -> 890.16522 | I86: =SUBTOTAL(9,'Planta central'!S86:S95) -> 935.6241 | J86: =SUBTOTAL(9,'Planta central'!T86:T95) -> 1108.1167
A87: ='Planta central'!A87 -> 0
A88: ='Planta central'!A88 -> 0
A89: ='Planta central'!A89 -> 0
A90: ='Planta central'!A90 -> 0
A91: ='Planta central'!A91 -> 0
A92: ='Planta central'!A92 -> 0
A93: ='Planta central'!A93 -> 0
A94: ='Planta central'!A94 -> 0
A95: ='Planta central'!A95 -> 0
A96: ='Planta central'!A96 -> CLINICA ODONTOLOGICA | B96: =+UPPER(A96) -> CLINICA ODONTOLOGICA | C96: =SUBTOTAL(9,'Planta central'!M96:M106) -> 110.36196 | D96: =SUBTOTAL(9,'Planta central'!N96:N106) -> 319.82895 | E96: =SUBTOTAL(9,'Planta central'!O96:O106) -> 397.56835 | F96: =SUBTOTAL(9,'Planta central'!P96:P106) -> 577.74029 | G96: =SUBTOTAL(9,'Planta central'!Q96:Q106) -> 629.17274 | H96: =SUBTOTAL(9,'Planta central'!R96:R106) -> 789.26632 | I96: =SUBTOTAL(9,'Planta central'!S96:S106) -> 829.5725 | J96: =SUBTOTAL(9,'Planta central'!T96:T106) -> 982.51332
A97: ='Planta central'!A97 -> 0
A98: ='Planta central'!A98 -> 0
A99: ='Planta central'!A99 -> 0
A100: ='Planta central'!A100 -> 0
A101: ='Planta central'!A101 -> 0
...

Sheet Inflación
B1: AÑO | C1: INFLACIÓN
A2: 1 | B2: 2011 | C2: 5.41 | D2: previsión
A3: 2 | B3: 2012 | C3: 4.16
A4: 3 | B4: 2013 | C4: 2.7
A5: 4 | B5: 2014 | C5: 3.67
A6: 5 | B6: 2015 | C6: 3.38
A7: 6 | B7: 2016 | C7: 0.4
A8: 7 | B8: 2017 | C8: -0.2
A9: 8 | B9: 2018 | C9: -0.22
A10: 9 | B10: 2019 | C10: 1.27
A11: 10 | B11: 2020 | C11: 1.34
A12: 11 | B12: 2021 | C12: 1.43
A13: 12 | B13: 2022 | C13: 3.31 | D13: AFP
A14: 13 | B14: 2023 | C14: 1.35
A15: 14 | B15: 2024 | C15: 0.53
A16: 15 | B16: 2025 | C16: 1.91
A17: 16 | B17: 2026 | C17: 1.55
A18: 17 | B18: 2027 | C18: 1
A19: 18 | B19: 2028 | C19: 1 | D19: statista

Sheet 8 Mantenimiento
A1: DESCRIPCIÓN | B1: VALOR | C1: UNIDAD | D1: AÑO | E1: =+'1 Estudiantes'!B3 -> 2023 | F1: =+'1 Estudiantes'!C3 -> 2023 | G1: =+'1 Estudiantes'!D3 -> 2024 | H1: =+'1 Estudiantes'!E3 -> 2024 | I1: =+'1 Estudiantes'!F3 -> 2025 | J1: =+'1 Estudiantes'!G3 -> 2025 | K1: =+'1 Estudiantes'!H3 -> 2026 | L1: =+'1 Estudiantes'!I3 -> 2026
A2: Refacciones | C2: Mensual | D2: No. Alumnos | E2: =+'1 Estudiantes'!B12 -> 30 | F2: =+'1 Estudiantes'!C12 -> 86.94 | G2: =+'1 Estudiantes'!D12 -> 108.07212 | H2: =+'1 Estudiantes'!E12 -> 157.04876 | I2: =+'1 Estudiantes'!F12 -> 171.02979 | J2: =+'1 Estudiantes'!G12 -> 214.54848 | K2: =+'1 Estudiantes'!H12 -> 225.50502 | L2: =+'1 Estudiantes'!I12 -> 267.07935
A3: Garantía | C3: Anual | D3: Servicios Básicos | E3: =+(($B$12/'Planta central'!$B$2)/2)*'8 Mantenimiento'!E2 -> 1120.0508 | F3: =+((($B$12/'Planta central'!$B$2)/2)*'8 Mantenimiento'!F2)*'5 Demanda'!C79 -> 3292.3237 | G3: =+((($B$12/'Planta central'!$B$2)/2)*'8 Mantenimiento'!G2)*'5 Demanda'!D79 -> 4092.5743 | H3: =+((($B$12/'Planta central'!$B$2)/2)*'8 Mantenimiento'!H2)*'5 Demanda'!E79 -> 6057.4991 | I3: =+((($B$12/'Planta central'!$B$2)/2)*'8 Mantenimiento'!I2)*'5 Demanda'!F79 -> 6596.7587 | J3: =+((($B$12/'Planta central'!$B$2)/2)*'8 Mantenimiento'!J2)*'5 Demanda'!G79 -> 8118.3106 | K3: =+((($B$12/'Planta central'!$B$2)/2)*'8 Mantenimiento'!K2)*'5 Demanda'!H79 -> 8532.8957 | L3: =+((($B$12/'Planta central'!$B$2)/2)*'8 Mantenimiento'!L2)*'5 Demanda'!I79 -> 10106.029
A4: Servicios Basicos | B4: =+((B12/12)/'Planta central'!B2) -> 6.2225045 | C4: Mensual | D4: Mantenimiento | E4: =+(($B$20/'Planta central'!$B$2)/2)*'8 Mantenimiento'!E2 -> 3132.9663 | F4: =+((($B$20/'Planta central'!$B$2)/2)*'8 Mantenimiento'!F2)*'5 Demanda'!C79 -> 9209.1709 | G4: =+((($B$20/'Planta central'!$B$2)/2)*'8 Mantenimiento'!G2)*'5 Demanda'!D79 -> 11447.603 | H4: =+((($B$20/'Planta central'!$B$2)/2)*'8 Mantenimiento'!H2)*'5 Demanda'!E79 -> 16943.821 | I4: =+((($B$20/'Planta central'!$B$2)/2)*'8 Mantenimiento'!I2)*'5 Demanda'!F79 -> 18452.219 | J4: =+((($B$20/'Planta central'!$B$2)/2)*'8 Mantenimiento'!J2)*'5 Demanda'!G79 -> 22708.25 | K4: =+((($B$20/'Planta central'!$B$2)/2)*'8 Mantenimiento'!K2)*'5 Demanda'!H79 -> 23867.913 | L4: =+((($B$20/'Planta central'!$B$2)/2)*'8 Mantenimiento'!L2)*'5 Demanda'!I79 -> 28268.225
A7: SERVICIOS BÁSICOS | B7: ANUAL
A8: Agua | B8: 120000
A9: Internet | B9: 624000
A10: Energia Eléctrica | B10: 296000
A11: Comunicaciones | B11: 18000
A12: TOTAL | B12: =SUM(B8:B11) -> 1058000
A14: MANTENIMIENTO | B14: ANUAL
A15: Servicio de Limpieza | B15: 399400
A16: Seguros Bienes y Vehículos | B16: 120000
A18: Servicio de Seguridad | B18: 265000
A19: Refacciones e Infraestructura | B19: 2175000
A20: TOTAL | B20: =SUM(B15:B19) -> 2959400
D49: =+('8 Mantenimiento'!#REF!) -> #REF!

Sheet 9 Inv. Vin. Becas
A1: INVESTIGACIÓN Y VINCULACIÓN CON LA SOCIEDAD
A2: =+'1 Estudiantes'!A3 -> AÑO | B2: =+'1 Estudiantes'!B3 -> 2023 | C2: =+'1 Estudiantes'!C3 -> 2023 | D2: =+'1 Estudiantes'!D3 -> 2024 | E2: =+'1 Estudiantes'!E3 -> 2024 | F2: =+'1 Estudiantes'!F3 -> 2025 | G2: =+'1 Estudiantes'!G3 -> 2025 | H2: =+'1 Estudiantes'!H3 -> 2026 | I2: =+'1 Estudiantes'!I3 -> 2026
A3: =+'1 Estudiantes'!A12 -> Total Nº de Estudiantes | B3: =+'5 Demanda'!B11 -> 30 | C3: =+'5 Demanda'!C11 -> 86.94 | D3: =+'5 Demanda'!D11 -> 108.07212 | E3: =+'5 Demanda'!E11 -> 157.04876 | F3: =+'5 Demanda'!F11 -> 171.02979 | G3: =+'5 Demanda'!G11 -> 214.54848 | H3: =+'5 Demanda'!H11 -> 225.50502 | I3: =+'5 Demanda'!I11 -> 267.07935
A4: Becas Institucionales | B4: =+'5 Demanda'!B34 -> 6169.387 | C4: =+'5 Demanda'!C34 -> 17878.884 | D4: =+'5 Demanda'!D34 -> 22224.625 | E4: =+'5 Demanda'!E34 -> 32296.487 | F4: =+'5 Demanda'!F34 -> 35171.632 | G4: =+'5 Demanda'!G34 -> 44121.086 | H4: =+'5 Demanda'!H34 -> 46374.258 | I4: =+'5 Demanda'!I34 -> 54923.863
A5: % Variación Presupuesto | B5: 1 | C5: 1.03 | D5: 1 | E5: 1.03 | F5: 1 | G5: 1.03 | H5: 1 | I5: 1.03
A6: Presupuesto Universidad | B6: =(62451974.57)*(B5/2) -> 31225987 | C6: =+(B6+B17)*C5/2 -> 33312099 | D6: =+C6 -> 33312099 | E6: =+((B6+C6)*E5)/2 -> 33237114 | F6: =+E6 -> 33237114 | G6: =+((D6+E6)*G5)/2 -> 34272845 | H6: =+G6 -> 34272845 | I6: =+((F6+G6)*I5)/2 -> 34767629
A7: Nº Estudiantes Uni | B7: =+'Planta central'!$B$2 -> 14169 | C7: =+'Planta central'!$B$2 -> 14169 | D7: =+'Planta central'!$B$2 -> 14169 | E7: =+'Planta central'!$B$2 -> 14169 | F7: =+'Planta central'!$B$2 -> 14169 | G7: =+'Planta central'!$B$2 -> 14169 | H7: =+'Planta central'!$B$2 -> 14169 | I7: =+'Planta central'!$B$2 -> 14169
A8: Investigación 5% | B8: =+(B6*5%)/B7*B3 -> 3305.7365 | C8: =+(C6*5%)/C7*C3 -> 10220.036 | D8: =+(D6*5%)/D7*D3 -> 12704.175 | E8: =+(E6*5%)/E7*E3 -> 18419.958 | F8: =+(F6*5%)/F7*F3 -> 20059.767 | G8: =+(G6*5%)/G7*G3 -> 25948.15 | H8: =+(H6*5%)/H7*H3 -> 27273.267 | I8: =+(I6*5%)/I7*I3 -> 32767.717
A9: Vinculación 1% | B9: =+(B6*1%)/B7*B3 -> 661.14731 | C9: =+(C6*1%)/C7*C3 -> 2044.0072 | D9: =+(D6*1%)/D7*D3 -> 2540.835 | E9: =+(E6*1%)/E7*E3 -> 3683.9916 | F9: =+(F6*1%)/F7*F3 -> 4011.9533 | G9: =+(G6*1%)/G7*G3 -> 5189.6299 | H9: =+(H6*1%)/H7*H3 -> 5454.6534 | I9: =+(I6*1%)/I7*I3 -> 6553.5434
A10: % Variación Presupuesto | B10: 1 | C10: 1 | D10: 1.03 | E10: 1 | F10: 1.03 | G10: 1 | H10: 1.03 | I10: 1
A11: Presupuesto Gobierno | C11: =+B11 -> 0 | D11: =+((C11+B11)*D10)/2 -> 0 | E11: =+D11 -> 0 | F11: =+((E11+D11)*F10)/2 -> 0 | G11: =+F11 -> 0 | H11: =+((G11+F11)*H10)/2 -> 0 | I11: =+H11 -> 0
A12: Nº Docentes Universidad | B12: =+'Planta central'!$F$2 -> 891 | C12: =+'Planta central'!$F$2 -> 891 | D12: =+'Planta central'!$F$2 -> 891 | E12: =+'Planta central'!$F$2 -> 891 | F12: =+'Planta central'!$F$2 -> 891 | G12: =+'Planta central'!$F$2 -> 891 | H12: =+'Planta central'!$F$2 -> 891 | I12: =+'Planta central'!$F$2 -> 891
A13: Becas Estudiantes 90% | B13: =+(B11*90%)/B7*B3 -> 0 | C13: =+(C11*90%)/C7*C3 -> 0 | D13: =+(D11*90%)/D7*D3 -> 0 | E13: =+(E11*90%)/E7*E3 -> 0 | F13: =+(F11*90%)/F7*F3 -> 0 | G13: =+(G11*90%)/G7*G3 -> 0 | H13: =+(H11*90%)/H7*H3 -> 0 | I13: =+(I11*90%)/I7*I3 -> 0
A14: Becas Docentes 10% | B14: =+(B11*10%)/B12*'5 Demanda'!B20 -> 0 | C14: =+(C11*10%)/C12*'5 Demanda'!C20 -> 0 | D14: =+(D11*10%)/D12*'5 Demanda'!D20 -> 0 | E14: =+(E11*10%)/E12*'5 Demanda'!E20 -> 0 | F14: =+(F11*10%)/F12*'5 Demanda'!F20 -> 0 | G14: =+(G11*10%)/G12*'5 Demanda'!G20 -> 0 | H14: =+(H11*10%)/H12*'5 Demanda'!H20 -> 0 | I14: =+(I11*10%)/I12*'5 Demanda'!I20 -> 0
A17: 2022 | B17: =66915398.32/2 -> 33457699

Sheet Planta central
A1: PLANTA CENTRAL
A2: Nº ESTUDIANTES UNIVERSIDAD | B2: 14169 | D2: Nº DOCENTES | F2: 891 | G2: ESTUDIANTES DE LA CARRERA | L2: No. Alumnos | M2: =+'1 Estudiantes'!B12 -> 30 | N2: =+'1 Estudiantes'!C12 -> 86.94 | O2: =+'1 Estudiantes'!D12 -> 108.07212 | P2: =+'1 Estudiantes'!E12 -> 157.04876 | Q2: =+'1 Estudiantes'!F12 -> 171.02979 | R2: =+'1 Estudiantes'!G12 -> 214.54848 | S2: =+'1 Estudiantes'!H12 -> 225.50502 | T2: =+'1 Estudiantes'!I12 -> 267.07935 | U2: =+'1 Estudiantes'!#REF! -> #REF! | V2: =+'1 Estudiantes'!K12 -> 0
A3: CARGO/DEPARTAMENTO | B3: Nº PERSONAS | C3: SUELDO BASICO | D3: FUNCIONAL | E3: FONDO DE RESERVA | F3: BENEFICIOS SOCIAL XIV | G3: BENEFICIO SOCIAL XIII | H3: APORTE PATRONAL | I3: MASA SALARIAL | J3: VARIOS | K3: TOTAL MENSUAL | L3: Años | M3: =+'1 Estudiantes'!B3 -> 2023 | N3: =+'1 Estudiantes'!C3 -> 2023 | O3: =+'1 Estudiantes'!D3 -> 2024 | P3: =+'1 Estudiantes'!E3 -> 2024 | Q3: =+'1 Estudiantes'!F3 -> 2025 | R3: =+'1 Estudiantes'!G3 -> 2025 | S3: =+'1 Estudiantes'!H3 -> 2026 | T3: =+'1 Estudiantes'!I3 -> 2026 | ... V3: =+'1 Estudiantes'!K3 -> 0
A4: Auditoría | B4: 1 | C4: 820 | E4: =+C4*0.0833 -> 68.306 | F4: =(394/12) -> 32.833333 | G4: =+C4/12 -> 68.333333 | H4: =+C4*0.1115 -> 91.43 | I4: =SUM(C4:H4) -> 1080.9027 | K4: =SUM(I4:J4) -> 1080.9027 | M4: =+(K4/$B$2)*$M$2*6 -> 13.73156 | N4: =+(K4/$B$2)*$N$2*6 -> 39.794062 | O4: =+(K4/$B$2)*$O$2*6 -> 49.466628 | P4: =+(K4/$B$2)*$P$2*6 -> 71.884153 | Q4: =+(K4/$B$2)*$Q$2*6 -> 78.28353 | R4: =+(K4/$B$2)*$R$2*6 -> 98.202846 | S4: =+(K4/$B$2)*$S$2*6 -> 103.21786 | T4: =+(K4/$B$2)*$T$2*6 -> 122.24721 | U4: =+(K4/$B$2)*$U$2*6 -> #REF! | V4: =+(K4/$B$2)*$V$2*6 -> 0
B5: 1 | C5: 700 | E5: =+C5*0.0833 -> 58.31 | F5: 32.833333 | G5: =+C5/12 -> 58.333333 | H5: =+C5*0.1115 -> 78.05 | I5: =SUM(C5:H5) -> 927.52667 | K5: =SUM(I5:J5) -> 927.52667 | M5: =+(K5/$B$2)*$M$2*6 -> 11.783104 | N5: =+(K5/$B$2)*$N$2*6 -> 34.147435 | O5: =+(K5/$B$2)*$O$2*6 -> 42.447501 | P5: =+(K5/$B$2)*$P$2*6 -> 61.684064 | Q5: =+(K5/$B$2)*$Q$2*6 -> 67.175393 | R5: =+(K5/$B$2)*$R$2*6 -> 84.268234 | S5: =+(K5/$B$2)*$S$2*6 -> 88.571636 | T5: =+(K5/$B$2)*$T$2*6 -> 104.90079 | U5: =+(K5/$B$2)*$U$2*6 -> #REF! | V5: =+(K5/$B$2)*$V$2*6 -> 0
B6: 1 | C6: 1800 | E6: =+C6*0.0833 -> 149.94 | F6: 32.833333 | G6: =+C6/12 -> 150 | H6: =+C6*0.1115 -> 200.7 | I6: =SUM(C6:H6) -> 2333.4733 | K6: =SUM(I6:J6) -> 2333.4733 | M6: =+(K6/$B$2)*$M$2*6 -> 29.643955 | N6: =+(K6/$B$2)*$N$2*6 -> 85.908182 | O6: =+(K6/$B$2)*$O$2*6 -> 106.7895 | P6: =+(K6/$B$2)*$P$2*6 -> 155.18488 | Q6: =+(K6/$B$2)*$Q$2*6 -> 168.99998 | R6: =+(K6/$B$2)*$R$2*6 -> 212.00218 | S6: =+(K6/$B$2)*$S$2*6 -> 222.82869 | T6: =+(K6/$B$2)*$T$2*6 -> 263.90961 | U6: =+(K6/$B$2)*$U$2*6 -> #REF! | V6: =+(K6/$B$2)*$V$2*6 -> 0
B7: 1 | C7: 2500 | E7: =+C7*0.0833 -> 208.25 | F7: 32.833333 | G7: =+C7/12 -> 208.33333 | H7: =+C7*0.1115 -> 278.75 | I7: =SUM(C7:H7) -> 3228.1667 | K7: =SUM(I7:J7) -> 3228.1667 | M7: =+(K7/$B$2)*$M$2*6 -> 41.009951 | N7: =+(K7/$B$2)*$N$2*6 -> 118.84684 | O7: =+(K7/$B$2)*$O$2*6 -> 147.73441 | P7: =+(K7/$B$2)*$P$2*6 -> 214.68541 | Q7: =+(K7/$B$2)*$Q$2*6 -> 233.79745 | R7: =+(K7/$B$2)*$R$2*6 -> 293.28742 | S7: =+(K7/$B$2)*$S$2*6 -> 308.26499 | T7: =+(K7/$B$2)*$T$2*6 -> 365.09704 | U7: =+(K7/$B$2)*$U$2*6 -> #REF! | V7: =+(K7/$B$2)*$V$2*6 -> 0
E8: =+C8*0.0833 -> 0 | G8: =+C8/12 -> 0 | H8: =+C8*0.1115 -> 0 | I8: =SUM(C8:H8) -> 0 | K8: =SUM(I8:J8) -> 0 | M8: =+(K8/$B$2)*$M$2*6 -> 0 | N8: =+(K8/$B$2)*$N$2*6 -> 0 | O8: =+(K8/$B$2)*$O$2*6 -> 0 | P8: =+(K8/$B$2)*$P$2*6 -> 0 | Q8: =+(K8/$B$2)*$Q$2*6 -> 0 | R8: =+(K8/$B$2)*$R$2*6 -> 0 | S8: =+(K8/$B$2)*$S$2*6 -> 0 | T8: =+(K8/$B$2)*$T$2*6 -> 0 | U8: =+(K8/$B$2)*$U$2*6 -> #REF! | V8: =+(K8/$B$2)*$V$2*6 -> 0
A9: TITULACION Y REGISTRO | B9: 1 | C9: 850 | E9: =+C9*0.0833 -> 70.805 | F9: 32.833333 | G9: =+C9/12 -> 70.833333 | H9: =+C9*0.1115 -> 94.775 | I9: =SUM(C9:H9) -> 1119.2467 | K9: =SUM(I9:J9) -> 1119.2467 | M9: =+(K9/$B$2)*$M$2*6 -> 14.218675 | N9: =+(K9/$B$2)*$N$2*6 -> 41.205719 | O9: =+(K9/$B$2)*$O$2*6 -> 51.22141 | P9: =+(K9/$B$2)*$P$2*6 -> 74.434175 | Q9: =+(K9/$B$2)*$Q$2*6 -> 81.060564 | R9: =+(K9/$B$2)*$R$2*6 -> 101.6865 | S9: =+(K9/$B$2)*$S$2*6 -> 106.87942 | T9: =+(K9/$B$2)*$T$2*6 -> 126.58381 | U9: =+(K9/$B$2)*$U$2*6 -> #REF! | V9: =+(K9/$B$2)*$V$2*6 -> 0
B10: 1 | C10: 1850 | E10: =+C10*0.0833 -> 154.105 | F10: 32.833333 | G10: =+C10/12 -> 154.16667 | H10: =+C10*0.1115 -> 206.275 | I10: =SUM(C10:H10) -> 2397.38 | K10: =SUM(I10:J10) -> 2397.38 | M10: =+(K10/$B$2)*$M$2*6 -> 30.455812 | N10: =+(K10/$B$2)*$N$2*6 -> 88.260943 | O10: =+(K10/$B$2)*$O$2*6 -> 109.71414 | P10: =+(K10/$B$2)*$P$2*6 -> 159.43492 | Q10: =+(K10/$B$2)*$Q$2*6 -> 173.62837 | R10: =+(K10/$B$2)*$R$2*6 -> 217.80827 | S10: =+(K10/$B$2)*$S$2*6 -> 228.93128 | T10: =+(K10/$B$2)*$T$2*6 -> 271.13728 | U10: =+(K10/$B$2)*$U$2*6 -> #REF! | V10: =+(K10/$B$2)*$V$2*6 -> 0
E11: =+C11*0.0833 -> 0 | G11: =+C11/12 -> 0 | H11: =+C11*0.1115 -> 0 | I11: =SUM(C11:H11) -> 0 | K11: =SUM(I11:J11) -> 0 | M11: =+(K11/$B$2)*$M$2*6 -> 0 | N11: =+(K11/$B$2)*$N$2*6 -> 0 | O11: =+(K11/$B$2)*$O$2*6 -> 0 | P11: =+(K11/$B$2)*$P$2*6 -> 0 | Q11: =+(K11/$B$2)*$Q$2*6 -> 0 | R11: =+(K11/$B$2)*$R$2*6 -> 0 | S11: =+(K11/$B$2)*$S$2*6 -> 0 | T11: =+(K11/$B$2)*$T$2*6 -> 0 | U11: =+(K11/$B$2)*$U$2*6 -> #REF! | V11: =+(K11/$B$2)*$V$2*6 -> 0
A12: UNIDAD COORDINADORA DE ESTUDIOS NO PRESENCIALES | B12: 1 | C12: 1500 | E12: =+C12*0.0833 -> 124.95 | F12: 32.833333 | G12: =+C12/12 -> 125 | H12: =+C12*0.1115 -> 167.25 | I12: =SUM(C12:H12) -> 1950.0333 | K12: =SUM(I12:J12) -> 1950.0333 | M12: =+(K12/$B$2)*$M$2*6 -> 24.772814 | N12: =+(K12/$B$2)*$N$2*6 -> 71.791615 | O12: =+(K12/$B$2)*$O$2*6 -> 89.241684 | P12: =+(K12/$B$2)*$P$2*6 -> 129.68466 | Q12: =+(K12/$B$2)*$Q$2*6 -> 141.22964 | R12: =+(K12/$B$2)*$R$2*6 -> 177.16565 | S12: =+(K12/$B$2)*$S$2*6 -> 186.21313 | T12: =+(K12/$B$2)*$T$2*6 -> 220.54357 | U12: =+(K12/$B$2)*$U$2*6 -> #REF! | V12: =+(K12/$B$2)*$V$2*6 -> 0
B13: 1 | C13: 700 | E13: =+C13*0.0833 -> 58.31 | F13: 32.833333 | G13: =+C13/12 -> 58.333333 | H13: =+C13*0.1115 -> 78.05 | I13: =SUM(C13:H13) -> 927.52667 | K13: =SUM(I13:J13) -> 927.52667 | M13: =+(K13/$B$2)*$M$2*6 -> 11.783104 | N13: =+(K13/$B$2)*$N$2*6 -> 34.147435 | O13: =+(K13/$B$2)*$O$2*6 -> 42.447501 | P13: =+(K13/$B$2)*$P$2*6 -> 61.684064 | Q13: =+(K13/$B$2)*$Q$2*6 -> 67.175393 | R13: =+(K13/$B$2)*$R$2*6 -> 84.268234 | S13: =+(K13/$B$2)*$S$2*6 -> 88.571636 | T13: =+(K13/$B$2)*$T$2*6 -> 104.90079 | U13: =+(K13/$B$2)*$U$2*6 -> #REF! | V13: =+(K13/$B$2)*$V$2*6 -> 0
B14: 1 | C14: 820 | E14: =+C14*0.0833 -> 68.306 | F14: 32.833333 | G14: =+C14/12 -> 68.333333 | H14: =+C14*0.1115 -> 91.43 | I14: =SUM(C14:H14) -> 1080.9027 | K14: =SUM(I14:J14) -> 1080.9027 | M14: =+(K14/$B$2)*$M$2*6 -> 13.73156 | N14: =+(K14/$B$2)*$N$2*6 -> 39.794062 | O14: =+(K14/$B$2)*$O$2*6 -> 49.466628 | P14: =+(K14/$B$2)*$P$2*6 -> 71.884153 | Q14: =+(K14/$B$2)*$Q$2*6 -> 78.28353 | R14: =+(K14/$B$2)*$R$2*6 -> 98.202846 | S14: =+(K14/$B$2)*$S$2*6 -> 103.21786 | T14: =+(K14/$B$2)*$T$2*6 -> 122.24721 | U14: =+(K14/$B$2)*$U$2*6 -> #REF! | V14: =+(K14/$B$2)*$V$2*6 -> 0
A15: Rectorado | B15: 1 | C15: 810 | E15: =+C15*0.0833 -> 67.473 | F15: =(394/12) -> 32.833333 | G15: =+C15/12 -> 67.5 | H15: =+C15*0.1115 -> 90.315 | I15: =SUM(C15:H15) -> 1068.1213 | K15: =SUM(I15:J15) -> 1068.1213 | M15: =+(K15/$B$2)*$M$2*6 -> 13.569189 | N15: =+(K15/$B$2)*$N$2*6 -> 39.32351 | O15: =+(K15/$B$2)*$O$2*6 -> 48.881701 | P15: =+(K15/$B$2)*$P$2*6 -> 71.034146 | Q15: =+(K15/$B$2)*$Q$2*6 -> 77.357852 | R15: =+(K15/$B$2)*$R$2*6 -> 97.041628 | S15: =+(K15/$B$2)*$S$2*6 -> 101.99734 | T15: =+(K15/$B$2)*$T$2*6 -> 120.80167 | U15: =+(K15/$B$2)*$U$2*6 -> #REF! | V15: =+(K15/$B$2)*$V$2*6 -> 0
B16: 1 | C16: 650 | E16: =+C16*0.0833 -> 54.145 | F16: =(394/12) -> 32.833333 | G16: =+C16/12 -> 54.166667 | H16: =+C16*0.1115 -> 72.475 | I16: =SUM(C16:H16) -> 863.62 | K16: =SUM(I16:J16) -> 863.62 | M16: =+(K16/$B$2)*$M$2*6 -> 10.971247 | N16: =+(K16/$B$2)*$N$2*6 -> 31.794674 | O16: =+(K16/$B$2)*$O$2*6 -> 39.522864 | P16: =+(K16/$B$2)*$P$2*6 -> 57.434026 | Q16: =+(K16/$B$2)*$Q$2*6 -> 62.547003 | R16: =+(K16/$B$2)*$R$2*6 -> 78.462145 | S16: =+(K16/$B$2)*$S$2*6 -> 82.469043 | T16: =+(K16/$B$2)*$T$2*6 -> 97.673118 | U16: =+(K16/$B$2)*$U$2*6 -> #REF! | V16: =+(K16/$B$2)*$V$2*6 -> 0
B17: 1 | C17: 650 | E17: =+C17*0.0833 -> 54.145 | F17: =(394/12) -> 32.833333 | G17: =+C17/12 -> 54.166667 | H17: =+C17*0.1115 -> 72.475 | I17: =SUM(C17:H17) -> 863.62 | K17: =SUM(I17:J17) -> 863.62 | M17: =+(K17/$B$2)*$M$2*6 -> 10.971247 | N17: =+(K17/$B$2)*$N$2*6 -> 31.794674 | O17: =+(K17/$B$2)*$O$2*6 -> 39.522864 | P17: =+(K17/$B$2)*$P$2*6 -> 57.434026 | Q17: =+(K17/$B$2)*$Q$2*6 -> 62.547003 | R17: =+(K17/$B$2)*$R$2*6 -> 78.462145 | S17: =+(K17/$B$2)*$S$2*6 -> 82.469043 | T17: =+(K17/$B$2)*$T$2*6 -> 97.673118 | U17: =+(K17/$B$2)*$U$2*6 -> #REF! | V17: =+(K17/$B$2)*$V$2*6 -> 0
B18: 1 | C18: 1300 | E18: =+C18*0.0833 -> 108.29 | F18: =(394/12) -> 32.833333 | G18: =+C18/12 -> 108.33333 | H18: =+C18*0.1115 -> 144.95 | I18: =SUM(C18:H18) -> 1694.4067 | K18: =SUM(I18:J18) -> 1694.4067 | M18: =+(K18/$B$2)*$M$2*6 -> 21.525386 | N18: =+(K18/$B$2)*$N$2*6 -> 62.38057 | O18: =+(K18/$B$2)*$O$2*6 -> 77.543138 | P18: =+(K18/$B$2)*$P$2*6 -> 112.68451 | Q18: =+(K18/$B$2)*$Q$2*6 -> 122.71608 | R18: =+(K18/$B$2)*$R$2*6 -> 153.9413 | S18: =+(K18/$B$2)*$S$2*6 -> 161.80276 | T18: =+(K18/$B$2)*$T$2*6 -> 191.63287 | U18: =+(K18/$B$2)*$U$2*6 -> #REF! | V18: =+(K18/$B$2)*$V$2*6 -> 0
B19: 1 | C19: 750 | E19: =+C19*0.0833 -> 62.475 | F19: =(394/12) -> 32.833333 | G19: =+C19/12 -> 62.5 | H19: =+C19*0.1115 -> 83.625 | I19: =SUM(C19:H19) -> 991.43333 | K19: =SUM(I19:J19) -> 991.43333 | M19: =+(K19/$B$2)*$M$2*6 -> 12.594961 | N19: =+(K19/$B$2)*$N$2*6 -> 36.500196 | O19: =+(K19/$B$2)*$O$2*6 -> 45.372137 | P19: =+(K19/$B$2)*$P$2*6 -> 65.934101 | Q19: =+(K19/$B$2)*$Q$2*6 -> 71.803783 | R19: =+(K19/$B$2)*$R$2*6 -> 90.074322 | S19: =+(K19/$B$2)*$S$2*6 -> 94.674229 | T19: =+(K19/$B$2)*$T$2*6 -> 112.12847 | U19: =+(K19/$B$2)*$U$2*6 -> #REF! | V19: =+(K19/$B$2)*$V$2*6 -> 0
B20: 1 | C20: 700 | E20: =+C20*0.0833 -> 58.31 | F20: =(394/12) -> 32.833333 | G20: =+C20/12 -> 58.333333 | H20: =+C20*0.1115 -> 78.05 | I20: =SUM(C20:H20) -> 927.52667 | K20: =SUM(I20:J20) -> 927.52667 | M20: =+(K20/$B$2)*$M$2*6 -> 11.783104 | N20: =+(K20/$B$2)*$N$2*6 -> 34.147435 | O20: =+(K20/$B$2)*$O$2*6 -> 42.447501 | P20: =+(K20/$B$2)*$P$2*6 -> 61.684064 | Q20: =+(K20/$B$2)*$Q$2*6 -> 67.175393 | R20: =+(K20/$B$2)*$R$2*6 -> 84.268234 | S20: =+(K20/$B$2)*$S$2*6 -> 88.571636 | T20: =+(K20/$B$2)*$T$2*6 -> 104.90079 | U20: =+(K20/$B$2)*$U$2*6 -> #REF! | V20: =+(K20/$B$2)*$V$2*6 -> 0
B21: 1 | C21: 2200 | E21: =+C21*0.0833 -> 183.26 | F21: =(394/12) -> 32.833333 | G21: =+C21/12 -> 183.33333 | H21: =+C21*0.1115 -> 245.3 | I21: =SUM(C21:H21) -> 2844.7267 | K21: =SUM(I21:J21) -> 2844.7267 | M21: =+(K21/$B$2)*$M$2*6 -> 36.13881 | N21: =+(K21/$B$2)*$N$2*6 -> 104.73027 | O21: =+(K21/$B$2)*$O$2*6 -> 130.18659 | P21: =+(K21/$B$2)*$P$2*6 -> 189.18518 | Q21: =+(K21/$B$2)*$Q$2*6 -> 206.0271 | R21: =+(K21/$B$2)*$R$2*6 -> 258.45089 | S21: =+(K21/$B$2)*$S$2*6 -> 271.64943 | T21: =+(K21/$B$2)*$T$2*6 -> 321.731 | U21: =+(K21/$B$2)*$U$2*6 -> #REF! | V21: =+(K21/$B$2)*$V$2*6 -> 0
E22: =+C22*0.0833 -> 0 | G22: =+C22/12 -> 0 | H22: =+C22*0.1115 -> 0 | I22: =SUM(C22:H22) -> 0 | K22: =SUM(I22:J22) -> 0 | M22: =+(K22/$B$2)*$M$2*6 -> 0 | N22: =+(K22/$B$2)*$N$2*6 -> 0 | O22: =+(K22/$B$2)*$O$2*6 -> 0 | P22: =+(K22/$B$2)*$P$2*6 -> 0 | Q22: =+(K22/$B$2)*$Q$2*6 -> 0 | R22: =+(K22/$B$2)*$R$2*6 -> 0 | S22: =+(K22/$B$2)*$S$2*6 -> 0 | T22: =+(K22/$B$2)*$T$2*6 -> 0 | U22: =+(K22/$B$2)*$U$2*6 -> #REF! | V22: =+(K22/$B$2)*$V$2*6 -> 0
E23: =+C23*0.0833 -> 0 | G23: =+C23/12 -> 0 | H23: =+C23*0.1115 -> 0 | I23: =SUM(C23:H23) -> 0 | K23: =SUM(I23:J23) -> 0 | M23: =+(K23/$B$2)*$M$2*6 -> 0 | N23: =+(K23/$B$2)*$N$2*6 -> 0 | O23: =+(K23/$B$2)*$O$2*6 -> 0 | P23: =+(K23/$B$2)*$P$2*6 -> 0 | Q23: =+(K23/$B$2)*$Q$2*6 -> 0 | R23: =+(K23/$B$2)*$R$2*6 -> 0 | S23: =+(K23/$B$2)*$S$2*6 -> 0 | T23: =+(K23/$B$2)*$T$2*6 -> 0 | U23: =+(K23/$B$2)*$U$2*6 -> #REF! | V23: =+(K23/$B$2)*$V$2*6 -> 0
A24: Secretaría General | B24: 1 | C24: 820 | E24: =+C24*0.0833 -> 68.306 | F24: =(394/12) -> 32.833333 | G24: =+C24/12 -> 68.333333 | H24: =+C24*0.1115 -> 91.43 | I24: =SUM(C24:H24) -> 1080.9027 | K24: =SUM(I24:J24) -> 1080.9027 | M24: =+(K24/$B$2)*$M$2*6 -> 13.73156 | N24: =+(K24/$B$2)*$N$2*6 -> 39.794062 | O24: =+(K24/$B$2)*$O$2*6 -> 49.466628 | P24: =+(K24/$B$2)*$P$2*6 -> 71.884153 | Q24: =+(K24/$B$2)*$Q$2*6 -> 78.28353 | R24: =+(K24/$B$2)*$R$2*6 -> 98.202846 | S24: =+(K24/$B$2)*$S$2*6 -> 103.21786 | T24: =+(K24/$B$2)*$T$2*6 -> 122.24721 | U24: =+(K24/$B$2)*$U$2*6 -> #REF! | V24: =+(K24/$B$2)*$V$2*6 -> 0
B25: 1 | C25: 820 | E25: =+C25*0.0833 -> 68.306 | F25: =(394/12) -> 32.833333 | G25: =+C25/12 -> 68.333333 | H25: =+C25*0.1115 -> 91.43 | I25: =SUM(C25:H25) -> 1080.9027 | K25: =SUM(I25:J25) -> 1080.9027 | M25: =+(K25/$B$2)*$M$2*6 -> 13.73156 | N25: =+(K25/$B$2)*$N$2*6 -> 39.794062 | O25: =+(K25/$B$2)*$O$2*6 -> 49.466628 | P25: =+(K25/$B$2)*$P$2*6 -> 71.884153 | Q25: =+(K25/$B$2)*$Q$2*6 -> 78.28353 | R25: =+(K25/$B$2)*$R$2*6 -> 98.202846 | S25: =+(K25/$B$2)*$S$2*6 -> 103.21786 | T25: =+(K25/$B$2)*$T$2*6 -> 122.24721 | U25: =+(K25/$B$2)*$U$2*6 -> #REF! | V25: =+(K25/$B$2)*$V$2*6 -> 0
B26: 1 | C26: 1460.13 | E26: =+C26*0.0833 -> 121.62883 | F26: =(394/12) -> 32.833333 | G26: =+C26/12 -> 121.6775 | H26: =+C26*0.1115 -> 162.8045 | I26: =SUM(C26:H26) -> 1899.0742 | K26: =SUM(I26:J26) -> 1899.0742 | M26: =+(K26/$B$2)*$M$2*6 -> 24.125439 | N26: =+(K26/$B$2)*$N$2*6 -> 69.915523 | O26: =+(K26/$B$2)*$O$2*6 -> 86.909579 | P26: =+(K26/$B$2)*$P$2*6 -> 126.29568 | Q26: =+(K26/$B$2)*$Q$2*6 -> 137.53896 | R26: =+(K26/$B$2)*$R$2*6 -> 172.53587 | S26: =+(K26/$B$2)*$S$2*6 -> 181.34692 | T26: =+(K26/$B$2)*$T$2*6 -> 214.78022 | U26: =+(K26/$B$2)*$U$2*6 -> #REF! | V26: =+(K26/$B$2)*$V$2*6 -> 0
B27: 1 | C27: 1350 | E27: =+C27*0.0833 -> 112.455 | F27: =(394/12) -> 32.833333 | G27: =+C27/12 -> 112.5 | H27: =+C27*0.1115 -> 150.525 | I27: =SUM(C27:H27) -> 1758.3133 | K27: =SUM(I27:J27) -> 1758.3133 | M27: =+(K27/$B$2)*$M$2*6 -> 22.337243 | N27: =+(K27/$B$2)*$N$2*6 -> 64.733331 | O27: =+(K27/$B$2)*$O$2*6 -> 80.467775 | P27: =+(K27/$B$2)*$P$2*6 -> 116.93455 | Q27: =+(K27/$B$2)*$Q$2*6 -> 127.34447 | R27: =+(K27/$B$2)*$R$2*6 -> 159.74738 | S27: =+(K27/$B$2)*$S$2*6 -> 167.90535 | T27: =+(K27/$B$2)*$T$2*6 -> 198.86055 | U27: =+(K27/$B$2)*$U$2*6 -> #REF! | V27: =+(K27/$B$2)*$V$2*6 -> 0
B28: 1 | C28: 3600 | E28: =+C28*0.0833 -> 299.88 | F28: =(394/12) -> 32.833333 | G28: =+C28/12 -> 300 | H28: =+C28*0.1115 -> 401.4 | I28: =SUM(C28:H28) -> 4634.1133 | K28: =SUM(I28:J28) -> 4634.1133 | M28: =+(K28/$B$2)*$M$2*6 -> 58.870802 | N28: =+(K28/$B$2)*$N$2*6 -> 170.60759 | O28: =+(K28/$B$2)*$O$2*6 -> 212.07641 | P28: =+(K28/$B$2)*$P$2*6 -> 308.18622 | Q28: =+(K28/$B$2)*$Q$2*6 -> 335.62203 | R28: =+(K28/$B$2)*$R$2*6 -> 421.02137 | S28: =+(K28/$B$2)*$S$2*6 -> 442.52205 | T28: =+(K28/$B$2)*$T$2*6 -> 524.10586 | U28: =+(K28/$B$2)*$U$2*6 -> #REF! | V28: =+(K28/$B$2)*$V$2*6 -> 0
B29: 1 | C29: 850 | E29: =+C29*0.0833 -> 70.805 | F29: =(394/12) -> 32.833333 | G29: =+C29/12 -> 70.833333 | H29: =+C29*0.1115 -> 94.775 | I29: =SUM(C29:H29) -> 1119.2467 | K29: =SUM(I29:J29) -> 1119.2467 | M29: =+(K29/$B$2)*$M$2*6 -> 14.218675 | N29: =+(K29/$B$2)*$N$2*6 -> 41.205719 | O29: =+(K29/$B$2)*$O$2*6 -> 51.22141 | P29: =+(K29/$B$2)*$P$2*6 -> 74.434175 | Q29: =+(K29/$B$2)*$Q$2*6 -> 81.060564 | R29: =+(K29/$B$2)*$R$2*6 -> 101.6865 | S29: =+(K29/$B$2)*$S$2*6 -> 106.87942 | T29: =+(K29/$B$2)*$T$2*6 -> 126.58381 | U29: =+(K29/$B$2)*$U$2*6 -> #REF! | V29: =+(K29/$B$2)*$V$2*6 -> 0
B30: 1 | C30: 2000 | E30: =+C30*0.0833 -> 166.6 | F30: =(394/12) -> 32.833333 | G30: =+C30/12 -> 166.66667 | H30: =+C30*0.1115 -> 223 | I30: =SUM(C30:H30) -> 2589.1 | K30: =SUM(I30:J30) -> 2589.1 | M30: =+(K30/$B$2)*$M$2*6 -> 32.891383 | N30: =+(K30/$B$2)*$N$2*6 -> 95.319227 | O30: =+(K30/$B$2)*$O$2*6 -> 118.48805 | P30: =+(K30/$B$2)*$P$2*6 -> 172.18503 | Q30: =+(K30/$B$2)*$Q$2*6 -> 187.51354 | R30: =+(K30/$B$2)*$R$2*6 -> 235.22654 | S30: =+(K30/$B$2)*$S$2*6 -> 247.23906 | T30: =+(K30/$B$2)*$T$2*6 -> 292.8203 | U30: =+(K30/$B$2)*$U$2*6 -> #REF! | V30: =+(K30/$B$2)*$V$2*6 -> 0
B31: 1 | C31: 650 | E31: =+C31*0.0833 -> 54.145 | F31: =(394/12) -> 32.833333 | G31: =+C31/12 -> 54.166667 | H31: =+C31*0.1115 -> 72.475 | I31: =SUM(C31:H31) -> 863.62 | K31: =SUM(I31:J31) -> 863.62 | M31: =+(K31/$B$2)*$M$2*6 -> 10.971247 | N31: =+(K31/$B$2)*$N$2*6 -> 31.794674 | O31: =+(K31/$B$2)*$O$2*6 -> 39.522864 | P31: =+(K31/$B$2)*$P$2*6 -> 57.434026 | Q31: =+(K31/$B$2)*$Q$2*6 -> 62.547003 | R31: =+(K31/$B$2)*$R$2*6 -> 78.462145 | S31: =+(K31/$B$2)*$S$2*6 -> 82.469043 | T31: =+(K31/$B$2)*$T$2*6 -> 97.673118 | U31: =+(K31/$B$2)*$U$2*6 -> #REF! | V31: =+(K31/$B$2)*$V$2*6 -> 0
B32: 1 | C32: 820 | E32: =+C32*0.0833 -> 68.306 | F32: =(394/12) -> 32.833333 | G32: =+C32/12 -> 68.333333 | H32: =+C32*0.1115 -> 91.43 | I32: =SUM(C32:H32) -> 1080.9027 | K32: =SUM(I32:J32) -> 1080.9027 | M32: =+(K32/$B$2)*$M$2*6 -> 13.73156 | N32: =+(K32/$B$2)*$N$2*6 -> 39.794062 | O32: =+(K32/$B$2)*$O$2*6 -> 49.466628 | P32: =+(K32/$B$2)*$P$2*6 -> 71.884153 | Q32: =+(K32/$B$2)*$Q$2*6 -> 78.28353 | R32: =+(K32/$B$2)*$R$2*6 -> 98.202846 | S32: =+(K32/$B$2)*$S$2*6 -> 103.21786 | T32: =+(K32/$B$2)*$T$2*6 -> 122.24721 | U32: =+(K32/$B$2)*$U$2*6 -> #REF! | V32: =+(K32/$B$2)*$V$2*6 -> 0
B33: 1 | C33: 700 | E33: =+C33*0.0833 -> 58.31 | F33: =(394/12) -> 32.833333 | G33: =+C33/12 -> 58.333333 | H33: =+C33*0.1115 -> 78.05 | I33: =SUM(C33:H33) -> 927.52667 | K33: =SUM(I33:J33) -> 927.52667 | M33: =+(K33/$B$2)*$M$2*6 -> 11.783104 | N33: =+(K33/$B$2)*$N$2*6 -> 34.147435 | O33: =+(K33/$B$2)*$O$2*6 -> 42.447501 | P33: =+(K33/$B$2)*$P$2*6 -> 61.684064 | Q33: =+(K33/$B$2)*$Q$2*6 -> 67.175393 | R33: =+(K33/$B$2)*$R$2*6 -> 84.268234 | S33: =+(K33/$B$2)*$S$2*6 -> 88.571636 | T33: =+(K33/$B$2)*$T$2*6 -> 104.90079 | U33: =+(K33/$B$2)*$U$2*6 -> #REF! | V33: =+(K33/$B$2)*$V$2*6 -> 0
B34: 1 | C34: 820 | E34: =+C34*0.0833 -> 68.306 | F34: =(394/12) -> 32.833333 | G34: =+C34/12 -> 68.333333 | H34: =+C34*0.1115 -> 91.43 | I34: =SUM(C34:H34) -> 1080.9027 | K34: =SUM(I34:J34) -> 1080.9027 | M34: =+(K34/$B$2)*$M$2*6 -> 13.73156 | N34: =+(K34/$B$2)*$N$2*6 -> 39.794062 | O34: =+(K34/$B$2)*$O$2*6 -> 49.466628 | P34: =+(K34/$B$2)*$P$2*6 -> 71.884153 | Q34: =+(K34/$B$2)*$Q$2*6 -> 78.28353 | R34: =+(K34/$B$2)*$R$2*6 -> 98.202846 | S34: =+(K34/$B$2)*$S$2*6 -> 103.21786 | T34: =+(K34/$B$2)*$T$2*6 -> 122.24721 | U34: =+(K34/$B$2)*$U$2*6 -> #REF! | V34: =+(K34/$B$2)*$V$2*6 -> 0
A35: CENTRO DE APOYO - QUITO | B35: 1 | C35: 650 | E35: =+C35*0.0833 -> 54.145 | F35: =(394/12) -> 32.833333 | G35: =+C35/12 -> 54.166667 | H35: =+C35*0.1115 -> 72.475 | I35: =SUM(C35:H35) -> 863.62 | K35: =SUM(I35:J35) -> 863.62 | M35: =+(K35/$B$2)*$M$2*6 -> 10.971247 | N35: =+(K35/$B$2)*$N$2*6 -> 31.794674 | O35: =+(K35/$B$2)*$O$2*6 -> 39.522864 | P35: =+(K35/$B$2)*$P$2*6 -> 57.434026 | Q35: =+(K35/$B$2)*$Q$2*6 -> 62.547003 | R35: =+(K35/$B$2)*$R$2*6 -> 78.462145 | S35: =+(K35/$B$2)*$S$2*6 -> 82.469043 | T35: =+(K35/$B$2)*$T$2*6 -> 97.673118 | U35: =+(K35/$B$2)*$U$2*6 -> #REF! | V35: =+(K35/$B$2)*$V$2*6 -> 0
B36: 1 | C36: 800 | E36: =+C36*0.0833 -> 66.64 | F36: =(394/12) -> 32.833333 | G36: =+C36/12 -> 66.666667 | H36: =+C36*0.1115 -> 89.2 | I36: =SUM(C36:H36) -> 1055.34 | K36: =SUM(I36:J36) -> 1055.34 | M36: =+(K36/$B$2)*$M$2*6 -> 13.406818 | N36: =+(K36/$B$2)*$N$2*6 -> 38.852958 | O36: =+(K36/$B$2)*$O$2*6 -> 48.296774 | P36: =+(K36/$B$2)*$P$2*6 -> 70.184138 | Q36: =+(K36/$B$2)*$Q$2*6 -> 76.432174 | R36: =+(K36/$B$2)*$R$2*6 -> 95.880411 | S36: =+(K36/$B$2)*$S$2*6 -> 100.77682 | T36: =+(K36/$B$2)*$T$2*6 -> 119.35614 | U36: =+(K36/$B$2)*$U$2*6 -> #REF! | V36: =+(K36/$B$2)*$V$2*6 -> 0
B37: 1 | C37: 650 | E37: =+C37*0.0833 -> 54.145 | F37: =(394/12) -> 32.833333 | G37: =+C37/12 -> 54.166667 | H37: =+C37*0.1115 -> 72.475 | I37: =SUM(C37:H37) -> 863.62 | K37: =SUM(I37:J37) -> 863.62 | M37: =+(K37/$B$2)*$M$2*6 -> 10.971247 | N37: =+(K37/$B$2)*$N$2*6 -> 31.794674 | O37: =+(K37/$B$2)*$O$2*6 -> 39.522864 | P37: =+(K37/$B$2)*$P$2*6 -> 57.434026 | Q37: =+(K37/$B$2)*$Q$2*6 -> 62.547003 | R37: =+(K37/$B$2)*$R$2*6 -> 78.462145 | S37: =+(K37/$B$2)*$S$2*6 -> 82.469043 | T37: =+(K37/$B$2)*$T$2*6 -> 97.673118 | U37: =+(K37/$B$2)*$U$2*6 -> #REF! | V37: =+(K37/$B$2)*$V$2*6 -> 0
B38: 1 | C38: 700 | E38: =+C38*0.0833 -> 58.31 | F38: =(394/12) -> 32.833333 | G38: =+C38/12 -> 58.333333 | H38: =+C38*0.1115 -> 78.05 | I38: =SUM(C38:H38) -> 927.52667 | K38: =SUM(I38:J38) -> 927.52667 | M38: =+(K38/$B$2)*$M$2*6 -> 11.783104 | N38: =+(K38/$B$2)*$N$2*6 -> 34.147435 | O38: =+(K38/$B$2)*$O$2*6 -> 42.447501 | P38: =+(K38/$B$2)*$P$2*6 -> 61.684064 | Q38: =+(K38/$B$2)*$Q$2*6 -> 67.175393 | R38: =+(K38/$B$2)*$R$2*6 -> 84.268234 | S38: =+(K38/$B$2)*$S$2*6 -> 88.571636 | T38: =+(K38/$B$2)*$T$2*6 -> 104.90079 | U38: =+(K38/$B$2)*$U$2*6 -> #REF! | V38: =+(K38/$B$2)*$V$2*6 -> 0
B39: 1 | C39: 900 | E39: =+C39*0.0833 -> 74.97 | F39: =(394/12) -> 32.833333 | G39: =+C39/12 -> 75 | H39: =+C39*0.1115 -> 100.35 | I39: =SUM(C39:H39) -> 1183.1533 | K39: =SUM(I39:J39) -> 1183.1533 | M39: =+(K39/$B$2)*$M$2*6 -> 15.030531 | N39: =+(K39/$B$2)*$N$2*6 -> 43.55848 | O39: =+(K39/$B$2)*$O$2*6 -> 54.146047 | P39: =+(K39/$B$2)*$P$2*6 -> 78.684213 | Q39: =+(K39/$B$2)*$Q$2*6 -> 85.688954 | R39: =+(K39/$B$2)*$R$2*6 -> 107.49259 | S39: =+(K39/$B$2)*$S$2*6 -> 112.98201 | T39: =+(K39/$B$2)*$T$2*6 -> 133.81149 | U39: =+(K39/$B$2)*$U$2*6 -> #REF! | V39: =+(K39/$B$2)*$V$2*6 -> 0
E40: =+C40*0.0833 -> 0 | G40: =+C40/12 -> 0 | H40: =+C40*0.1115 -> 0 | I40: =SUM(C40:H40) -> 0 | K40: =SUM(I40:J40) -> 0 | M40: =+(K40/$B$2)*$M$2*6 -> 0 | N40: =+(K40/$B$2)*$N$2*6 -> 0 | O40: =+(K40/$B$2)*$O$2*6 -> 0 | P40: =+(K40/$B$2)*$P$2*6 -> 0 | Q40: =+(K40/$B$2)*$Q$2*6 -> 0 | R40: =+(K40/$B$2)*$R$2*6 -> 0 | S40: =+(K40/$B$2)*$S$2*6 -> 0 | T40: =+(K40/$B$2)*$T$2*6 -> 0 | U40: =+(K40/$B$2)*$U$2*6 -> #REF! | V40: =+(K40/$B$2)*$V$2*6 -> 0
E41: =+C41*0.0833 -> 0 | G41: =+C41/12 -> 0 | H41: =+C41*0.1115 -> 0 | I41: =SUM(C41:H41) -> 0 | K41: =SUM(I41:J41) -> 0 | M41: =+(K41/$B$2)*$M$2*6 -> 0 | N41: =+(K41/$B$2)*$N$2*6 -> 0 | O41: =+(K41/$B$2)*$O$2*6 -> 0 | P41: =+(K41/$B$2)*$P$2*6 -> 0 | Q41: =+(K41/$B$2)*$Q$2*6 -> 0 | R41: =+(K41/$B$2)*$R$2*6 -> 0 | S41: =+(K41/$B$2)*$S$2*6 -> 0 | T41: =+(K41/$B$2)*$T$2*6 -> 0 | U41: =+(K41/$B$2)*$U$2*6 -> #REF! | V41: =+(K41/$B$2)*$V$2*6 -> 0
A42: Evaluación Interna | B42: 1 | C42: 820 | E42: =+C42*0.0833 -> 68.306 | F42: =(394/12) -> 32.833333 | G42: =+C42/12 -> 68.333333 | H42: =+C42*0.1115 -> 91.43 | I42: =SUM(C42:H42) -> 1080.9027 | K42: =SUM(I42:J42) -> 1080.9027 | M42: =+(K42/$B$2)*$M$2*6 -> 13.73156 | N42: =+(K42/$B$2)*$N$2*6 -> 39.794062 | O42: =+(K42/$B$2)*$O$2*6 -> 49.466628 | P42: =+(K42/$B$2)*$P$2*6 -> 71.884153 | Q42: =+(K42/$B$2)*$Q$2*6 -> 78.28353 | R42: =+(K42/$B$2)*$R$2*6 -> 98.202846 | S42: =+(K42/$B$2)*$S$2*6 -> 103.21786 | T42: =+(K42/$B$2)*$T$2*6 -> 122.24721 | U42: =+(K42/$B$2)*$U$2*6 -> #REF! | V42: =+(K42/$B$2)*$V$2*6 -> 0
B43: 1 | C43: 820 | E43: =+C43*0.0833 -> 68.306 | F43: =(394/12) -> 32.833333 | G43: =+C43/12 -> 68.333333 | H43: =+C43*0.1115 -> 91.43 | I43: =SUM(C43:H43) -> 1080.9027 | K43: =SUM(I43:J43) -> 1080.9027 | M43: =+(K43/$B$2)*$M$2*6 -> 13.73156 | N43: =+(K43/$B$2)*$N$2*6 -> 39.794062 | O43: =+(K43/$B$2)*$O$2*6 -> 49.466628 | P43: =+(K43/$B$2)*$P$2*6 -> 71.884153 | Q43: =+(K43/$B$2)*$Q$2*6 -> 78.28353 | R43: =+(K43/$B$2)*$R$2*6 -> 98.202846 | S43: =+(K43/$B$2)*$S$2*6 -> 103.21786 | T43: =+(K43/$B$2)*$T$2*6 -> 122.24721 | U43: =+(K43/$B$2)*$U$2*6 -> #REF! | V43: =+(K43/$B$2)*$V$2*6 -> 0
B44: 1 | C44: 820 | E44: =+C44*0.0833 -> 68.306 | F44: =(394/12) -> 32.833333 | G44: =+C44/12 -> 68.333333 | H44: =+C44*0.1115 -> 91.43 | I44: =SUM(C44:H44) -> 1080.9027 | K44: =SUM(I44:J44) -> 1080.9027 | M44: =+(K44/$B$2)*$M$2*6 -> 13.73156 | N44: =+(K44/$B$2)*$N$2*6 -> 39.794062 | O44: =+(K44/$B$2)*$O$2*6 -> 49.466628 | P44: =+(K44/$B$2)*$P$2*6 -> 71.884153 | Q44: =+(K44/$B$2)*$Q$2*6 -> 78.28353 | R44: =+(K44/$B$2)*$R$2*6 -> 98.202846 | S44: =+(K44/$B$2)*$S$2*6 -> 103.21786 | T44: =+(K44/$B$2)*$T$2*6 -> 122.24721 | U44: =+(K44/$B$2)*$U$2*6 -> #REF! | V44: =+(K44/$B$2)*$V$2*6 -> 0
B45: 1 | C45: 820 | E45: =+C45*0.0833 -> 68.306 | F45: =(394/12) -> 32.833333 | G45: =+C45/12 -> 68.333333 | H45: =+C45*0.1115 -> 91.43 | I45: =SUM(C45:H45) -> 1080.9027 | K45: =SUM(I45:J45) -> 1080.9027 | M45: =+(K45/$B$2)*$M$2*6 -> 13.73156 | N45: =+(K45/$B$2)*$N$2*6 -> 39.794062 | O45: =+(K45/$B$2)*$O$2*6 -> 49.466628 | P45: =+(K45/$B$2)*$P$2*6 -> 71.884153 | Q45: =+(K45/$B$2)*$Q$2*6 -> 78.28353 | R45: =+(K45/$B$2)*$R$2*6 -> 98.202846 | S45: =+(K45/$B$2)*$S$2*6 -> 103.21786 | T45: =+(K45/$B$2)*$T$2*6 -> 122.24721 | U45: =+(K45/$B$2)*$U$2*6 -> #REF! | V45: =+(K45/$B$2)*$V$2*6 -> 0
B46: 1 | C46: 700 | E46: =+C46*0.0833 -> 58.31 | F46: =(394/12) -> 32.833333 | G46: =+C46/12 -> 58.333333 | H46: =+C46*0.1115 -> 78.05 | I46: =SUM(C46:H46) -> 927.52667 | K46: =SUM(I46:J46) -> 927.52667 | M46: =+(K46/$B$2)*$M$2*6 -> 11.783104 | N46: =+(K46/$B$2)*$N$2*6 -> 34.147435 | O46: =+(K46/$B$2)*$O$2*6 -> 42.447501 | P46: =+(K46/$B$2)*$P$2*6 -> 61.684064 | Q46: =+(K46/$B$2)*$Q$2*6 -> 67.175393 | R46: =+(K46/$B$2)*$R$2*6 -> 84.268234 | S46: =+(K46/$B$2)*$S$2*6 -> 88.571636 | T46: =+(K46/$B$2)*$T$2*6 -> 104.90079 | U46: =+(K46/$B$2)*$U$2*6 -> #REF! | V46: =+(K46/$B$2)*$V$2*6 -> 0
B47: 1 | C47: 820 | E47: =+C47*0.0833 -> 68.306 | F47: =(394/12) -> 32.833333 | G47: =+C47/12 -> 68.333333 | H47: =+C47*0.1115 -> 91.43 | I47: =SUM(C47:H47) -> 1080.9027 | K47: =SUM(I47:J47) -> 1080.9027 | M47: =+(K47/$B$2)*$M$2*6 -> 13.73156 | N47: =+(K47/$B$2)*$N$2*6 -> 39.794062 | O47: =+(K47/$B$2)*$O$2*6 -> 49.466628 | P47: =+(K47/$B$2)*$P$2*6 -> 71.884153 | Q47: =+(K47/$B$2)*$Q$2*6 -> 78.28353 | R47: =+(K47/$B$2)*$R$2*6 -> 98.202846 | S47: =+(K47/$B$2)*$S$2*6 -> 103.21786 | T47: =+(K47/$B$2)*$T$2*6 -> 122.24721 | U47: =+(K47/$B$2)*$U$2*6 -> #REF! | V47: =+(K47/$B$2)*$V$2*6 -> 0
E48: =+C48*0.0833 -> 0 | G48: =+C48/12 -> 0 | H48: =+C48*0.1115 -> 0 | I48: =SUM(C48:H48) -> 0 | K48: =SUM(I48:J48) -> 0 | M48: =+(K48/$B$2)*$M$2*6 -> 0 | N48: =+(K48/$B$2)*$N$2*6 -> 0 | O48: =+(K48/$B$2)*$O$2*6 -> 0 | P48: =+(K48/$B$2)*$P$2*6 -> 0 | Q48: =+(K48/$B$2)*$Q$2*6 -> 0 | R48: =+(K48/$B$2)*$R$2*6 -> 0 | S48: =+(K48/$B$2)*$S$2*6 -> 0 | T48: =+(K48/$B$2)*$T$2*6 -> 0 | U48: =+(K48/$B$2)*$U$2*6 -> #REF! | V48: =+(K48/$B$2)*$V$2*6 -> 0
A49: CENTRO DE APOYO - TENA | B49: 1 | C49: 650 | E49: =+C49*0.0833 -> 54.145 | F49: =(394/12) -> 32.833333 | G49: =+C49/12 -> 54.166667 | H49: =+C49*0.1115 -> 72.475 | I49: =SUM(C49:H49) -> 863.62 | K49: =SUM(I49:J49) -> 863.62 | M49: =+(K49/$B$2)*$M$2*6 -> 10.971247 | N49: =+(K49/$B$2)*$N$2*6 -> 31.794674 | O49: =+(K49/$B$2)*$O$2*6 -> 39.522864 | P49: =+(K49/$B$2)*$P$2*6 -> 57.434026 | Q49: =+(K49/$B$2)*$Q$2*6 -> 62.547003 | R49: =+(K49/$B$2)*$R$2*6 -> 78.462145 | S49: =+(K49/$B$2)*$S$2*6 -> 82.469043 | T49: =+(K49/$B$2)*$T$2*6 -> 97.673118 | U49: =+(K49/$B$2)*$U$2*6 -> #REF! | V49: =+(K49/$B$2)*$V$2*6 -> 0
B50: 1 | C50: 650 | E50: =+C50*0.0833 -> 54.145 | F50: =(394/12) -> 32.833333 | G50: =+C50/12 -> 54.166667 | H50: =+C50*0.1115 -> 72.475 | I50: =SUM(C50:H50) -> 863.62 | K50: =SUM(I50:J50) -> 863.62 | M50: =+(K50/$B$2)*$M$2*6 -> 10.971247 | N50: =+(K50/$B$2)*$N$2*6 -> 31.794674 | O50: =+(K50/$B$2)*$O$2*6 -> 39.522864 | P50: =+(K50/$B$2)*$P$2*6 -> 57.434026 | Q50: =+(K50/$B$2)*$Q$2*6 -> 62.547003 | R50: =+(K50/$B$2)*$R$2*6 -> 78.462145 | S50: =+(K50/$B$2)*$S$2*6 -> 82.469043 | T50: =+(K50/$B$2)*$T$2*6 -> 97.673118 | U50: =+(K50/$B$2)*$U$2*6 -> #REF! | V50: =+(K50/$B$2)*$V$2*6 -> 0
B51: 1 | C51: 700 | E51: =+C51*0.0833 -> 58.31 | F51: =(394/12) -> 32.833333 | G51: =+C51/12 -> 58.333333 | H51: =+C51*0.1115 -> 78.05 | I51: =SUM(C51:H51) -> 927.52667 | K51: =SUM(I51:J51) -> 927.52667 | M51: =+(K51/$B$2)*$M$2*6 -> 11.783104 | N51: =+(K51/$B$2)*$N$2*6 -> 34.147435 | O51: =+(K51/$B$2)*$O$2*6 -> 42.447501 | P51: =+(K51/$B$2)*$P$2*6 -> 61.684064 | Q51: =+(K51/$B$2)*$Q$2*6 -> 67.175393 | R51: =+(K51/$B$2)*$R$2*6 -> 84.268234 | S51: =+(K51/$B$2)*$S$2*6 -> 88.571636 | T51: =+(K51/$B$2)*$T$2*6 -> 104.90079 | U51: =+(K51/$B$2)*$U$2*6 -> #REF! | V51: =+(K51/$B$2)*$V$2*6 -> 0
B52: 1 | C52: 820 | E52: =+C52*0.0833 -> 68.306 | F52: =(394/12) -> 32.833333 | G52: =+C52/12 -> 68.333333 | H52: =+C52*0.1115 -> 91.43 | I52: =SUM(C52:H52) -> 1080.9027 | K52: =SUM(I52:J52) -> 1080.9027 | M52: =+(K52/$B$2)*$M$2*6 -> 13.73156 | N52: =+(K52/$B$2)*$N$2*6 -> 39.794062 | O52: =+(K52/$B$2)*$O$2*6 -> 49.466628 | P52: =+(K52/$B$2)*$P$2*6 -> 71.884153 | Q52: =+(K52/$B$2)*$Q$2*6 -> 78.28353 | R52: =+(K52/$B$2)*$R$2*6 -> 98.202846 | S52: =+(K52/$B$2)*$S$2*6 -> 103.21786 | T52: =+(K52/$B$2)*$T$2*6 -> 122.24721 | U52: =+(K52/$B$2)*$U$2*6 -> #REF! | V52: =+(K52/$B$2)*$V$2*6 -> 0
B53: 1 | C53: 1090 | E53: =+C53*0.0833 -> 90.797 | F53: =(394/12) -> 32.833333 | G53: =+C53/12 -> 90.833333 | H53: =+C53*0.1115 -> 121.535 | I53: =SUM(C53:H53) -> 1425.9987 | K53: =SUM(I53:J53) -> 1425.9987 | M53: =+(K53/$B$2)*$M$2*6 -> 18.115588 | N53: =+(K53/$B$2)*$N$2*6 -> 52.498973 | O53: =+(K53/$B$2)*$O$2*6 -> 65.259665 | P53: =+(K53/$B$2)*$P$2*6 -> 94.834354 | Q53: =+(K53/$B$2)*$Q$2*6 -> 103.27684 | R53: =+(K53/$B$2)*$R$2*6 -> 129.55572 | S53: =+(K53/$B$2)*$S$2*6 -> 136.17186 | T53: =+(K53/$B$2)*$T$2*6 -> 161.27664 | U53: =+(K53/$B$2)*$U$2*6 -> #REF! | V53: =+(K53/$B$2)*$V$2*6 -> 0
E54: =+C54*0.0833 -> 0 | G54: =+C54/12 -> 0 | H54: =+C54*0.1115 -> 0 | I54: =SUM(C54:H54) -> 0 | K54: =SUM(I54:J54) -> 0 | M54: =+(K54/$B$2)*$M$2*6 -> 0 | N54: =+(K54/$B$2)*$N$2*6 -> 0 | O54: =+(K54/$B$2)*$O$2*6 -> 0 | P54: =+(K54/$B$2)*$P$2*6 -> 0 | Q54: =+(K54/$B$2)*$Q$2*6 -> 0 | R54: =+(K54/$B$2)*$R$2*6 -> 0 | S54: =+(K54/$B$2)*$S$2*6 -> 0 | T54: =+(K54/$B$2)*$T$2*6 -> 0 | U54: =+(K54/$B$2)*$U$2*6 -> #REF! | V54: =+(K54/$B$2)*$V$2*6 -> 0
A55: Editorial | B55: 1 | C55: 750 | E55: =+C55*0.0833 -> 62.475 | F55: =(394/12) -> 32.833333 | G55: =+C55/12 -> 62.5 | H55: =+C55*0.1115 -> 83.625 | I55: =SUM(C55:H55) -> 991.43333 | K55: =SUM(I55:J55) -> 991.43333 | M55: =+(K55/$B$2)*$M$2*6 -> 12.594961 | N55: =+(K55/$B$2)*$N$2*6 -> 36.500196 | O55: =+(K55/$B$2)*$O$2*6 -> 45.372137 | P55: =+(K55/$B$2)*$P$2*6 -> 65.934101 | Q55: =+(K55/$B$2)*$Q$2*6 -> 71.803783 | R55: =+(K55/$B$2)*$R$2*6 -> 90.074322 | S55: =+(K55/$B$2)*$S$2*6 -> 94.674229 | T55: =+(K55/$B$2)*$T$2*6 -> 112.12847 | U55: =+(K55/$B$2)*$U$2*6 -> #REF! | V55: =+(K55/$B$2)*$V$2*6 -> 0
B56: 1 | C56: 820 | E56: =+C56*0.0833 -> 68.306 | F56: =(394/12) -> 32.833333 | G56: =+C56/12 -> 68.333333 | H56: =+C56*0.1115 -> 91.43 | I56: =SUM(C56:H56) -> 1080.9027 | K56: =SUM(I56:J56) -> 1080.9027 | M56: =+(K56/$B$2)*$M$2*6 -> 13.73156 | N56: =+(K56/$B$2)*$N$2*6 -> 39.794062 | O56: =+(K56/$B$2)*$O$2*6 -> 49.466628 | P56: =+(K56/$B$2)*$P$2*6 -> 71.884153 | Q56: =+(K56/$B$2)*$Q$2*6 -> 78.28353 | R56: =+(K56/$B$2)*$R$2*6 -> 98.202846 | S56: =+(K56/$B$2)*$S$2*6 -> 103.21786 | T56: =+(K56/$B$2)*$T$2*6 -> 122.24721 | U56: =+(K56/$B$2)*$U$2*6 -> #REF! | V56: =+(K56/$B$2)*$V$2*6 -> 0
B57: 1 | C57: 700 | E57: =+C57*0.0833 -> 58.31 | F57: =(394/12) -> 32.833333 | G57: =+C57/12 -> 58.333333 | H57: =+C57*0.1115 -> 78.05 | I57: =SUM(C57:H57) -> 927.52667 | K57: =SUM(I57:J57) -> 927.52667 | M57: =+(K57/$B$2)*$M$2*6 -> 11.783104 | N57: =+(K57/$B$2)*$N$2*6 -> 34.147435 | O57: =+(K57/$B$2)*$O$2*6 -> 42.447501 | P57: =+(K57/$B$2)*$P$2*6 -> 61.684064 | Q57: =+(K57/$B$2)*$Q$2*6 -> 67.175393 | R57: =+(K57/$B$2)*$R$2*6 -> 84.268234 | S57: =+(K57/$B$2)*$S$2*6 -> 88.571636 | T57: =+(K57/$B$2)*$T$2*6 -> 104.90079 | U57: =+(K57/$B$2)*$U$2*6 -> #REF! | V57: =+(K57/$B$2)*$V$2*6 -> 0
B58: 1 | C58: 902.95 | E58: =+C58*0.0833 -> 75.215735 | F58: =(394/12) -> 32.833333 | G58: =+C58/12 -> 75.245833 | H58: =+C58*0.1115 -> 100.67893 | I58: =SUM(C58:H58) -> 1186.9238 | K58: =SUM(I58:J58) -> 1186.9238 | M58: =+(K58/$B$2)*$M$2*6 -> 15.078431 | N58: =+(K58/$B$2)*$N$2*6 -> 43.697293 | O58: =+(K58/$B$2)*$O$2*6 -> 54.3186 | P58: =+(K58/$B$2)*$P$2*6 -> 78.934965 | Q58: =+(K58/$B$2)*$Q$2*6 -> 85.962029 | R58: =+(K58/$B$2)*$R$2*6 -> 107.83515 | S58: =+(K58/$B$2)*$S$2*6 -> 113.34206 | T58: =+(K58/$B$2)*$T$2*6 -> 134.23792 | U58: =+(K58/$B$2)*$U$2*6 -> #REF! | V58: =+(K58/$B$2)*$V$2*6 -> 0
B59: 1 | C59: 700 | E59: =+C59*0.0833 -> 58.31 | F59: =(394/12) -> 32.833333 | G59: =+C59/12 -> 58.333333 | H59: =+C59*0.1115 -> 78.05 | I59: =SUM(C59:H59) -> 927.52667 | K59: =SUM(I59:J59) -> 927.52667 | M59: =+(K59/$B$2)*$M$2*6 -> 11.783104 | N59: =+(K59/$B$2)*$N$2*6 -> 34.147435 | O59: =+(K59/$B$2)*$O$2*6 -> 42.447501 | P59: =+(K59/$B$2)*$P$2*6 -> 61.684064 | Q59: =+(K59/$B$2)*$Q$2*6 -> 67.175393 | R59: =+(K59/$B$2)*$R$2*6 -> 84.268234 | S59: =+(K59/$B$2)*$S$2*6 -> 88.571636 | T59: =+(K59/$B$2)*$T$2*6 -> 104.90079 | U59: =+(K59/$B$2)*$U$2*6 -> #REF! | V59: =+(K59/$B$2)*$V$2*6 -> 0
B60: 1 | C60: 650 | E60: =+C60*0.0833 -> 54.145 | F60: =(394/12) -> 32.833333 | G60: =+C60/12 -> 54.166667 | H60: =+C60*0.1115 -> 72.475 | I60: =SUM(C60:H60) -> 863.62 | K60: =SUM(I60:J60) -> 863.62 | M60: =+(K60/$B$2)*$M$2*6 -> 10.971247 | N60: =+(K60/$B$2)*$N$2*6 -> 31.794674 | O60: =+(K60/$B$2)*$O$2*6 -> 39.522864 | P60: =+(K60/$B$2)*$P$2*6 -> 57.434026 | Q60: =+(K60/$B$2)*$Q$2*6 -> 62.547003 | R60: =+(K60/$B$2)*$R$2*6 -> 78.462145 | S60: =+(K60/$B$2)*$S$2*6 -> 82.469043 | T60: =+(K60/$B$2)*$T$2*6 -> 97.673118 | U60: =+(K60/$B$2)*$U$2*6 -> #REF! | V60: =+(K60/$B$2)*$V$2*6 -> 0
E61: =+C61*0.0833 -> 0 | G61: =+C61/12 -> 0 | H61: =+C61*0.1115 -> 0 | I61: =SUM(C61:H61) -> 0 | K61: =SUM(I61:J61) -> 0 | M61: =+(K61/$B$2)*$M$2*6 -> 0 | N61: =+(K61/$B$2)*$N$2*6 -> 0 | O61: =+(K61/$B$2)*$O$2*6 -> 0 | P61: =+(K61/$B$2)*$P$2*6 -> 0 | Q61: =+(K61/$B$2)*$Q$2*6 -> 0 | R61: =+(K61/$B$2)*$R$2*6 -> 0 | S61: =+(K61/$B$2)*$S$2*6 -> 0 | T61: =+(K61/$B$2)*$T$2*6 -> 0 | U61: =+(K61/$B$2)*$U$2*6 -> #REF! | V61: =+(K61/$B$2)*$V$2*6 -> 0
E62: =+C62*0.0833 -> 0 | G62: =+C62/12 -> 0 | H62: =+C62*0.1115 -> 0 | I62: =SUM(C62:H62) -> 0 | K62: =SUM(I62:J62) -> 0 | M62: =+(K62/$B$2)*$M$2*6 -> 0 | N62: =+(K62/$B$2)*$N$2*6 -> 0 | O62: =+(K62/$B$2)*$O$2*6 -> 0 | P62: =+(K62/$B$2)*$P$2*6 -> 0 | Q62: =+(K62/$B$2)*$Q$2*6 -> 0 | R62: =+(K62/$B$2)*$R$2*6 -> 0 | S62: =+(K62/$B$2)*$S$2*6 -> 0 | T62: =+(K62/$B$2)*$T$2*6 -> 0 | U62: =+(K62/$B$2)*$U$2*6 -> #REF! | V62: =+(K62/$B$2)*$V$2*6 -> 0
A63: Seguridad Ocupacional | B63: 1 | C63: 1350 | D63: 0 | E63: =+C63*0.0833 -> 112.455 | F63: =(394/12) -> 32.833333 | G63: =+C63/12 -> 112.5 | H63: =+C63*0.1115 -> 150.525 | I63: =SUM(C63:H63) -> 1758.3133 | K63: =SUM(I63:J63) -> 1758.3133 | M63: =+(K63/$B$2)*$M$2*6 -> 22.337243 | N63: =+(K63/$B$2)*$N$2*6 -> 64.733331 | O63: =+(K63/$B$2)*$O$2*6 -> 80.467775 | P63: =+(K63/$B$2)*$P$2*6 -> 116.93455 | Q63: =+(K63/$B$2)*$Q$2*6 -> 127.34447 | R63: =+(K63/$B$2)*$R$2*6 -> 159.74738 | S63: =+(K63/$B$2)*$S$2*6 -> 167.90535 | T63: =+(K63/$B$2)*$T$2*6 -> 198.86055 | U63: =+(K63/$B$2)*$U$2*6 -> #REF! | V63: =+(K63/$B$2)*$V$2*6 -> 0
B64: 1 | C64: 820 | E64: =+C64*0.0833 -> 68.306 | F64: =(394/12) -> 32.833333 | G64: =+C64/12 -> 68.333333 | H64: =+C64*0.1115 -> 91.43 | I64: =SUM(C64:H64) -> 1080.9027 | K64: =SUM(I64:J64) -> 1080.9027 | M64: =+(K64/$B$2)*$M$2*6 -> 13.73156 | N64: =+(K64/$B$2)*$N$2*6 -> 39.794062 | O64: =+(K64/$B$2)*$O$2*6 -> 49.466628 | P64: =+(K64/$B$2)*$P$2*6 -> 71.884153 | Q64: =+(K64/$B$2)*$Q$2*6 -> 78.28353 | R64: =+(K64/$B$2)*$R$2*6 -> 98.202846 | S64: =+(K64/$B$2)*$S$2*6 -> 103.21786 | T64: =+(K64/$B$2)*$T$2*6 -> 122.24721 | U64: =+(K64/$B$2)*$U$2*6 -> #REF! | V64: =+(K64/$B$2)*$V$2*6 -> 0
M65: =+(K65/$B$2)*$M$2*6 -> 0 | N65: =+(K65/$B$2)*$N$2*6 -> 0 | O65: =+(K65/$B$2)*$O$2*6 -> 0 | P65: =+(K65/$B$2)*$P$2*6 -> 0 | Q65: =+(K65/$B$2)*$Q$2*6 -> 0 | R65: =+(K65/$B$2)*$R$2*6 -> 0 | S65: =+(K65/$B$2)*$S$2*6 -> 0 | T65: =+(K65/$B$2)*$T$2*6 -> 0 | U65: =+(K65/$B$2)*$U$2*6 -> #REF! | V65: =+(K65/$B$2)*$V$2*6 -> 0
A66: CENTRO DE APOYO - ZAMORA | B66: 1 | C66: 820 | E66: =+C66*0.0833 -> 68.306 | F66: =(394/12) -> 32.833333 | G66: =+C66/12 -> 68.333333 | H66: =+C66*0.1115 -> 91.43 | I66: =SUM(C66:H66) -> 1080.9027 | K66: =SUM(I66:J66) -> 1080.9027 | M66: =+(K66/$B$2)*$M$2*6 -> 13.73156 | N66: =+(K66/$B$2)*$N$2*6 -> 39.794062 | O66: =+(K66/$B$2)*$O$2*6 -> 49.466628 | P66: =+(K66/$B$2)*$P$2*6 -> 71.884153 | Q66: =+(K66/$B$2)*$Q$2*6 -> 78.28353 | R66: =+(K66/$B$2)*$R$2*6 -> 98.202846 | S66: =+(K66/$B$2)*$S$2*6 -> 103.21786 | T66: =+(K66/$B$2)*$T$2*6 -> 122.24721 | U66: =+(K66/$B$2)*$U$2*6 -> #REF! | V66: =+(K66/$B$2)*$V$2*6 -> 0
B67: 1 | C67: 900 | E67: =+C67*0.0833 -> 74.97 | F67: =(394/12) -> 32.833333 | G67: =+C67/12 -> 75 | H67: =+C67*0.1115 -> 100.35 | I67: =SUM(C67:H67) -> 1183.1533 | K67: =SUM(I67:J67) -> 1183.1533 | M67: =+(K67/$B$2)*$M$2*6 -> 15.030531 | N67: =+(K67/$B$2)*$N$2*6 -> 43.55848 | O67: =+(K67/$B$2)*$O$2*6 -> 54.146047 | P67: =+(K67/$B$2)*$P$2*6 -> 78.684213 | Q67: =+(K67/$B$2)*$Q$2*6 -> 85.688954 | R67: =+(K67/$B$2)*$R$2*6 -> 107.49259 | S67: =+(K67/$B$2)*$S$2*6 -> 112.98201 | T67: =+(K67/$B$2)*$T$2*6 -> 133.81149 | U67: =+(K67/$B$2)*$U$2*6 -> #REF! | V67: =+(K67/$B$2)*$V$2*6 -> 0
B68: 1 | C68: 700 | E68: =+C68*0.0833 -> 58.31 | F68: =(394/12) -> 32.833333 | G68: =+C68/12 -> 58.333333 | H68: =+C68*0.1115 -> 78.05 | I68: =SUM(C68:H68) -> 927.52667 | K68: =SUM(I68:J68) -> 927.52667 | M68: =+(K68/$B$2)*$M$2*6 -> 11.783104 | N68: =+(K68/$B$2)*$N$2*6 -> 34.147435 | O68: =+(K68/$B$2)*$O$2*6 -> 42.447501 | P68: =+(K68/$B$2)*$P$2*6 -> 61.684064 | Q68: =+(K68/$B$2)*$Q$2*6 -> 67.175393 | R68: =+(K68/$B$2)*$R$2*6 -> 84.268234 | S68: =+(K68/$B$2)*$S$2*6 -> 88.571636 | T68: =+(K68/$B$2)*$T$2*6 -> 104.90079 | U68: =+(K68/$B$2)*$U$2*6 -> #REF! | V68: =+(K68/$B$2)*$V$2*6 -> 0
B69: 1 | C69: =387.07*2 -> 774.14 | E69: =+C69*0.0833 -> 64.485862 | F69: =(394/12) -> 32.833333 | G69: =+C69/12 -> 64.511667 | H69: =+C69*0.1115 -> 86.31661 | I69: =SUM(C69:H69) -> 1022.2875 | K69: =SUM(I69:J69) -> 1022.2875 | M69: =+(K69/$B$2)*$M$2*6 -> 12.986925 | N69: =+(K69/$B$2)*$N$2*6 -> 37.63611 | O69: =+(K69/$B$2)*$O$2*6 -> 46.784152 | P69: =+(K69/$B$2)*$P$2*6 -> 67.986019 | Q69: =+(K69/$B$2)*$Q$2*6 -> 74.03837 | R69: =+(K69/$B$2)*$R$2*6 -> 92.877502 | S69: =+(K69/$B$2)*$S$2*6 -> 97.620561 | T69: =+(K69/$B$2)*$T$2*6 -> 115.61799 | U69: =+(K69/$B$2)*$U$2*6 -> #REF! | V69: =+(K69/$B$2)*$V$2*6 -> 0
M70: =+(K70/$B$2)*$M$2*6 -> 0 | N70: =+(K70/$B$2)*$N$2*6 -> 0 | O70: =+(K70/$B$2)*$O$2*6 -> 0 | P70: =+(K70/$B$2)*$P$2*6 -> 0 | Q70: =+(K70/$B$2)*$Q$2*6 -> 0 | R70: =+(K70/$B$2)*$R$2*6 -> 0 | S70: =+(K70/$B$2)*$S$2*6 -> 0 | T70: =+(K70/$B$2)*$T$2*6 -> 0 | U70: =+(K70/$B$2)*$U$2*6 -> #REF! | V70: =+(K70/$B$2)*$V$2*6 -> 0
A71: Dirección de Planificación | B71: 1 | C71: 1500 | E71: =+C71*0.0833 -> 124.95 | F71: =(394/12) -> 32.833333 | G71: =+C71/12 -> 125 | H71: =+C71*0.1115 -> 167.25 | I71: =SUM(C71:H71) -> 1950.0333 | K71: =SUM(I71:J71) -> 1950.0333 | M71: =+(K71/$B$2)*$M$2*6 -> 24.772814 | N71: =+(K71/$B$2)*$N$2*6 -> 71.791615 | O71: =+(K71/$B$2)*$O$2*6 -> 89.241684 | P71: =+(K71/$B$2)*$P$2*6 -> 129.68466 | Q71: =+(K71/$B$2)*$Q$2*6 -> 141.22964 | R71: =+(K71/$B$2)*$R$2*6 -> 177.16565 | S71: =+(K71/$B$2)*$S$2*6 -> 186.21313 | T71: =+(K71/$B$2)*$T$2*6 -> 220.54357 | U71: =+(K71/$B$2)*$U$2*6 -> #REF! | V71: =+(K71/$B$2)*$V$2*6 -> 0
B72: 1 | C72: 820 | E72: =+C72*0.0833 -> 68.306 | F72: =(394/12) -> 32.833333 | G72: =+C72/12 -> 68.333333 | H72: =+C72*0.1115 -> 91.43 | I72: =SUM(C72:H72) -> 1080.9027 | K72: =SUM(I72:J72) -> 1080.9027 | M72: =+(K72/$B$2)*$M$2*6 -> 13.73156 | N72: =+(K72/$B$2)*$N$2*6 -> 39.794062 | O72: =+(K72/$B$2)*$O$2*6 -> 49.466628 | P72: =+(K72/$B$2)*$P$2*6 -> 71.884153 | Q72: =+(K72/$B$2)*$Q$2*6 -> 78.28353 | R72: =+(K72/$B$2)*$R$2*6 -> 98.202846 | S72: =+(K72/$B$2)*$S$2*6 -> 103.21786 | T72: =+(K72/$B$2)*$T$2*6 -> 122.24721 | U72: =+(K72/$B$2)*$U$2*6 -> #REF! | V72: =+(K72/$B$2)*$V$2*6 -> 0
B73: 1 | C73: 820 | E73: =+C73*0.0833 -> 68.306 | F73: =(394/12) -> 32.833333 | G73: =+C73/12 -> 68.333333 | H73: =+C73*0.1115 -> 91.43 | I73: =SUM(C73:H73) -> 1080.9027 | K73: =SUM(I73:J73) -> 1080.9027 | M73: =+(K73/$B$2)*$M$2*6 -> 13.73156 | N73: =+(K73/$B$2)*$N$2*6 -> 39.794062 | O73: =+(K73/$B$2)*$O$2*6 -> 49.466628 | P73: =+(K73/$B$2)*$P$2*6 -> 71.884153 | Q73: =+(K73/$B$2)*$Q$2*6 -> 78.28353 | R73: =+(K73/$B$2)*$R$2*6 -> 98.202846 | S73: =+(K73/$B$2)*$S$2*6 -> 103.21786 | T73: =+(K73/$B$2)*$T$2*6 -> 122.24721 | U73: =+(K73/$B$2)*$U$2*6 -> #REF! | V73: =+(K73/$B$2)*$V$2*6 -> 0
B74: 1 | C74: 2200 | E74: =+C74*0.0833 -> 183.26 | F74: =(394/12) -> 32.833333 | G74: =+C74/12 -> 183.33333 | H74: =+C74*0.1115 -> 245.3 | I74: =SUM(C74:H74) -> 2844.7267 | K74: =SUM(I74:J74) -> 2844.7267 | M74: =+(K74/$B$2)*$M$2*6 -> 36.13881 | N74: =+(K74/$B$2)*$N$2*6 -> 104.73027 | O74: =+(K74/$B$2)*$O$2*6 -> 130.18659 | P74: =+(K74/$B$2)*$P$2*6 -> 189.18518 | Q74: =+(K74/$B$2)*$Q$2*6 -> 206.0271 | R74: =+(K74/$B$2)*$R$2*6 -> 258.45089 | S74: =+(K74/$B$2)*$S$2*6 -> 271.64943 | T74: =+(K74/$B$2)*$T$2*6 -> 321.731 | U74: =+(K74/$B$2)*$U$2*6 -> #REF! | V74: =+(K74/$B$2)*$V$2*6 -> 0
B75: 1 | C75: 820 | E75: =+C75*0.0833 -> 68.306 | F75: =(394/12) -> 32.833333 | G75: =+C75/12 -> 68.333333 | H75: =+C75*0.1115 -> 91.43 | I75: =SUM(C75:H75) -> 1080.9027 | K75: =SUM(I75:J75) -> 1080.9027 | M75: =+(K75/$B$2)*$M$2*6 -> 13.73156 | N75: =+(K75/$B$2)*$N$2*6 -> 39.794062 | O75: =+(K75/$B$2)*$O$2*6 -> 49.466628 | P75: =+(K75/$B$2)*$P$2*6 -> 71.884153 | Q75: =+(K75/$B$2)*$Q$2*6 -> 78.28353 | R75: =+(K75/$B$2)*$R$2*6 -> 98.202846 | S75: =+(K75/$B$2)*$S$2*6 -> 103.21786 | T75: =+(K75/$B$2)*$T$2*6 -> 122.24721 | U75: =+(K75/$B$2)*$U$2*6 -> #REF! | V75: =+(K75/$B$2)*$V$2*6 -> 0
B76: 1 | C76: 900 | E76: =+C76*0.0833 -> 74.97 | G76: =+C76/12 -> 75 | H76: =+C76*0.1115 -> 100.35 | I76: =SUM(C76:H76) -> 1150.32 | K76: =SUM(I76:J76) -> 1150.32 | M76: =+(K76/$B$2)*$M$2*6 -> 14.613424 | N76: =+(K76/$B$2)*$N$2*6 -> 42.349702 | O76: =+(K76/$B$2)*$O$2*6 -> 52.643456 | P76: =+(K76/$B$2)*$P$2*6 -> 76.500671 | Q76: =+(K76/$B$2)*$Q$2*6 -> 83.311026 | R76: =+(K76/$B$2)*$R$2*6 -> 104.50959 | S76: =+(K76/$B$2)*$S$2*6 -> 109.84668 | T76: =+(K76/$B$2)*$T$2*6 -> 130.09812 | U76: =+(K76/$B$2)*$U$2*6 -> #REF! | V76: =+(K76/$B$2)*$V$2*6 -> 0
E77: =+C77*0.0833 -> 0 | G77: =+C77/12 -> 0 | H77: =+C77*0.1115 -> 0 | I77: =SUM(C77:H77) -> 0 | K77: =SUM(I77:J77) -> 0 | M77: =+(K77/$B$2)*$M$2*6 -> 0 | N77: =+(K77/$B$2)*$N$2*6 -> 0 | O77: =+(K77/$B$2)*$O$2*6 -> 0 | P77: =+(K77/$B$2)*$P$2*6 -> 0 | Q77: =+(K77/$B$2)*$Q$2*6 -> 0 | R77: =+(K77/$B$2)*$R$2*6 -> 0 | S77: =+(K77/$B$2)*$S$2*6 -> 0 | T77: =+(K77/$B$2)*$T$2*6 -> 0 | U77: =+(K77/$B$2)*$U$2*6 -> #REF! | V77: =+(K77/$B$2)*$V$2*6 -> 0
E78: =+C78*0.0833 -> 0 | G78: =+C78/12 -> 0 | H78: =+C78*0.1115 -> 0 | I78: =SUM(C78:H78) -> 0 | K78: =SUM(I78:J78) -> 0 | M78: =+(K78/$B$2)*$M$2*6 -> 0 | N78: =+(K78/$B$2)*$N$2*6 -> 0 | O78: =+(K78/$B$2)*$O$2*6 -> 0 | P78: =+(K78/$B$2)*$P$2*6 -> 0 | Q78: =+(K78/$B$2)*$Q$2*6 -> 0 | R78: =+(K78/$B$2)*$R$2*6 -> 0 | S78: =+(K78/$B$2)*$S$2*6 -> 0 | T78: =+(K78/$B$2)*$T$2*6 -> 0 | U78: =+(K78/$B$2)*$U$2*6 -> #REF! | V78: =+(K78/$B$2)*$V$2*6 -> 0
E79: =+C79*0.0833 -> 0 | G79: =+C79/12 -> 0 | H79: =+C79*0.1115 -> 0 | I79: =SUM(C79:H79) -> 0 | K79: =SUM(I79:J79) -> 0 | M79: =+(K79/$B$2)*$M$2*6 -> 0 | N79: =+(K79/$B$2)*$N$2*6 -> 0 | O79: =+(K79/$B$2)*$O$2*6 -> 0 | P79: =+(K79/$B$2)*$P$2*6 -> 0 | Q79: =+(K79/$B$2)*$Q$2*6 -> 0 | R79: =+(K79/$B$2)*$R$2*6 -> 0 | S79: =+(K79/$B$2)*$S$2*6 -> 0 | T79: =+(K79/$B$2)*$T$2*6 -> 0 | U79: =+(K79/$B$2)*$U$2*6 -> #REF! | V79: =+(K79/$B$2)*$V$2*6 -> 0
E80: =+C80*0.0833 -> 0 | G80: =+C80/12 -> 0 | H80: =+C80*0.1115 -> 0 | I80: =SUM(C80:H80) -> 0 | K80: =SUM(I80:J80) -> 0 | M80: =+(K80/$B$2)*$M$2*6 -> 0 | N80: =+(K80/$B$2)*$N$2*6 -> 0 | O80: =+(K80/$B$2)*$O$2*6 -> 0 | P80: =+(K80/$B$2)*$P$2*6 -> 0 | Q80: =+(K80/$B$2)*$Q$2*6 -> 0 | R80: =+(K80/$B$2)*$R$2*6 -> 0 | S80: =+(K80/$B$2)*$S$2*6 -> 0 | T80: =+(K80/$B$2)*$T$2*6 -> 0 | U80: =+(K80/$B$2)*$U$2*6 -> #REF! | V80: =+(K80/$B$2)*$V$2*6 -> 0
A81: Gestión de Calidad | B81: 1 | C81: 820 | D81: 0 | E81: =+C81*0.0833 -> 68.306 | F81: =(394/12) -> 32.833333 | G81: =+C81/12 -> 68.333333 | H81: =+C81*0.1115 -> 91.43 | I81: =SUM(C81:H81) -> 1080.9027 | K81: =SUM(I81:J81) -> 1080.9027 | M81: =+(K81/$B$2)*$M$2*6 -> 13.73156 | N81: =+(K81/$B$2)*$N$2*6 -> 39.794062 | O81: =+(K81/$B$2)*$O$2*6 -> 49.466628 | P81: =+(K81/$B$2)*$P$2*6 -> 71.884153 | Q81: =+(K81/$B$2)*$Q$2*6 -> 78.28353 | R81: =+(K81/$B$2)*$R$2*6 -> 98.202846 | S81: =+(K81/$B$2)*$S$2*6 -> 103.21786 | T81: =+(K81/$B$2)*$T$2*6 -> 122.24721 | U81: =+(K81/$B$2)*$U$2*6 -> #REF! | V81: =+(K81/$B$2)*$V$2*6 -> 0
B82: 1 | C82: 820 | E82: =+C82*0.0833 -> 68.306 | F82: =(394/12) -> 32.833333 | G82: =+C82/12 -> 68.333333 | H82: =+C82*0.1115 -> 91.43 | I82: =SUM(C82:H82) -> 1080.9027 | K82: =SUM(I82:J82) -> 1080.9027 | M82: =+(K82/$B$2)*$M$2*6 -> 13.73156 | N82: =+(K82/$B$2)*$N$2*6 -> 39.794062 | O82: =+(K82/$B$2)*$O$2*6 -> 49.466628 | P82: =+(K82/$B$2)*$P$2*6 -> 71.884153 | Q82: =+(K82/$B$2)*$Q$2*6 -> 78.28353 | R82: =+(K82/$B$2)*$R$2*6 -> 98.202846 | S82: =+(K82/$B$2)*$S$2*6 -> 103.21786 | T82: =+(K82/$B$2)*$T$2*6 -> 122.24721 | U82: =+(K82/$B$2)*$U$2*6 -> #REF! | V82: =+(K82/$B$2)*$V$2*6 -> 0
B83: 1 | C83: 700 | E83: =+C83*0.0833 -> 58.31 | F83: =(394/12) -> 32.833333 | G83: =+C83/12 -> 58.333333 | H83: =+C83*0.1115 -> 78.05 | I83: =SUM(C83:H83) -> 927.52667 | K83: =SUM(I83:J83) -> 927.52667 | M83: =+(K83/$B$2)*$M$2*6 -> 11.783104 | N83: =+(K83/$B$2)*$N$2*6 -> 34.147435 | O83: =+(K83/$B$2)*$O$2*6 -> 42.447501 | P83: =+(K83/$B$2)*$P$2*6 -> 61.684064 | Q83: =+(K83/$B$2)*$Q$2*6 -> 67.175393 | R83: =+(K83/$B$2)*$R$2*6 -> 84.268234 | S83: =+(K83/$B$2)*$S$2*6 -> 88.571636 | T83: =+(K83/$B$2)*$T$2*6 -> 104.90079 | U83: =+(K83/$B$2)*$U$2*6 -> #REF! | V83: =+(K83/$B$2)*$V$2*6 -> 0
B84: 1 | C84: 700 | E84: =+C84*0.0833 -> 58.31 | F84: =(394/12) -> 32.833333 | G84: =+C84/12 -> 58.333333 | H84: =+C84*0.1115 -> 78.05 | I84: =SUM(C84:H84) -> 927.52667 | K84: =SUM(I84:J84) -> 927.52667 | M84: =+(K84/$B$2)*$M$2*6 -> 11.783104 | N84: =+(K84/$B$2)*$N$2*6 -> 34.147435 | O84: =+(K84/$B$2)*$O$2*6 -> 42.447501 | P84: =+(K84/$B$2)*$P$2*6 -> 61.684064 | Q84: =+(K84/$B$2)*$Q$2*6 -> 67.175393 | R84: =+(K84/$B$2)*$R$2*6 -> 84.268234 | S84: =+(K84/$B$2)*$S$2*6 -> 88.571636 | T84: =+(K84/$B$2)*$T$2*6 -> 104.90079 | U84: =+(K84/$B$2)*$U$2*6 -> #REF! | V84: =+(K84/$B$2)*$V$2*6 -> 0
E85: =+C85*0.0833 -> 0 | G85: =+C85/12 -> 0 | H85: =+C85*0.1115 -> 0 | I85: =SUM(C85:H85) -> 0 | K85: =SUM(I85:J85) -> 0 | M85: =+(K85/$B$2)*$M$2*6 -> 0 | N85: =+(K85/$B$2)*$N$2*6 -> 0 | O85: =+(K85/$B$2)*$O$2*6 -> 0 | P85: =+(K85/$B$2)*$P$2*6 -> 0 | Q85: =+(K85/$B$2)*$Q$2*6 -> 0 | R85: =+(K85/$B$2)*$R$2*6 -> 0 | S85: =+(K85/$B$2)*$S$2*6 -> 0 | T85: =+(K85/$B$2)*$T$2*6 -> 0 | U85: =+(K85/$B$2)*$U$2*6 -> #REF! | V85: =+(K85/$B$2)*$V$2*6 -> 0
A86: CENTRO DE DOCUMENTACION Y ARCHIVO | B86: 1 | C86: 820 | E86: =+C86*0.0833 -> 68.306 | F86: =(394/12) -> 32.833333 | G86: =+C86/12 -> 68.333333 | H86: =+C86*0.1115 -> 91.43 | I86: =SUM(C86:H86) -> 1080.9027 | K86: =SUM(I86:J86) -> 1080.9027 | M86: =+(K86/$B$2)*$M$2*6 -> 13.73156 | N86: =+(K86/$B$2)*$N$2*6 -> 39.794062 | O86: =+(K86/$B$2)*$O$2*6 -> 49.466628 | P86: =+(K86/$B$2)*$P$2*6 -> 71.884153 | Q86: =+(K86/$B$2)*$Q$2*6 -> 78.28353 | R86: =+(K86/$B$2)*$R$2*6 -> 98.202846 | S86: =+(K86/$B$2)*$S$2*6 -> 103.21786 | T86: =+(K86/$B$2)*$T$2*6 -> 122.24721 | U86: =+(K86/$B$2)*$U$2*6 -> #REF! | V86: =+(K86/$B$2)*$V$2*6 -> 0
B87: 1 | C87: 2000 | E87: =+C87*0.0833 -> 166.6 | F87: =(394/12) -> 32.833333 | G87: =+C87/12 -> 166.66667 | H87: =+C87*0.1115 -> 223 | I87: =SUM(C87:H87) -> 2589.1 | K87: =SUM(I87:J87) -> 2589.1 | M87: =+(K87/$B$2)*$M$2*6 -> 32.891383 | N87: =+(K87/$B$2)*$N$2*6 -> 95.319227 | O87: =+(K87/$B$2)*$O$2*6 -> 118.48805 | P87: =+(K87/$B$2)*$P$2*6 -> 172.18503 | Q87: =+(K87/$B$2)*$Q$2*6 -> 187.51354 | R87: =+(K87/$B$2)*$R$2*6 -> 235.22654 | S87: =+(K87/$B$2)*$S$2*6 -> 247.23906 | T87: =+(K87/$B$2)*$T$2*6 -> 292.8203 | U87: =+(K87/$B$2)*$U$2*6 -> #REF! | V87: =+(K87/$B$2)*$V$2*6 -> 0
B88: 1 | C88: 820 | E88: =+C88*0.0833 -> 68.306 | F88: =(394/12) -> 32.833333 | G88: =+C88/12 -> 68.333333 | H88: =+C88*0.1115 -> 91.43 | I88: =SUM(C88:H88) -> 1080.9027 | K88: =SUM(I88:J88) -> 1080.9027 | M88: =+(K88/$B$2)*$M$2*6 -> 13.73156 | N88: =+(K88/$B$2)*$N$2*6 -> 39.794062 | O88: =+(K88/$B$2)*$O$2*6 -> 49.466628 | P88: =+(K88/$B$2)*$P$2*6 -> 71.884153 | Q88: =+(K88/$B$2)*$Q$2*6 -> 78.28353 | R88: =+(K88/$B$2)*$R$2*6 -> 98.202846 | S88: =+(K88/$B$2)*$S$2*6 -> 103.21786 | T88: =+(K88/$B$2)*$T$2*6 -> 122.24721 | U88: =+(K88/$B$2)*$U$2*6 -> #REF! | V88: =+(K88/$B$2)*$V$2*6 -> 0
B89: 1 | C89: 820 | E89: =+C89*0.0833 -> 68.306 | F89: =(394/12) -> 32.833333 | G89: =+C89/12 -> 68.333333 | H89: =+C89*0.1115 -> 91.43 | I89: =SUM(C89:H89) -> 1080.9027 | K89: =SUM(I89:J89) -> 1080.9027 | M89: =+(K89/$B$2)*$M$2*6 -> 13.73156 | N89: =+(K89/$B$2)*$N$2*6 -> 39.794062 | O89: =+(K89/$B$2)*$O$2*6 -> 49.466628 | P89: =+(K89/$B$2)*$P$2*6 -> 71.884153 | Q89: =+(K89/$B$2)*$Q$2*6 -> 78.28353 | R89: =+(K89/$B$2)*$R$2*6 -> 98.202846 | S89: =+(K89/$B$2)*$S$2*6 -> 103.21786 | T89: =+(K89/$B$2)*$T$2*6 -> 122.24721 | U89: =+(K89/$B$2)*$U$2*6 -> #REF! | V89: =+(K89/$B$2)*$V$2*6 -> 0
B90: 1 | C90: 900 | E90: =+C90*0.0833 -> 74.97 | F90: =(394/12) -> 32.833333 | G90: =+C90/12 -> 75 | H90: =+C90*0.1115 -> 100.35 | I90: =SUM(C90:H90) -> 1183.1533 | K90: =SUM(I90:J90) -> 1183.1533 | M90: =+(K90/$B$2)*$M$2*6 -> 15.030531 | N90: =+(K90/$B$2)*$N$2*6 -> 43.55848 | O90: =+(K90/$B$2)*$O$2*6 -> 54.146047 | P90: =+(K90/$B$2)*$P$2*6 -> 78.684213 | Q90: =+(K90/$B$2)*$Q$2*6 -> 85.688954 | R90: =+(K90/$B$2)*$R$2*6 -> 107.49259 | S90: =+(K90/$B$2)*$S$2*6 -> 112.98201 | T90: =+(K90/$B$2)*$T$2*6 -> 133.81149 | U90: =+(K90/$B$2)*$U$2*6 -> #REF! | V90: =+(K90/$B$2)*$V$2*6 -> 0
B91: 1 | C91: 2151.66 | E91: =+C91*0.0833 -> 179.23328 | F91: =(394/12) -> 32.833333 | G91: =+C91/12 -> 179.305 | H91: =+C91*0.1115 -> 239.91009 | I91: =SUM(C91:H91) -> 2782.9417 | K91: =SUM(I91:J91) -> 2782.9417 | M91: =+(K91/$B$2)*$M$2*6 -> 35.353907 | N91: =+(K91/$B$2)*$N$2*6 -> 102.45562 | O91: =+(K91/$B$2)*$O$2*6 -> 127.35906 | P91: =+(K91/$B$2)*$P$2*6 -> 185.07625 | Q91: =+(K91/$B$2)*$Q$2*6 -> 201.55238 | R91: =+(K91/$B$2)*$R$2*6 -> 252.83756 | S91: =+(K91/$B$2)*$S$2*6 -> 265.74945 | T91: =+(K91/$B$2)*$T$2*6 -> 314.74328 | U91: =+(K91/$B$2)*$U$2*6 -> #REF! | V91: =+(K91/$B$2)*$V$2*6 -> 0
E92: =+C92*0.0833 -> 0 | G92: =+C92/12 -> 0 | H92: =+C92*0.1115 -> 0 | I92: =SUM(C92:H92) -> 0 | K92: =SUM(I92:J92) -> 0 | M92: =+(K92/$B$2)*$M$2*6 -> 0 | N92: =+(K92/$B$2)*$N$2*6 -> 0 | O92: =+(K92/$B$2)*$O$2*6 -> 0 | P92: =+(K92/$B$2)*$P$2*6 -> 0 | Q92: =+(K92/$B$2)*$Q$2*6 -> 0 | R92: =+(K92/$B$2)*$R$2*6 -> 0 | S92: =+(K92/$B$2)*$S$2*6 -> 0 | T92: =+(K92/$B$2)*$T$2*6 -> 0 | U92: =+(K92/$B$2)*$U$2*6 -> #REF! | V92: =+(K92/$B$2)*$V$2*6 -> 0
E93: =+C93*0.0833 -> 0 | G93: =+C93/12 -> 0 | H93: =+C93*0.1115 -> 0 | I93: =SUM(C93:H93) -> 0 | K93: =SUM(I93:J93) -> 0 | M93: =+(K93/$B$2)*$M$2*6 -> 0 | N93: =+(K93/$B$2)*$N$2*6 -> 0 | O93: =+(K93/$B$2)*$O$2*6 -> 0 | P93: =+(K93/$B$2)*$P$2*6 -> 0 | Q93: =+(K93/$B$2)*$Q$2*6 -> 0 | R93: =+(K93/$B$2)*$R$2*6 -> 0 | S93: =+(K93/$B$2)*$S$2*6 -> 0 | T93: =+(K93/$B$2)*$T$2*6 -> 0 | U93: =+(K93/$B$2)*$U$2*6 -> #REF! | V93: =+(K93/$B$2)*$V$2*6 -> 0
E94: =+C94*0.0833 -> 0 | G94: =+C94/12 -> 0 | H94: =+C94*0.1115 -> 0 | I94: =SUM(C94:H94) -> 0 | K94: =SUM(I94:J94) -> 0 | M94: =+(K94/$B$2)*$M$2*6 -> 0 | N94: =+(K94/$B$2)*$N$2*6 -> 0 | O94: =+(K94/$B$2)*$O$2*6 -> 0 | P94: =+(K94/$B$2)*$P$2*6 -> 0 | Q94: =+(K94/$B$2)*$Q$2*6 -> 0 | R94: =+(K94/$B$2)*$R$2*6 -> 0 | S94: =+(K94/$B$2)*$S$2*6 -> 0 | T94: =+(K94/$B$2)*$T$2*6 -> 0 | U94: =+(K94/$B$2)*$U$2*6 -> #REF! | V94: =+(K94/$B$2)*$V$2*6 -> 0
E95: =+C95*0.0833 -> 0 | G95: =+C95/12 -> 0 | H95: =+C95*0.1115 -> 0 | I95: =SUM(C95:H95) -> 0 | K95: =SUM(I95:J95) -> 0 | M95: =+(K95/$B$2)*$M$2*6 -> 0 | N95: =+(K95/$B$2)*$N$2*6 -> 0 | O95: =+(K95/$B$2)*$O$2*6 -> 0 | P95: =+(K95/$B$2)*$P$2*6 -> 0 | Q95: =+(K95/$B$2)*$Q$2*6 -> 0 | R95: =+(K95/$B$2)*$R$2*6 -> 0 | S95: =+(K95/$B$2)*$S$2*6 -> 0 | T95: =+(K95/$B$2)*$T$2*6 -> 0 | U95: =+(K95/$B$2)*$U$2*6 -> #REF! | V95: =+(K95/$B$2)*$V$2*6 -> 0
A96: CLINICA ODONTOLOGICA | B96: 1 | C96: 700 | E96: =+C96*0.0833 -> 58.31 | F96: =(394/12) -> 32.833333 | G96: =+C96/12 -> 58.333333 | H96: =+C96*0.1115 -> 78.05 | I96: =SUM(C96:H96) -> 927.52667 | K96: =SUM(I96:J96) -> 927.52667 | M96: =+(K96/$B$2)*$M$2*6 -> 11.783104 | N96: =+(K96/$B$2)*$N$2*6 -> 34.147435 | O96: =+(K96/$B$2)*$O$2*6 -> 42.447501 | P96: =+(K96/$B$2)*$P$2*6 -> 61.684064 | Q96: =+(K96/$B$2)*$Q$2*6 -> 67.175393 | R96: =+(K96/$B$2)*$R$2*6 -> 84.268234 | S96: =+(K96/$B$2)*$S$2*6 -> 88.571636 | T96: =+(K96/$B$2)*$T$2*6 -> 104.90079 | U96: =+(K96/$B$2)*$U$2*6 -> #REF! | V96: =+(K96/$B$2)*$V$2*6 -> 0
B97: 1 | C97: 700 | E97: =+C97*0.0833 -> 58.31 | F97: =(394/12) -> 32.833333 | G97: =+C97/12 -> 58.333333 | H97: =+C97*0.1115 -> 78.05 | I97: =SUM(C97:H97) -> 927.52667 | K97: =SUM(I97:J97) -> 927.52667 | M97: =+(K97/$B$2)*$M$2*6 -> 11.783104 | N97: =+(K97/$B$2)*$N$2*6 -> 34.147435 | O97: =+(K97/$B$2)*$O$2*6 -> 42.447501 | P97: =+(K97/$B$2)*$P$2*6 -> 61.684064 | Q97: =+(K97/$B$2)*$Q$2*6 -> 67.175393 | R97: =+(K97/$B$2)*$R$2*6 -> 84.268234 | S97: =+(K97/$B$2)*$S$2*6 -> 88.571636 | T97: =+(K97/$B$2)*$T$2*6 -> 104.90079 | U97: =+(K97/$B$2)*$U$2*6 -> #REF! | V97: =+(K97/$B$2)*$V$2*6 -> 0
B98: 1 | C98: 700 | E98: =+C98*0.0833 -> 58.31 | F98: =(394/12) -> 32.833333 | G98: =+C98/12 -> 58.333333 | H98: =+C98*0.1115 -> 78.05 | I98: =SUM(C98:H98) -> 927.52667 | K98: =SUM(I98:J98) -> 927.52667 | M98: =+(K98/$B$2)*$M$2*6 -> 11.783104 | N98: =+(K98/$B$2)*$N$2*6 -> 34.147435 | O98: =+(K98/$B$2)*$O$2*6 -> 42.447501 | P98: =+(K98/$B$2)*$P$2*6 -> 61.684064 | Q98: =+(K98/$B$2)*$Q$2*6 -> 67.175393 | R98: =+(K98/$B$2)*$R$2*6 -> 84.268234 | S98: =+(K98/$B$2)*$S$2*6 -> 88.571636 | T98: =+(K98/$B$2)*$T$2*6 -> 104.90079 | U98: =+(K98/$B$2)*$U$2*6 -> #REF! | V98: =+(K98/$B$2)*$V$2*6 -> 0
B99: 1 | C99: 700 | E99: =+C99*0.0833 -> 58.31 | F99: =(394/12) -> 32.833333 | G99: =+C99/12 -> 58.333333 | H99: =+C99*0.1115 -> 78.05 | I99: =SUM(C99:H99) -> 927.52667 | K99: =SUM(I99:J99) -> 927.52667 | M99: =+(K99/$B$2)*$M$2*6 -> 11.783104 | N99: =+(K99/$B$2)*$N$2*6 -> 34.147435 | O99: =+(K99/$B$2)*$O$2*6 -> 42.447501 | P99: =+(K99/$B$2)*$P$2*6 -> 61.684064 | Q99: =+(K99/$B$2)*$Q$2*6 -> 67.175393 | R99: =+(K99/$B$2)*$R$2*6 -> 84.268234 | S99: =+(K99/$B$2)*$S$2*6 -> 88.571636 | T99: =+(K99/$B$2)*$T$2*6 -> 104.90079 | U99: =+(K99/$B$2)*$U$2*6 -> #REF! | V99: =+(K99/$B$2)*$V$2*6 -> 0
B100: 1 | C100: 700 | E100: =+C100*0.0833 -> 58.31 | F100: =(394/12) -> 32.833333 | G100: =+C100/12 -> 58.333333 | H100: =+C100*0.1115 -> 78.05 | I100: =SUM(C100:H100) -> 927.52667 | K100: =SUM(I100:J100) -> 927.52667 | M100: =+(K100/$B$2)*$M$2*6 -> 11.783104 | N100: =+(K100/$B$2)*$N$2*6 -> 34.147435 | O100: =+(K100/$B$2)*$O$2*6 -> 42.447501 | P100: =+(K100/$B$2)*$P$2*6 -> 61.684064 | Q100: =+(K100/$B$2)*$Q$2*6 -> 67.175393 | R100: =+(K100/$B$2)*$R$2*6 -> 84.268234 | S100: =+(K100/$B$2)*$S$2*6 -> 88.571636 | T100: =+(K100/$B$2)*$T$2*6 -> 104.90079 | U100: =+(K100/$B$2)*$U$2*6 -> #REF! | V100: =+(K100/$B$2)*$V$2*6 -> 0
...

Sheet 10 Costos y Gastos
B1: 1.05
A3: PROYECCION DE COSTOS Y GASTOS
A4: CONCEPTO | B4: =+'1 Estudiantes'!B3 -> 2023 | C4: =+'1 Estudiantes'!C3 -> 2023 | D4: =+'1 Estudiantes'!D3 -> 2024 | E4: =+'1 Estudiantes'!E3 -> 2024 | F4: =+'1 Estudiantes'!F3 -> 2025 | G4: =+'1 Estudiantes'!G3 -> 2025 | H4: =+'1 Estudiantes'!H3 -> 2026 | I4: =+'1 Estudiantes'!I3 -> 2026
A5: COSTOS POR SERVICIOS | B5: =SUM(B6:B20) -> 27376.806 | C5: =SUM(C6:C20) -> 88847.297 | D5: =SUM(D6:D20) -> 118741.71 | E5: =SUM(E6:E20) -> 182905.7 | F5: =SUM(F6:F20) -> 210184.62 | G5: =SUM(G6:G20) -> 276049.3 | H5: =SUM(H6:H20) -> 303307.68 | I5: =SUM(I6:I20) -> 365252.7 | J5: =SUM(B5:I5) -> 1572665.8
A6: Mantenimiento Edificio | B6: =+'8 Mantenimiento'!E4 -> 3132.9663 | C6: =+'8 Mantenimiento'!F4 -> 9209.1709 | D6: =+'8 Mantenimiento'!G4 -> 11447.603 | E6: =+'8 Mantenimiento'!H4 -> 16943.821 | F6: =+'8 Mantenimiento'!I4 -> 18452.219 | G6: =+'8 Mantenimiento'!J4 -> 22708.25 | H6: =+'8 Mantenimiento'!K4 -> 23867.913 | I6: =+'8 Mantenimiento'!L4 -> 28268.225 | J6: =SUM(B6:I6) -> 134030.17
A7: =+'5 Demanda'!A27 -> Capacitación Docente | B7: =+'5 Demanda'!B27 -> 179.02525 | C7: =+'5 Demanda'!C27 -> 605.28438 | D7: =+'5 Demanda'!D27 -> 807.04584 | E7: =+'5 Demanda'!E27 -> 1271.4826 | F7: =+'5 Demanda'!F27 -> 1490.3443 | G7: =+'5 Demanda'!G27 -> 1932.9714 | H7: =+'5 Demanda'!H27 -> 2133.6624 | I7: =+'5 Demanda'!I27 -> 2505.0358 | J7: =SUM(B7:I7) -> 10924.852
A8: =+'5 Demanda'!A28 -> Internacionalización | B8: =+'5 Demanda'!B28 -> 115.71035 | C8: =+'5 Demanda'!C28 -> 340.1238 | D8: =+'5 Demanda'!D28 -> 422.79619 | E8: =+'5 Demanda'!E28 -> 634.73767 | F8: =+'5 Demanda'!F28 -> 691.24422 | G8: =+'5 Demanda'!G28 -> 878.83823 | H8: =+'5 Demanda'!H28 -> 923.71866 | I8: =+'5 Demanda'!I28 -> 1108.7856 | J8: =SUM(B8:I8) -> 5115.9547
A9: Insumos Prácticas y Laboratorios
A10: =+'7 Sueldos'!D202 -> Tiempo Completo PhD | B10: =+'7 Sueldos'!E202*$B$1 -> 5637.9053 | C10: =+'7 Sueldos'!F202*$B$1 -> 19050.993 | D10: =+'7 Sueldos'!G202*$B$1 -> 25401.324 | E10: =+'7 Sueldos'!H202*$B$1 -> 39303.763 | F10: =+'7 Sueldos'!I202*$B$1 -> 46069.165 | G10: =+'7 Sueldos'!J202*$B$1 -> 60916.624 | H10: =+'7 Sueldos'!K202*$B$1 -> 67241.3 | I10: =+'7 Sueldos'!L202*$B$1 -> 78972.633 | J10: =SUM(B10:I10) -> 342593.71 | L10: =+J10+J11+J12+J13+J14 -> 1140204.1
A11: =+'7 Sueldos'!D203 -> Tiempo Completo Mgs. | B11: =+'7 Sueldos'!E203*$B$1 -> 9105.9192 | C11: =+'7 Sueldos'!F203*$B$1 -> 30775.167 | D11: =+'7 Sueldos'!G203*$B$1 -> 41033.556 | E11: =+'7 Sueldos'!H203*$B$1 -> 63503.024 | F11: =+'7 Sueldos'!I203*$B$1 -> 74433.873 | G11: =+'7 Sueldos'!J203*$B$1 -> 98431.33 | H11: =+'7 Sueldos'!K203*$B$1 -> 108650.98 | I11: =+'7 Sueldos'!L203*$B$1 -> 127631.37 | J11: =SUM(B11:I11) -> 553565.22
A12: =+'7 Sueldos'!D204 -> Medio Tiempo | B12: =+'7 Sueldos'!E204*$B$1 -> 0 | C12: =+'7 Sueldos'!F204*$B$1 -> 0 | D12: =+'7 Sueldos'!G204*$B$1 -> 0 | E12: =+'7 Sueldos'!H204*$B$1 -> 0 | F12: =+'7 Sueldos'!I204*$B$1 -> 0 | G12: =+'7 Sueldos'!J204*$B$1 -> 0 | H12: =+'7 Sueldos'!K204*$B$1 -> 0 | I12: =+'7 Sueldos'!L204*$B$1 -> 0 | J12: =SUM(B12:I12) -> 0
A13: =+'7 Sueldos'!D205 -> Tiempo Parcial | B13: =+'7 Sueldos'!E205*$B$1 -> 608.31483 | C13: =+'7 Sueldos'!F205*$B$1 -> 2058.9867 | D13: =+'7 Sueldos'!G205*$B$1 -> 2745.3156 | E13: =+'7 Sueldos'!H205*$B$1 -> 4255.0113 | F13: =+'7 Sueldos'!I205*$B$1 -> 4987.4313 | G13: =+'7 Sueldos'!J205*$B$1 -> 6600.1431 | H13: =+'7 Sueldos'!K205*$B$1 -> 7285.4038 | I13: =+'7 Sueldos'!L205*$B$1 -> 8571.9171 | J13: =SUM(B13:I13) -> 37112.524
A14: =+'7 Sueldos'!D206 -> Ocasional Tipo 2 (Técnico Docente) | B14: =+'7 Sueldos'!E206*$B$1 -> 2858.7248 | C14: =+'7 Sueldos'!F206*$B$1 -> 9276.6501 | D14: =+'7 Sueldos'!G206*$B$1 -> 12755.394 | E14: =+'7 Sueldos'!H206*$B$1 -> 20596.633 | F14: =+'7 Sueldos'!I206*$B$1 -> 25010.197 | G14: =+'7 Sueldos'!J206*$B$1 -> 35880.815 | H14: =+'7 Sueldos'!K206*$B$1 -> 42266.383 | I14: =+'7 Sueldos'!L206*$B$1 -> 58287.891 | J14: =SUM(B14:I14) -> 206932.69
A15: =+'5 Demanda'!A33 -> Costo del Seguro Estudiantil | B15: =+'5 Demanda'!B33 -> 921.02477 | C15: =+'5 Demanda'!C33 -> 2707.2983 | D15: =+'5 Demanda'!D33 -> 3365.3493 | E15: =+'5 Demanda'!E33 -> 5052.3493 | F15: =+'5 Demanda'!F33 -> 5502.1269 | G15: =+'5 Demanda'!G33 -> 6995.3272 | H15: =+'5 Demanda'!H33 -> 7352.5639 | I15: =+'5 Demanda'!I33 -> 8825.6492 | J15: =SUM(B15:I15) -> 40721.689
A16: =+'5 Demanda'!A34 -> Becas Institucionales 10 % estudiantes | J16: =SUM(B16:I16) -> 0
A17: =+'9 Inv. Vin. Becas'!A8 -> Investigación 5% | B17: =+'9 Inv. Vin. Becas'!B8*$B$1 -> 3471.0234 | C17: =+'9 Inv. Vin. Becas'!C8*$B$1 -> 10731.038 | D17: =+'9 Inv. Vin. Becas'!D8*$B$1 -> 13339.384 | E17: =+'9 Inv. Vin. Becas'!E8*$B$1 -> 19340.956 | F17: =+'9 Inv. Vin. Becas'!F8*$B$1 -> 21062.755 | G17: =+'9 Inv. Vin. Becas'!G8*$B$1 -> 27245.557 | H17: =+'9 Inv. Vin. Becas'!H8*$B$1 -> 28636.93 | I17: =+'9 Inv. Vin. Becas'!I8*$B$1 -> 34406.103 | J17: =SUM(B17:I17) -> 158233.75
A18: =+'9 Inv. Vin. Becas'!A9 -> Vinculación 1% | B18: =+'9 Inv. Vin. Becas'!B9*$B$1 -> 694.20467 | C18: =+'9 Inv. Vin. Becas'!C9*$B$1 -> 2146.2076 | D18: =+'9 Inv. Vin. Becas'!D9*$B$1 -> 2667.8767 | E18: =+'9 Inv. Vin. Becas'!E9*$B$1 -> 3868.1912 | F18: =+'9 Inv. Vin. Becas'!F9*$B$1 -> 4212.551 | G18: =+'9 Inv. Vin. Becas'!G9*$B$1 -> 5449.1114 | H18: =+'9 Inv. Vin. Becas'!H9*$B$1 -> 5727.3861 | I18: =+'9 Inv. Vin. Becas'!I9*$B$1 -> 6881.2206 | J18: =SUM(B18:I18) -> 31646.749
A19: Materiales y Suministros | B19: =+'5 Demanda'!B105*$B$1 -> 651.987 | C19: =+'5 Demanda'!C105*$B$1 -> 1670.329 | D19: =+'5 Demanda'!D105*$B$1 -> 2053.8855 | E19: =+'5 Demanda'!E105*$B$1 -> 2989.5903 | F19: =+'5 Demanda'!F105*$B$1 -> 3111.9263 | G19: =+'5 Demanda'!G105*$B$1 -> 3813.4751 | H19: =+'5 Demanda'!H105*$B$1 -> 4017.9491 | I19: =+'5 Demanda'!I105*$B$1 -> 4746.4183 | J19: =SUM(B19:I19) -> 23055.561
A20: Depreciación | C20: =+Depreciación!N56 -> 276.04841 | D20: =+Depreciación!O56 -> 2702.179 | E20: =+Depreciación!P56 -> 5146.1422 | F20: =+Depreciación!Q56 -> 5160.7853 | G20: =+Depreciación!R56 -> 5196.8561 | H20: =+Depreciación!S56 -> 5203.4966 | I20: =+Depreciación!T56 -> 5047.4538 | J20: =SUM(B20:I20) -> 28732.961
A21: GASTOS DE ADMINISTRACIÓN | B21: =SUM(B22:B32) -> 32340.876 | C21: =SUM(C22:C32) -> 56507.955 | D21: =SUM(D22:D32) -> 64268.401 | E21: =SUM(E22:E32) -> 81492.48 | F21: =SUM(F22:F32) -> 85875.288 | G21: =SUM(G22:G32) -> 100894.1 | H21: =SUM(H22:H32) -> 104027.97 | I21: =SUM(I22:I32) -> 116452.88 | J21: =SUM(B21:I21) -> 641859.94
A22: Administración Central | B22: =+'Planta central'!M440 -> 4905.8122 | C22: =+'Planta central'!N440 -> 14217.044 | D22: =+'Planta central'!O440 -> 17672.717 | E22: =+'Planta central'!P440 -> 25681.725 | F22: =+'Planta central'!Q440 -> 27968.001 | G22: =+'Planta central'!R440 -> 35084.484 | H22: =+'Planta central'!S440 -> 36876.175 | I22: =+'Planta central'!T440 -> 43674.704 | J22: =SUM(B22:I22) -> 206080.66
A23: =+'7 Sueldos'!D195 -> Decano | B23: =+'7 Sueldos'!E195 -> 2945.2328 | C23: =+'7 Sueldos'!F195 -> 7327.1992 | D23: =+'7 Sueldos'!G195 -> 8618.5197 | E23: =+'7 Sueldos'!H195 -> 11298.594 | F23: =+'7 Sueldos'!I195 -> 11927.203 | G23: =+'7 Sueldos'!J195 -> 14112.355 | H23: =+'7 Sueldos'!K195 -> 14514.694 | I23: =+'7 Sueldos'!L195 -> 16114.782 | J23: =SUM(B23:I23) -> 86858.579
A24: =+'7 Sueldos'!D196 -> Subdecano | B24: =+'7 Sueldos'!E196 -> 2191.0613 | C24: =+'7 Sueldos'!F196 -> 5451.3971 | D24: =+'7 Sueldos'!G196 -> 6412.1326 | E24: =+'7 Sueldos'!H196 -> 8406.7756 | F24: =+'7 Sueldos'!I196 -> 8874.4952 | G24: =+'7 Sueldos'!J196 -> 10500.778 | H24: =+'7 Sueldos'!K196 -> 10800.152 | I24: =+'7 Sueldos'!L196 -> 11991.798 | J24: =SUM(B24:I24) -> 64628.59
A25: =+'7 Sueldos'!D197 -> Director de Carrera | B25: =+'7 Sueldos'!E197 -> 17621.36 | C25: =+'7 Sueldos'!F197 -> 17864.806 | D25: =+'7 Sueldos'!G197 -> 17864.806 | E25: =+'7 Sueldos'!H197 -> 18127.77 | F25: =+'7 Sueldos'!I197 -> 18127.77 | G25: =+'7 Sueldos'!J197 -> 18731.526 | H25: =+'7 Sueldos'!K197 -> 18731.526 | I25: =+'7 Sueldos'!L197 -> 18992.852 | J25: =SUM(B25:I25) -> 146062.42
A26: =+'7 Sueldos'!D198 -> Secretario | B26: =+'7 Sueldos'!E198 -> 773.21905 | C26: =+'7 Sueldos'!F198 -> 1924.8891 | D26: =+'7 Sueldos'!G198 -> 2264.1249 | E26: =+'7 Sueldos'!H198 -> 2970.1566 | F26: =+'7 Sueldos'!I198 -> 3135.4044 | G26: =+'7 Sueldos'!J198 -> 3711.0133 | H26: =+'7 Sueldos'!K198 -> 3816.8132 | I26: =+'7 Sueldos'!L198 -> 4240.5888 | J26: =SUM(B26:I26) -> 22836.209
A27: =+'7 Sueldos'!D199 -> Auxiliar de Secretaria | B27: =+'7 Sueldos'!E199 -> 660.09333 | C27: =+'7 Sueldos'!F199 -> 1643.5188 | D27: =+'7 Sueldos'!G199 -> 1933.1669 | E27: =+'7 Sueldos'!H199 -> 2536.3839 | F27: =+'7 Sueldos'!I199 -> 2677.4982 | G27: =+'7 Sueldos'!J199 -> 3169.2768 | H27: =+'7 Sueldos'!K199 -> 3259.632 | I27: =+'7 Sueldos'!L199 -> 3622.1412 | J27: =SUM(B27:I27) -> 19501.711
A28: =+'7 Sueldos'!D200 -> Coordinador | B28: =+'7 Sueldos'!E200 -> 697.8019 | C28: =+'7 Sueldos'!F200 -> 1737.3089 | D28: =+'7 Sueldos'!G200 -> 2043.4862 | E28: =+'7 Sueldos'!H200 -> 2680.9748 | F28: =+'7 Sueldos'!I200 -> 2830.1336 | G28: =+'7 Sueldos'!J200 -> 3349.8556 | H28: =+'7 Sueldos'!K200 -> 3445.359 | I28: =+'7 Sueldos'!L200 -> 3828.2904 | J28: =SUM(B28:I28) -> 20613.21
A29: =+'7 Sueldos'!D201 -> Bienestar Estudiantil | B29: =+'7 Sueldos'!E201 -> 697.8019 | C29: =+'7 Sueldos'!F201 -> 1737.3089 | D29: =+'7 Sueldos'!G201 -> 2043.4862 | E29: =+'7 Sueldos'!H201 -> 2680.9748 | F29: =+'7 Sueldos'!I201 -> 2830.1336 | G29: =+'7 Sueldos'!J201 -> 3349.8556 | H29: =+'7 Sueldos'!K201 -> 3445.359 | I29: =+'7 Sueldos'!L201 -> 3828.2904 | J29: =SUM(B29:I29) -> 20613.21
A30: =+'7 Sueldos'!D15 -> Bibliotecario | B30: =+'7 Sueldos'!E207 -> 622.38476 | C30: =+'7 Sueldos'!F207 -> 1549.7286 | D30: =+'7 Sueldos'!G207 -> 1822.8475 | E30: =+'7 Sueldos'!H207 -> 2391.7929 | F30: =+'7 Sueldos'!I207 -> 2524.8628 | G30: =+'7 Sueldos'!J207 -> 2988.6979 | H30: =+'7 Sueldos'!K207 -> 3073.9049 | I30: =+'7 Sueldos'!L207 -> 3415.992 | J30: =SUM(B30:I30) -> 18390.212
A31: =+'7 Sueldos'!D16 -> Auxiliar de Servicio | B31: =+'7 Sueldos'!E208 -> 716.84952 | C31: =+'7 Sueldos'!F208 -> 1786.3958 | D31: =+'7 Sueldos'!G208 -> 2101.2241 | E31: =+'7 Sueldos'!H208 -> 2759.3129 | F31: =+'7 Sueldos'!I208 -> 2912.8301 | G31: =+'7 Sueldos'!J208 -> 3449.2921 | H31: =+'7 Sueldos'!K208 -> 3547.6304 | I31: =+'7 Sueldos'!L208 -> 3945.8955 | J31: =SUM(B31:I31) -> 21219.43
A32: =+'7 Sueldos'!D17 -> Guardia | B32: =+'7 Sueldos'!E209 -> 509.25905 | C32: =+'7 Sueldos'!F209 -> 1268.3583 | D32: =+'7 Sueldos'!G209 -> 1491.8895 | E32: =+'7 Sueldos'!H209 -> 1958.0201 | F32: =+'7 Sueldos'!I209 -> 2066.9566 | G32: =+'7 Sueldos'!J209 -> 2446.9614 | H32: =+'7 Sueldos'!K209 -> 2516.7236 | I32: =+'7 Sueldos'!L209 -> 2797.5445 | J32: =SUM(B32:I32) -> 15055.713
A33: GASTOS DE VENTAS | B33: =+B34 -> 87.867881 | C33: =+C34 -> 258.28249 | D33: =+D34 -> 321.06206 | E33: =+E34 -> 482.00573 | F33: =+F34 -> 524.91556 | G33: =+G34 -> 667.3703 | H33: =+H34 -> 701.4515 | I33: =+I34 -> 841.98722 | J33: =+J34 -> 3884.9427
A34: =+'5 Demanda'!A29 -> Marketing y Comunicación | B34: =+'5 Demanda'!B29 -> 87.867881 | C34: =+'5 Demanda'!C29 -> 258.28249 | D34: =+'5 Demanda'!D29 -> 321.06206 | E34: =+'5 Demanda'!E29 -> 482.00573 | F34: =+'5 Demanda'!F29 -> 524.91556 | G34: =+'5 Demanda'!G29 -> 667.3703 | H34: =+'5 Demanda'!H29 -> 701.4515 | I34: =+'5 Demanda'!I29 -> 841.98722 | J34: =SUM(B34:I34) -> 3884.9427
A35: OTROS GASTOS | B35: =SUM(B36:B37) -> 1120.0508 | C35: =SUM(C36:C37) -> 3292.3237 | D35: =SUM(D36:D37) -> 4212.5743 | E35: =SUM(E36:E37) -> 6117.4991 | F35: =SUM(F36:F37) -> 6656.7587 | G35: =SUM(G36:G37) -> 8178.3106 | H35: =SUM(H36:H37) -> 8592.8957 | I35: =SUM(I36:I37) -> 10166.029 | J35: =SUM(J36:J37) -> 47976.442
A36: Servicios Básicos | B36: =+'8 Mantenimiento'!E3 -> 1120.0508 | C36: =+'8 Mantenimiento'!F3 -> 3292.3237 | D36: =+'8 Mantenimiento'!G3 -> 4092.5743 | E36: =+'8 Mantenimiento'!H3 -> 6057.4991 | F36: =+'8 Mantenimiento'!I3 -> 6596.7587 | G36: =+'8 Mantenimiento'!J3 -> 8118.3106 | H36: =+'8 Mantenimiento'!K3 -> 8532.8957 | I36: =+'8 Mantenimiento'!L3 -> 10106.029 | J36: =SUM(B36:I36) -> 47916.442
A37: Amortizacion | D37: =+'Amortización '!D5 -> 120 | E37: =+'Amortización '!E5 -> 60 | F37: =+'Amortización '!F5 -> 60 | G37: =+'Amortización '!G5 -> 60 | H37: =+'Amortización '!H5 -> 60 | I37: =+'Amortización '!I5 -> 60 | J37: =+'Amortización '!J5 -> 60
A38: GASTO FINANCIERO | B38: =SUM(B39) -> 0 | C38: =SUM(C39) -> 0 | D38: =SUM(D39) -> 0 | E38: =SUM(E39) -> 0 | F38: =SUM(F39) -> 0 | G38: =SUM(G39) -> 0 | H38: =SUM(H39) -> 0 | I38: =SUM(I39) -> 0 | J38: =SUM(J39) -> 0
A39: Interes | B39: =+$E$1/'Planta central'!$B$2*'Planta central'!M2*6 -> 0 | C39: =+$E$1/'Planta central'!$B$2*'Planta central'!N2*6 -> 0 | D39: =+$E$1/'Planta central'!$B$2*'Planta central'!O2*6 -> 0 | E39: =+$E$1/'Planta central'!$B$2*'Planta central'!P2*6 -> 0 | F39: =+$E$1/'Planta central'!$B$2*'Planta central'!Q2*6 -> 0 | G39: =+$E$1/'Planta central'!$B$2*'Planta central'!R2*6 -> 0 | H39: =+$E$1/'Planta central'!$B$2*'Planta central'!S2*6 -> 0 | I39: =+$E$1/'Planta central'!$B$2*'Planta central'!T2*6 -> 0 | J39: 0
A40: TOTAL COSTOS Y GASTOS | B40: =+B5+B21+B33+B35+B38 -> 60925.6 | C40: =+C5+C21+C33+C35+C38 -> 148905.86 | D40: =+D5+D21+D33+D35+D38 -> 187543.75 | E40: =+E5+E21+E33+E35+E38 -> 270997.69 | F40: =+F5+F21+F33+F35+F38 -> 303241.58 | G40: =+G5+G21+G33+G35+G38 -> 385789.07 | H40: =+H5+H21+H33+H35+H38 -> 416630 | I40: =+I5+I21+I33+I35+I38 -> 492713.6 | J40: =SUM(B40:I40)+'5 Demanda'!J34 -> 2525907.4
A43: PROYECCION DE COSTOS Y GASTOS
A44: CONCEPTO | B44: PONDERACIÓN
B45: =+B4 -> 2023 | C45: =+C4 -> 2023 | D45: =+D4 -> 2024 | E45: =+E4 -> 2024 | F45: =+F4 -> 2025 | G45: =+G4 -> 2025 | H45: =+H4 -> 2026 | I45: =+I4 -> 2026
A46: =+A5 -> COSTOS POR SERVICIOS | B46: =(B5/(B$40)) -> 0.44934815 | C46: =(C5/(C$40)) -> 0.59666758 | D46: =(D5/(D$40)) -> 0.63314139 | E46: =(E5/(E$40)) -> 0.67493455 | F46: =(F5/(F$40)) -> 0.69312598 | G46: =(G5/(G$40)) -> 0.71554462 | H46: =(H5/(H$40)) -> 0.72800251 | I46: =(I5/(I$40)) -> 0.74130835 | J46: =(J5/(J$40)) -> 0.62261421
A47: =+A6 -> Mantenimiento Edificio | B47: =(B6/(B$40)) -> 0.051422823 | C47: =(C6/(C$40)) -> 0.061845592 | D47: =(D6/(D$40)) -> 0.061039643 | E47: =(E6/(E$40)) -> 0.062523859 | F47: =(F6/(F$40)) -> 0.060849897 | G47: =(G6/(G$40)) -> 0.058861827 | H47: =(H6/(H$40)) -> 0.057288032 | I47: =(I6/(I$40)) -> 0.057372528 | J47: =(J6/(J$40)) -> 0.053062186
A48: =+A7 -> Capacitación Docente | B48: =(B7/(B$40)) -> 0.0029384241 | C48: =(C7/(C$40)) -> 0.0040648796 | D48: =(D7/(D$40)) -> 0.0043032405 | E48: =(E7/(E$40)) -> 0.0046918576 | F48: =(F7/(F$40)) -> 0.0049147096 | G48: =(G7/(G$40)) -> 0.0050104357 | H48: =(H7/(H$40)) -> 0.0051212404 | I48: =(I7/(I$40)) -> 0.0050841621 | J48: =(J7/(J$40)) -> 0.0043251198
A49: =+A8 -> Internacionalización | B49: =(B8/(B$40)) -> 0.0018992074 | C49: =(C8/(C$40)) -> 0.0022841533 | D49: =(D8/(D$40)) -> 0.002254387 | E49: =(E8/(E$40)) -> 0.0023422254 | F49: =(F8/(F$40)) -> 0.0022795166 | G49: =(G8/(G$40)) -> 0.0022780278 | H49: =(H8/(H$40)) -> 0.0022171199 | I49: =(I8/(I$40)) -> 0.0022503653 | J49: =(J8/(J$40)) -> 0.0020253928
A50: =+A9 -> Insumos Prácticas y Laboratorios | B50: =(B9/(B$40)) -> 0 | C50: =(C9/(C$40)) -> 0 | D50: =(D9/(D$40)) -> 0 | E50: =(E9/(E$40)) -> 0 | F50: =(F9/(F$40)) -> 0 | G50: =(G9/(G$40)) -> 0 | H50: =(H9/(H$40)) -> 0 | I50: =(I9/(I$40)) -> 0 | J50: =(J9/(J$40)) -> 0
A51: =+A10 -> Tiempo Completo PhD | B51: =(B10/(B$40)) -> 0.092537542 | C51: =(C10/(C$40)) -> 0.12793985 | D51: =(D10/(D$40)) -> 0.13544213 | E51: =(E10/(E$40)) -> 0.14503357 | F51: =(F10/(F$40)) -> 0.15192232 | G51: =(G10/(G$40)) -> 0.15790137 | H51: =(H10/(H$40)) -> 0.16139332 | I51: =(I10/(I$40)) -> 0.16028101 | J51: =(J10/(J$40)) -> 0.13563194
A52: =+A11 -> Tiempo Completo Mgs. | B52: =(B11/(B$40)) -> 0.14945966 | C52: =(C11/(C$40)) -> 0.20667533 | D52: =(D11/(D$40)) -> 0.21879458 | E52: =(E11/(E$40)) -> 0.2343305 | F52: =(F11/(F$40)) -> 0.24546064 | G52: =(G11/(G$40)) -> 0.25514287 | H52: =(H11/(H$40)) -> 0.26078529 | I52: =(I11/(I$40)) -> 0.25903765 | J52: =(J11/(J$40)) -> 0.219155
A53: =+A12 -> Medio Tiempo | B53: =(B12/(B$40)) -> 0 | C53: =(C12/(C$40)) -> 0 | D53: =(D12/(D$40)) -> 0 | E53: =(E12/(E$40)) -> 0 | F53: =(F12/(F$40)) -> 0 | G53: =(G12/(G$40)) -> 0 | H53: =(H12/(H$40)) -> 0 | I53: =(I12/(I$40)) -> 0 | J53: =(J12/(J$40)) -> 0
A54: =+A13 -> Tiempo Parcial | B54: =(B13/(B$40)) -> 0.0099845521 | C54: =(C13/(C$40)) -> 0.013827439 | D54: =(D13/(D$40)) -> 0.014638268 | E54: =(E13/(E$40)) -> 0.015701283 | F54: =(F13/(F$40)) -> 0.016447056 | G54: =(G13/(G$40)) -> 0.017108165 | H54: =(H13/(H$40)) -> 0.017486508 | I54: =(I13/(I$40)) -> 0.017397362 | J54: =(J13/(J$40)) -> 0.014692749
A55: =+A14 -> Ocasional Tipo 2 (Técnico Docente) | B55: =(B14/(B$40)) -> 0.046921569 | C55: =(C14/(C$40)) -> 0.062298759 | D55: =(D14/(D$40)) -> 0.068012899 | E55: =(E14/(E$40)) -> 0.076002985 | F55: =(F14/(F$40)) -> 0.082476147 | G55: =(G14/(G$40)) -> 0.093006301 | H55: =(H14/(H$40)) -> 0.10144825 | I55: =(I14/(I$40)) -> 0.11829974 | J55: =(J14/(J$40)) -> 0.0819241
A56: =+A15 -> Costo del Seguro Estudiantil | B56: =(B15/(B$40)) -> 0.015117205 | C56: =(C15/(C$40)) -> 0.018181275 | D56: =(D15/(D$40)) -> 0.017944343 | E56: =(E15/(E$40)) -> 0.018643514 | F56: =(F15/(F$40)) -> 0.018144368 | G56: =(G15/(G$40)) -> 0.018132518 | H56: =(H15/(H$40)) -> 0.017647706 | I56: =(I15/(I$40)) -> 0.017912331 | J56: =(J15/(J$40)) -> 0.016121608
A57: =+A16 -> Becas Institucionales 10 % estudiantes | B57: =(B16/(B$40)) -> 0 | C57: =(C16/(C$40)) -> 0 | D57: =(D16/(D$40)) -> 0 | E57: =(E16/(E$40)) -> 0 | F57: =(F16/(F$40)) -> 0 | G57: =(G16/(G$40)) -> 0 | H57: =(H16/(H$40)) -> 0 | I57: =(I16/(I$40)) -> 0 | J57: =(J16/(J$40)) -> 0
... A60: =+A19 -> Materiales y Suministros | B60: =(B19/(B$40)) -> 0.010701364 | C60: =(C19/(C$40)) -> 0.011217349 | D60: =(D19/(D$40)) -> 0.010951501 | E60: =(E19/(E$40)) -> 0.011031793 | F60: =(F19/(F$40)) -> 0.010262202 | G60: =(G19/(G$40)) -> 0.0098848707 | H60: =(H19/(H$40)) -> 0.0096439266 | I60: =(I19/(I$40)) -> 0.0096332195 | J60: =(J19/(J$40)) -> 0.009127635
A61: =+A20 -> Depreciación | B61: =(B20/(B$40)) -> 0 | C61: =(C20/(C$40)) -> 0.0018538452 | D61: =(D20/(D$40)) -> 0.01440826 | E61: =(C20/(E$40)) -> 0.0010186375 | F61: =(D20/(F$40)) -> 0.0089109778 | G61: =(E20/(G$40)) -> 0.013339264 | H61: =(F20/(H$40)) -> 0.012386975 | I61: =(G20/(I$40)) -> 0.010547418 | J61: =(J20/(J$40)) -> 0.011375303
A62: =+A21 -> GASTOS DE ADMINISTRACIÓN | B62: =(B21/(B$40)) -> 0.53082572 | C62: =(C21/(C$40)) -> 0.37948779 | D62: =(D21/(D$40)) -> 0.34268485 | E62: =(E21/(E$40)) -> 0.30071283 | F62: =(F21/(F$40)) -> 0.28319101 | G62: =(G21/(G$40)) -> 0.26152658 | H62: =(H21/(H$40)) -> 0.2496891 | I62: =(I21/(I$40)) -> 0.23635004 | J62: =(J21/(J$40)) -> 0.25411064
A63: =+A22 -> Administración Central | B63: =(B22/(B$40)) -> 0.08052136 | C63: =(C22/(C$40)) -> 0.095476725 | D63: =(D22/(D$40)) -> 0.094232507 | E63: =(E22/(E$40)) -> 0.09476732 | F63: =(F22/(F$40)) -> 0.092230098 | G63: =(G22/(G$40)) -> 0.090942141 | H63: =(H22/(H$40)) -> 0.08851061 | I63: =(I22/(I$40)) -> 0.088641158 | J63: =(J22/(J$40)) -> 0.081586786
A64: =+A23 -> Decano | B64: =(B23/(B$40)) -> 0.048341465 | C64: =(C23/(C$40)) -> 0.049206924 | D64: =(D23/(D$40)) -> 0.045954716 | E64: =(E23/(E$40)) -> 0.041692585 | F64: =(F23/(F$40)) -> 0.039332347 | G64: =(G23/(G$40)) -> 0.036580493 | H64: =(H23/(H$40)) -> 0.034838331 | I64: =(I23/(I$40)) -> 0.032706185 | J64: =(J23/(J$40)) -> 0.03438708
A65: =+A24 -> Subdecano | B65: =(B24/(B$40)) -> 0.035962901 | C65: =(C24/(C$40)) -> 0.036609688 | D65: =(D24/(D$40)) -> 0.034190064 | E65: =(E24/(E$40)) -> 0.031021577 | F65: =(F24/(F$40)) -> 0.02926543 | G65: =(G24/(G$40)) -> 0.027218961 | H65: =(H24/(H$40)) -> 0.025922646 | I65: =(I24/(I$40)) -> 0.024338273 | J65: =(J24/(J$40)) -> 0.025586287
A66: =+A25 -> Director de Carrera | B66: =(B25/(B$40)) -> 0.28922752 | C66: =(C25/(C$40)) -> 0.11997383 | D66: =(D25/(D$40)) -> 0.095256742 | E66: =(E25/(E$40)) -> 0.066892711 | F66: =(F25/(F$40)) -> 0.059779961 | G66: =(G25/(G$40)) -> 0.0485538 | H66: =(H25/(H$40)) -> 0.044959618 | I66: =(I25/(I$40)) -> 0.038547448 | J66: =(J25/(J$40)) -> 0.057825721
A67: =+A26 -> Secretario | B67: =(B26/(B$40)) -> 0.012691201 | C67: =(C26/(C$40)) -> 0.012926886 | D67: =(D26/(D$40)) -> 0.012072516 | E67: =(E26/(E$40)) -> 0.010960081 | F67: =(F26/(F$40)) -> 0.010339626 | G67: =(G26/(G$40)) -> 0.0096192805 | H67: =(H26/(H$40)) -> 0.009161158 | I67: =(I26/(I$40)) -> 0.0086065998 | J67: =(J26/(J$40)) -> 0.0090407945
A68: =+A27 -> Auxiliar de Secretaria | B68: =(B27/(B$40)) -> 0.010834417 | C68: =(C27/(C$40)) -> 0.011037301 | D68: =(D27/(D$40)) -> 0.010307818 | E68: =(E27/(E$40)) -> 0.0093594299 | F68: =(F27/(F$40)) -> 0.0088295879 | G68: =(G27/(G$40)) -> 0.0082150506 | H68: =(H27/(H$40)) -> 0.0078238052 | I68: =(I27/(I$40)) -> 0.0073514131 | J68: =(J27/(J$40)) -> 0.0077206755
A69: =+A28 -> Coordinador | B69: =(B28/(B$40)) -> 0.011453345 | C69: =(C28/(C$40)) -> 0.011667163 | D69: =(D28/(D$40)) -> 0.010896051 | E69: =(E28/(E$40)) -> 0.0098929803 | F69: =(F28/(F$40)) -> 0.0093329338 | G69: =(G28/(G$40)) -> 0.0086831273 | H69: =(H28/(H$40)) -> 0.0082695895 | I69: =(I28/(I$40)) -> 0.0077698087 | J69: =(J28/(J$40)) -> 0.0081607151
A70: =+A29 -> Bienestar Estudiantil | B70: =(B29/(B$40)) -> 0.011453345 | C70: =(C29/(C$40)) -> 0.011667163 | D70: =(D29/(D$40)) -> 0.010896051 | E70: =(E29/(E$40)) -> 0.0098929803 | F70: =(F29/(F$40)) -> 0.0093329338 | G70: =(G29/(G$40)) -> 0.0086831273 | H70: =(H29/(H$40)) -> 0.0082695895 | I70: =(I29/(I$40)) -> 0.0077698087 | J70: =(J29/(J$40)) -> 0.0081607151
A71: =+A30 -> Bibliotecario | B71: =(B30/(B$40)) -> 0.010215488 | C71: =(C30/(C$40)) -> 0.010407439 | D71: =(D30/(D$40)) -> 0.0097195857 | E71: =(E30/(E$40)) -> 0.0088258795 | F71: =(F30/(F$40)) -> 0.0083262421 | G71: =(G30/(G$40)) -> 0.007746974 | H71: =(H30/(H$40)) -> 0.0073780209 | I71: =(I30/(I$40)) -> 0.0069330176 | J71: =(J30/(J$40)) -> 0.0072806358
A72: =+A31 -> Auxiliar de Servicio | B72: =(B31/(B$40)) -> 0.011765982 | C72: =(C31/(C$40)) -> 0.011996814 | D72: =(D31/(D$40)) -> 0.011203914 | E72: =(E31/(E$40)) -> 0.010182053 | F72: =(F31/(F$40)) -> 0.0096056421 | G72: =(G31/(G$40)) -> 0.0089408755 | H72: =(H31/(H$40)) -> 0.0085150623 | I72: =(I31/(I$40)) -> 0.0080084972 | J72: =(J31/(J$40)) -> 0.008400716
A73: =+A32 -> Guardia | B73: =(B32/(B$40)) -> 0.0083587038 | C73: =(C32/(C$40)) -> 0.0085178538 | D73: =(D32/(D$40)) -> 0.0079548878 | E73: =(E32/(E$40)) -> 0.0072252283 | F73: =(F32/(F$40)) -> 0.0068162045 | G73: =(G32/(G$40)) -> 0.0063427442 | H73: =(H32/(H$40)) -> 0.0060406682 | I73: =(I32/(I$40)) -> 0.0056778309 | J73: =(J32/(J$40)) -> 0.0059605167
... A80: =+A39 -> Interes | B80: =(B39/(B$40)) -> 0 | C80: =(C39/(C$40)) -> 0 | D80: =(D39/(D$40)) -> 0 | E80: =(E39/(E$40)) -> 0 | F80: =(F39/(F$40)) -> 0 | G80: =(G39/(G$40)) -> 0 | H80: =(H39/(H$40)) -> 0 | I80: =(I39/(I$40)) -> 0 | J80: =(J39/(J$40)) -> 0
A81: =+A40 -> TOTAL COSTOS Y GASTOS | B81: =SUM(B47:B61)+SUM(B63:B73)+SUM(B75)+SUM(B77:B78)+B80 -> 1 | C81: =SUM(C47:C61)+SUM(C63:C73)+SUM(C75)+SUM(C77:C78)+C80 -> 1 | D81: =SUM(D47:D61)+SUM(D63:D73)+SUM(D75)+SUM(D77:D78)+D80 -> 1 | E81: =SUM(E47:E61)+SUM(E63:E73)+SUM(E75)+SUM(E77:E78)+E80 -> 0.98202902 | F81: =SUM(F47:F61)+SUM(F63:F73)+SUM(F75)+SUM(F77:F78)+F80 -> 0.99189225 | G81: =SUM(G47:G61)+SUM(G63:G73)+SUM(G75)+SUM(G77:G78)+G80 -> 0.99986854 | H81: =SUM(H47:H61)+SUM(H63:H73)+SUM(H75)+SUM(H77:H78)+H80 -> 0.99989748 | I81: =SUM(I47:I61)+SUM(I63:I73)+SUM(I75)+SUM(I77:I78)+I80 -> 1.0003032 | J81: =(J40/(J$40)) -> 1
A84: PROYECCION DE COSTOS Y GASTOS
A85: CONCEPTO | B85: DESCONTADO PRESUPUESTOS ASIGNADO POR EL GOBIERNO PARA BECAS Y AYUDAS
B86: =+B45 -> 2023 | C86: =+C45 -> 2023 | D86: =+D45 -> 2024 | E86: =+E45 -> 2024 | F86: =+F45 -> 2025 | G86: =+G45 -> 2025 | H86: =+H45 -> 2026 | I86: =+I45 -> 2026 | ... K86: =+K45 -> 0
A87: =+A46 -> COSTOS POR SERVICIOS | B87: =SUM(B88:B95) -> #REF! | C87: =SUM(C88:C95) -> #REF! | D87: =SUM(D88:D95) -> 53716.439 | E87: =SUM(E88:E95) -> 78864.908 | F87: =SUM(F88:F95) -> 88497.108 | G87: =SUM(G88:G95) -> 113526.88 | H87: =SUM(H88:H95) -> 119434.23 | I87: =SUM(I88:I95) -> 141028.54 | ... K87: =SUM(K88:K95) -> #REF!
A88: =+A47 -> Mantenimiento Edificio | B88: ='10 Costos y Gastos'!B6-(SUM('9 Inv. Vin. Becas'!B13:B14)*'10 Costos y Gastos'!B47) -> 3132.9663 | C88: ='10 Costos y Gastos'!C6-(SUM('9 Inv. Vin. Becas'!$C$13:$C$14)*'10 Costos y Gastos'!C47) -> 9209.1709 | D88: ='10 Costos y Gastos'!D6-(SUM('9 Inv. Vin. Becas'!$D$13:$D$14)*'10 Costos y Gastos'!D47) -> 11447.603 | E88: ='10 Costos y Gastos'!E6-(SUM('9 Inv. Vin. Becas'!$E$13:$E$14)*'10 Costos y Gastos'!E47) -> 16943.821 | F88: ='10 Costos y Gastos'!F6-(SUM('9 Inv. Vin. Becas'!$F$13:$F$14)*'10 Costos y Gastos'!F47) -> 18452.219 | G88: ='10 Costos y Gastos'!G6-(SUM('9 Inv. Vin. Becas'!$G$13:$G$14)*'10 Costos y Gastos'!G47) -> 22708.25 | H88: ='10 Costos y Gastos'!H6-(SUM('9 Inv. Vin. Becas'!$H$13:$H$14)*'10 Costos y Gastos'!H47) -> 23867.913 | I88: ='10 Costos y Gastos'!I6-(SUM('9 Inv. Vin. Becas'!$I$13:$I$14)*'10 Costos y Gastos'!I47) -> 28268.225 | J88: ='10 Costos y Gastos'!J6-(SUM('9 Inv. Vin. Becas'!#REF!)*'10 Costos y Gastos'!J47) -> #REF! | K88: ='10 Costos y Gastos'!K6-(SUM('9 Inv. Vin. Becas'!#REF!)*'10 Costos y Gastos'!K47) -> #REF!
A89: =+A53 -> Medio Tiempo | B89: ='10 Costos y Gastos'!B12-(SUM('9 Inv. Vin. Becas'!$B$13:$B$14)*'10 Costos y Gastos'!B53) -> 0 | C89: ='10 Costos y Gastos'!C12-(SUM('9 Inv. Vin. Becas'!$C$13:$C$14)*'10 Costos y Gastos'!C53) -> 0 | D89: ='10 Costos y Gastos'!D12-(SUM('9 Inv. Vin. Becas'!$D$13:$D$14)*'10 Costos y Gastos'!D53) -> 0 | E89: ='10 Costos y Gastos'!E12-(SUM('9 Inv. Vin. Becas'!$E$13:$E$14)*'10 Costos y Gastos'!E53) -> 0 | F89: ='10 Costos y Gastos'!F12-(SUM('9 Inv. Vin. Becas'!$F$13:$F$14)*'10 Costos y Gastos'!F53) -> 0 | G89: ='10 Costos y Gastos'!G12-(SUM('9 Inv. Vin. Becas'!$G$13:$G$14)*'10 Costos y Gastos'!G53) -> 0 | H89: ='10 Costos y Gastos'!H12-(SUM('9 Inv. Vin. Becas'!$H$13:$H$14)*'10 Costos y Gastos'!H53) -> 0 | I89: ='10 Costos y Gastos'!I12-(SUM('9 Inv. Vin. Becas'!$I$13:$I$14)*'10 Costos y Gastos'!I53) -> 0 | J89: ='10 Costos y Gastos'!J12-(SUM('9 Inv. Vin. Becas'!#REF!)*'10 Costos y Gastos'!J53) -> #REF! | K89: ='10 Costos y Gastos'!K12-(SUM('9 Inv. Vin. Becas'!#REF!)*'10 Costos y Gastos'!K53) -> #REF!
A90: =+A54 -> Tiempo Parcial | B90: ='10 Costos y Gastos'!B13-(SUM('9 Inv. Vin. Becas'!$B$13:$B$14)*'10 Costos y Gastos'!B54) -> 608.31483 | C90: ='10 Costos y Gastos'!C13-(SUM('9 Inv. Vin. Becas'!$C$13:$C$14)*'10 Costos y Gastos'!C54) -> 2058.9867 | D90: ='10 Costos y Gastos'!D13-(SUM('9 Inv. Vin. Becas'!$D$13:$D$14)*'10 Costos y Gastos'!D54) -> 2745.3156 | E90: ='10 Costos y Gastos'!E13-(SUM('9 Inv. Vin. Becas'!$E$13:$E$14)*'10 Costos y Gastos'!E54) -> 4255.0113 | F90: ='10 Costos y Gastos'!F13-(SUM('9 Inv. Vin. Becas'!$F$13:$F$14)*'10 Costos y Gastos'!F54) -> 4987.4313 | G90: ='10 Costos y Gastos'!G13-(SUM('9 Inv. Vin. Becas'!$G$13:$G$14)*'10 Costos y Gastos'!G54) -> 6600.1431 | H90: ='10 Costos y Gastos'!H13-(SUM('9 Inv. Vin. Becas'!$H$13:$H$14)*'10 Costos y Gastos'!H54) -> 7285.4038 | I90: ='10 Costos y Gastos'!I13-(SUM('9 Inv. Vin. Becas'!$I$13:$I$14)*'10 Costos y Gastos'!I54) -> 8571.9171 | J90: ='10 Costos y Gastos'!J13-(SUM('9 Inv. Vin. Becas'!#REF!)*'10 Costos y Gastos'!J54) -> #REF! | K90: ='10 Costos y Gastos'!K13-(SUM('9 Inv. Vin. Becas'!#REF!)*'10 Costos y Gastos'!K54) -> #REF!
A91: =+A57 -> Becas Institucionales 10 % estudiantes | B91: =+'5 Demanda'!B34 -> 6169.387 | C91: =+'5 Demanda'!C34 -> 17878.884 | D91: =+'5 Demanda'!D34 -> 22224.625 | E91: =+'5 Demanda'!E34 -> 32296.487 | F91: =+'5 Demanda'!F34 -> 35171.632 | G91: =+'5 Demanda'!G34 -> 44121.086 | H91: =+'5 Demanda'!H34 -> 46374.258 | I91: =+'5 Demanda'!I34 -> 54923.863 | J91: =+'5 Demanda'!#REF! -> #REF! | K91: =+'5 Demanda'!#REF! -> #REF!
A92: =+A58 -> Investigación 5% | B92: =+'9 Inv. Vin. Becas'!B8 -> 3305.7365 | C92: =+'9 Inv. Vin. Becas'!C8 -> 10220.036 | D92: =+'9 Inv. Vin. Becas'!D8 -> 12704.175 | E92: =+'9 Inv. Vin. Becas'!E8 -> 18419.958 | F92: =+'9 Inv. Vin. Becas'!F8 -> 20059.767 | G92: =+'9 Inv. Vin. Becas'!G8 -> 25948.15 | H92: =+'9 Inv. Vin. Becas'!H8 -> 27273.267 | I92: =+'9 Inv. Vin. Becas'!I8 -> 32767.717 | J92: =+'9 Inv. Vin. Becas'!#REF! -> #REF! | K92: =+'9 Inv. Vin. Becas'!#REF! -> #REF!
A93: =+A59 -> Vinculación 1% | B93: =+'9 Inv. Vin. Becas'!B9 -> 661.14731 | C93: =+'9 Inv. Vin. Becas'!C9 -> 2044.0072 | D93: =+'9 Inv. Vin. Becas'!D9 -> 2540.835 | E93: =+'9 Inv. Vin. Becas'!E9 -> 3683.9916 | F93: =+'9 Inv. Vin. Becas'!F9 -> 4011.9533 | G93: =+'9 Inv. Vin. Becas'!G9 -> 5189.6299 | H93: =+'9 Inv. Vin. Becas'!H9 -> 5454.6534 | I93: =+'9 Inv. Vin. Becas'!I9 -> 6553.5434 | J93: =+'9 Inv. Vin. Becas'!#REF! -> #REF! | K93: =+'9 Inv. Vin. Becas'!#REF! -> #REF!
A94: =+A60 -> Materiales y Suministros | B94: ='10 Costos y Gastos'!B19-(SUM('9 Inv. Vin. Becas'!$B$13:$B$14)*'10 Costos y Gastos'!B60) -> 651.987 | C94: ='10 Costos y Gastos'!C19-(SUM('9 Inv. Vin. Becas'!$C$13:$C$14)*'10 Costos y Gastos'!C60) -> 1670.329 | D94: ='10 Costos y Gastos'!D19-(SUM('9 Inv. Vin. Becas'!$D$13:$D$14)*'10 Costos y Gastos'!D60) -> 2053.8855 | E94: ='10 Costos y Gastos'!E19-(SUM('9 Inv. Vin. Becas'!$E$13:$E$14)*'10 Costos y Gastos'!E60) -> 2989.5903 | F94: ='10 Costos y Gastos'!F19-(SUM('9 Inv. Vin. Becas'!$F$13:$F$14)*'10 Costos y Gastos'!F60) -> 3111.9263 | G94: ='10 Costos y Gastos'!G19-(SUM('9 Inv. Vin. Becas'!$G$13:$G$14)*'10 Costos y Gastos'!G60) -> 3813.4751 | H94: ='10 Costos y Gastos'!H19-(SUM('9 Inv. Vin. Becas'!$H$13:$H$14)*'10 Costos y Gastos'!H60) -> 4017.9491 | I94: ='10 Costos y Gastos'!I19-(SUM('9 Inv. Vin. Becas'!$I$13:$I$14)*'10 Costos y Gastos'!I60) -> 4746.4183 | J94: ='10 Costos y Gastos'!J19-(SUM('9 Inv. Vin. Becas'!#REF!)*'10 Costos y Gastos'!J60) -> #REF! | K94: ='10 Costos y Gastos'!K19-(SUM('9 Inv. Vin. Becas'!#REF!)*'10 Costos y Gastos'!K60) -> #REF!
